Workbook
Name 內部: 拆單用!$B$3:$B$39
Name 內部五金: 拆單用!$H$3:$H$7
Name 外部: 拆單用!$C$3:$C$58
Name 外部五金: 拆單用!$I$3:$I$80
Name 衣廚五金: 拆單用!$L$3:$L$27
Name 床架_臥塌: 拆單用!$G$3:$G$11
Name 其它五金: 拆單用!$K$3:$K$33
Name 和旺: 資料庫!$AJ$2:$AV$2
Name 抽屜: 拆單用!$D$3:$D$27
Name 抽屜五金: 拆單用!$J$3:$J$67
Name 抽盤: 拆單用!$F$3:$F$8
Name 抽盤_不見軌道: 拆單用!$F$3:$F$8
Name 抽箱: 拆單用!$E$3:$E$12
Name 科定: 資料庫!$AJ$3:$AV$3
Name 桶身: 拆單用!$A$3:$A$38

Sheet 客戶資料
A3: 1 | C3: 2 | D3: 3 | E3: 4 | F3: 5 | G3: 6 | H3: 7 | I3: 8 | J3: 9 | K3: 10 | L3: 11 | M3: 12 | N3: 13 | O3: 14 | P3: 15
Q4: 有無附上名片 | R4: 目錄盒
R5: 索取日期 | S5: 數量
A6: 設計師/業務 | B6: 客戶編號 | C6: 聯絡電話 | D6: 公司名稱 | E6: 統編 | F6: 公司地址 | G6: 公司電話 | H6: 切口金額 | I6: 切口餘額 | J6: 板材折數 | K6: 安裝折數 | O6: 登入日期 | P6: 客戶編號
B7: 員工
A8: 和旺系統櫃 | B8: AA0A000 | E8: 90019206 | F8: 新北市樹林區樹新路183巷13號1樓 | J8: 0 | O8: 44932 | P8: =#REF! -> #REF!
A9: 吳冠裕(冠鈺工程行) | B9: AA0B001 | C9: 0921122053 | D9: 冠鈺工程行 | E9: 85178554 | F9: 新北市樹林區樹新路183巷13號1樓 | J9: 0.41 | K9: 0.2 | O9: 44932 | P9: =#REF! -> #REF! | R9: 44961 | S9: 1
A10: 劉軒魁 | B10: AA0B002 | C10: 0953085789 | F10: 新北市新莊區民本街53巷27號2樓 | J10: 0.41 | K10: =K9 -> 0.2 | O10: 44932 | P10: =#REF! -> #REF!
A11: 周呈勳(泰丞水電) | B11: AA0B003 | C11: 0958377085 | J11: 0.41 | K11: =K10 -> 0.2 | O11: 44932 | P11: =#REF! -> #REF! | R11: 112/2/3 | S11: 3
A12: 李嘉欣(尚鋐電器) | B12: AA0B004 | C12: 0922338900 | D12: 尚鋐電氣行 | E12: 31709514 | F12: 新北市新莊區青山路一段8號之11樓 | J12: 0.41 | K12: =K11 -> 0.2 | O12: 44932 | P12: =#REF! -> #REF!
A13: 張家祥 | B13: AA0C011 | J13: 0.41 | K13: =K12 -> 0.2 | O13: 44932 | P13: =#REF! -> #REF!
A14: 吳心彤 | B14: AA0D001 | C14: 0928220353 | O14: 44932 | P14: =#REF! -> #REF!
A15: 陳昱廷 | B15: AA0D002 | P15: =#REF! -> #REF!
B16: AA0D003 | P16: =#REF! -> #REF!
P17: =#REF! -> #REF!
P18: =#REF! -> #REF!
P19: =#REF! -> #REF!
B21: 設計公司
A22: 柳震東(沐晨) | B22: BA0001 | C22: 0920199706 | D22: 沐晨室內裝修有限公司 | E22: 55769700 | F22: 台北市中山區八德路二段172號1樓 | J22: 0.6 | K22: 0.2 | O22: 44866 | P22: =#REF! -> #REF! | R22: 112/2/15 | S22: 1
A23: 秦怡婷(光漫) | B23: BA0002 | C23: 0987754669 | D23: 龍英室內裝修設計工程有限公司 | E23: 16398173 | F23: 台北市中山區民生東路一段87號6樓 | J23: 0.45 | K23: =K22 -> 0.2 | O23: 44939 | P23: =#REF! -> #REF! | R23: 112/3/12 | S23: 1
A24: 廖哲民拉斐爾) | B24: BA0003 | C24: 0955286630 | D24: 拉斐爾空間設計企業社 | E24: 41408777 | F24: 新北市板橋區金華街10巷48弄70號4樓 | J24: 0.41 | K24: =K23 -> 0.2 | O24: 44939 | P24: =#REF! -> #REF!
A25: 胡君維(和慕) | B25: BA0004 | C25: 0980260704 | D25: 和慕空間設計 | J25: 0.49 | K25: =K24 -> 0.2 | O25: 44958 | P25: =#REF! -> #REF! | R25: 112/2/15 | S25: 1
A26: 賴德修(山門) | B26: BA0005 | C26: 0903073307 | D26: 山門綠建材 | E26: 58336518 | F26: 宜蘭縣宜蘭市文化里民族路310號7樓 | J26: 0.49 | K26: =K25 -> 0.2 | O26: 44958 | P26: =#REF! -> #REF! | R26: 112/2/16 | S26: 1
A27: 彭思亮(豐達) | B27: BA0006 | C27: 0988598615 | D27: 豐達室內裝修設計有限公司 | E27: 80305291 | F27: 台北市民生東路五段85號2樓 | J27: 0.49 | K27: =K26 -> 0.2 | O27: 44977 | P27: =#REF! -> #REF! | R27: 112/2/20 | S27: 1
A28: 陳昭宇 | B28: BA0007 | J28: 0.49 | K28: =K27 -> 0.2 | O28: 44977 | P28: =#REF! -> #REF! | R28: 112/2/10 | S28: 1
A29: 張修睿 | B29: BA0008 | C29: 0954154359 | D29: 从彡設計 | F29: 台北市信義區基隆一段141號13樓之3 | J29: 0.49 | K29: =K28 -> 0.2 | O29: 44977 | P29: =#REF! -> #REF! | R29: 112/3/5 | S29: 1
A30: 溫培堯 | B30: BA0009 | C30: 0931657652 | D30: 川墨室內設計 | F30: 台中市 | J30: 0.49 | K30: =K29 -> 0.2 | O30: 44977 | P30: =#REF! -> #REF! | R30: 112/2/14 | S30: 1
A31: 胡逸軒 | B31: BA0010 | C31: 0925727388 | D31: 或設計有限公司 | E31: 66603930 | F31: 新北市汐止區新台五路一段86號15樓 | J31: 0.49 | K31: 0.2 | O31: 44998 | P31: =#REF! -> #REF! | R31: 112/3/26 | S31: 1
A32: 林采郁 | B32: BA0011 | C32: 0981127720 | D32: 菲朵空間設計 | F32: 新北市土城區立雲街5巷10號1樓 | J32: 0.49 | K32: 0.2 | O32: 45011 | P32: =#REF! -> #REF!
B33: BA0012 | P33: =#REF! -> #REF!
B34: BA0013 | P34: =#REF! -> #REF!
B35: BA0014 | P35: =#REF! -> #REF!
B36: BA0015 | P36: =#REF! -> #REF!
B37: BA0016 | P37: =#REF! -> #REF!
B38: BA0017 | P38: =#REF! -> #REF!
B39: BA0018 | P39: =#REF! -> #REF!
B40: BA0019 | P40: =#REF! -> #REF!
B41: BA0020 | P41: =#REF! -> #REF!
B42: BA0021 | P42: =#REF! -> #REF!
B43: BA0022 | P43: =#REF! -> #REF!
B45: 業務 | P45: =#REF! -> #REF!
A46: 賴德修 | B46: BB0001 | C46: 0903073307 | D46: 山門綠建材 | F46: 宜蘭縣 | J46: 0.41 | K46: 0.21 | O46: 44942 | P46: =#REF! -> #REF! | R46: 112/2/20 | S46: 1
A47: 莊家豪 | B47: BB0002 | D47: 正豐水電材料行 | F47: 新北市新莊區建國二路58號 | J47: 0.49 | K47: 0.2 | O47: 44977 | P47: =#REF! -> #REF! | R47: 112/2/20 | S47: 1
P48: =#REF! -> #REF!
P49: =#REF! -> #REF!
P50: =#REF! -> #REF!
P51: =#REF! -> #REF!
P52: =#REF! -> #REF!
P53: =#REF! -> #REF!
P54: =#REF! -> #REF!
P55: =#REF! -> #REF!
P56: =#REF! -> #REF!

Sheet 廠商資料
A1: 廠商名稱 | B1: 業務員 | C1: 公司資料
C2: 公司名稱 | D2: 統編 | E2: 登記地址 | F2: 工廠(店家)地址 | G2: 電話
A3: 李安
A4: 達思 | C4: 達思企業有限公司 | D4: 42574942 | E4: 桃園市龜山區復興街永樂巷36弄15號
A5: 積甲 | C5: 積甲系統生活空間有限公司 | D5: 50883560 | E5: 台北市士林區延平北路5段197巷9號1樓
A6: 九江 | C6: 九江五金行 | D6: 04568218 | E6: 台北市萬華區西寧南路233號1樓
A7: 昊川 | C7: 寧津縣昊川機械有限公司 | E7: 中華人民共合國山東省德州市寧津縣寧城街道辦事處八里堂村 | G7: +86 18553415459
A8: 嘉慷 | C8: 嘉慷五金行 | D8: 78186426 | E8: 新北市新莊區民安西路110號1樓 | G8: 02-22051026
A9: 建泰

Sheet 資料庫
A1: 櫃號 | B1: 櫃體 名稱 | C1: 產品名稱 | D1: 代號 | E1: 開板尺寸 | J1: 生產 數量 | K1: 板材 基材 | L1: 板材 廠商選項 | M1: 板材 廠商 | N1: 原廠 色號 | O1: 原廠 板材名稱 | P1: 和旺編碼 板材色號 | Q1: 色號 板名 | R1: 板材 廠商 | S1: 封邊條 廠商 | T1: 封邊條色號 | V1: 修補筆 廠商 | W1: 修補筆色號 | Z1: 標記 | AA1: 計價 單位 | AC1: 五金 配件 | AD1: 規格 | AE1: 門板 加工 | AF1: 規格 | AG1: 五金配 件牌價 | AH1: 門板加工 牌價 | AI1: 板材 牌價 | AJ1: 備註 | AK1: 特殊 加工 | AL1: 計價 單位 | AM1: 狀態 | AN1: 狀態代碼
E2: 長 | F2: 封邊 | G2: 寬 | H2: 封邊 | I2: 厚
N3: DC | O3: 雙色 | P3: DC | Q3: 雙色 | AM3: 新增 | AN3: A
A4: 1 | C4: 頂板 | F4: A | H4: A | I4: 4 | J4: 1 | K4: 木芯板 | L4: 百順 | M4: 百益 | N4: K101 | O4: 珍珠白發泡板 | P4: K101 | Q4: 珍珠白發泡板 | R4: 百益 | Z4: 背板溝 | AA4: 才 | AC4: w0 | AE4: 門片/抽頭斜把(限17mm板) | AF4: 公分 | AH4: 20 | AI4: 310 | AJ4: 需另加以上系列價格 | AL4: 個 | AM4: 補料 | AN4: B
A5: =A4+1 -> 2 | C5: 底板 | F5: AA | H5: AA | I5: 8 | J5: =J4+1 -> 2 | K5: 發泡板 | L5: 和旺 | O5: 發泡板 | P5: 9999 | Q5: 發泡板 | Z5: 背板溝 面開槽 | AA5: 片 | AC5: w1 | AE5: 門片/抽頭打型(限17mm板) | AF5: 才 | AH5: 540 | AI5: 310 | AJ5: 需另加以上系列價格 | AL5: 個 | AM5: 追加 | AN5: N
A6: =A5+1 -> 3 | C6: 左側板 | F6: AP | H6: AP | I6: 17 | J6: =J5+1 -> 3 | K6: 密迪板 | L6: 科定 | O6: 發泡板 | P6: Z1001 | Q6: 凡爾賽橡木 | Z6: 背板溝 側開槽 | AA6: 支 | AC6: w2 | AE6: 門片/抽頭Z把(限17mm板) | AF6: 公分 | AH6: 30 | AI6: 310 | AJ6: 需另加以上系列價格 | AL6: 個 | AM6: 外加工 | AN6: W
A7: =A6+1 -> 4 | C7: 右側板 | F7: PP | H7: PP | I7: 18 | J7: =J6+1 -> 4 | K7: PP皮板 | L7: 板橋木業 | M7: 百順 | N7: POLY | P7: BA0001 | Q7: 純白 | R7: 百順 | S7: 達思企業 | T7: SF9084C | U7: KM448C | V7: 達思企業 | W7: K37718 | Z7: 背板溝 兩向開槽 | AA7: 組 | AC7: w3 | AE7: 代挖埋入式把手 | AF7: 孔 | AH7: 60 | AI7: 310 | AJ7: 實價 | AL7: 個 | AM7: 外包 | AN7: O
A8: =A7+1 -> 5 | C8: 背板 | F8: P | H8: P | I8: 20 | J8: =J7+1 -> 5 | K8: 實木皮板 | L8: 一品 | M8: 李安 | N8: 臻木系列 | O8: 迎幸 | P8: V404-0 | Q8: 迎幸 | R8: 李安 | S8: 達思企業 | T8: SF9081C | V8: 達思企業 | W8: KMF278 | X8: JL3319 | Z8: 背板 | AA8: 米 | AC8: w4 | AI8: 300 | AL8: 個 | AM8: 修改 | AN8: F
A9: =A8+1 -> 6 | C9: 背拉桿 | I9: 23 | J9: =J8+1 -> 6 | M9: 李安 | N9: 臻木系列 | O9: 水洗灰橡 | P9: V404-1 | Q9: 水洗灰橡 | R9: 李安 | S9: 達思企業 | T9: AD1187C | U9: SF9083C | V9: 達思企業 | Z9: 背板溝 排孔 | AC9: Cabineo 12 | AI9: 300 | AL9: 組 | AM9: 重出 | AN9: R
A10: =A9+1 -> 7 | C10: 踢腳板 | I10: 34 | J10: =J9+1 -> 7 | M10: 李安 | N10: 臻木系列 | O10: 典藏胡桃 | P10: V404-2 | Q10: 典藏胡桃 | R10: 李安 | S10: 達思企業 | T10: HL83352 | V10: 達思企業 | Z10: 排孔 | AC10: Cabineo 8 | AE10: 另貼其它3mm木皮 | AF10: 才 | AI10: 300 | AL10: 組 | AM10: 外購 | AN10: P
A11: =A10+1 -> 8 | C11: 固隔 | I11: 40 | J11: =J10+1 -> 8 | M11: 李安 | O11: 莫蘭迪奶茶 | P11: V404-3 | Q11: 莫蘭迪奶茶 | R11: 李安 | S11: 達思企業 | T11: AD1185C | V11: 達思企業 | Z11: 背板溝 面開槽 排孔 | AC11: Clamex P-15 | AE11: 鋁框拉門 | AF11: 才 | AG11: 100 | AI11: 300 | AL11: 組
A12: =A11+1 -> 9 | C12: 固隔(退) | I12: 51 | J12: =J11+1 -> 9 | M12: 李安 | N12: 3301 | O12: 北美原橡 | P12: 3301 | Q12: 北美原橡 | R12: 李安 | S12: 達思企業 | T12: K37769C | V12: 達思企業 | Z12: 背板溝 側開槽 排孔 | AC12: Clamex P-14 | AG12: 100 | AI12: 300 | AL12: 組
A13: =A12+1 -> 10 | C13: 活隔 | J13: =J12+1 -> 10 | M13: 李安 | N13: 3302 | O13: 鋸齒凡爾賽 | P13: 3302 | Q13: 鋸齒凡爾賽 | R13: 李安 | S13: 達思企業 | T13: R5622C | V13: 達思企業 | Z13: 背板溝 兩向開槽 排孔 | AC13: Clamex P-10 | AG13: 100 | AI13: 300 | AL13: 組
A14: =A13+1 -> 11 | C14: 左門板 | J14: =J13+1 -> 11 | M14: 李安 | N14: 3304 | O14: 鋸齒棕橡 | P14: 3304 | Q14: 鋸齒棕橡 | R14: 李安 | S14: 達思企業 | T14: JM266C | V14: 達思企業 | W14: K37859 | Z14: 面開槽 | AC14: Clamex P-15/10 | AG14: 100 | AI14: 300 | AL14: 組
A15: =A14+1 -> 12 | C15: 右門板 | J15: =J14+1 -> 12 | M15: 李安 | N15: 3305 | O15: 鋸齒胡桃 | P15: 3305 | Q15: 鋸齒胡桃 | R15: 李安 | S15: 達思企業 | T15: L0727C | V15: 達思企業 | W15: K37854 | Z15: 面開槽 排孔 | AC15: Clamex P-14 Flexus 連接件 | AG15: 100 | AI15: 300 | AL15: 組
A16: =A15+1 -> 13 | C16: 門板 | J16: =J15+1 -> 13 | M16: 李安 | N16: V320-1 | O16: 水染白橡 | P16: V320-1 | Q16: 水染白橡 | R16: 李安 | S16: 達思企業 | T16: L3260WC | V16: 達思企業 | W16: L3260 | Z16: 側開槽 排孔 | AC16: Bisco P14 連接件 | AG16: 100 | AI16: 300 | AL16: 組
A17: =A16+1 -> 14 | C17: 中立板 | J17: =J16+1 -> 14 | M17: 李安 | N17: V320-2 | O17: 水洗粉橡 | P17: V320-2 | Q17: 水洗粉橡 | R17: 李安 | S17: 達思企業 | T17: K4757C | V17: 達思企業 | W17: L3575 | Z17: 側開槽 單邊排孔 | AC17: Bisco P10 連接件 | AI17: 300 | AL17: 組
A18: =A17+1 -> 15 | C18: 中立板(退) | J18: =J17+1 -> 15 | M18: 李安 | N18: V320-4 | O18: 水洗紅橡 | P18: V320-4 | Q18: 水洗紅橡 | R18: 李安 | S18: 達思企業 | T18: SF8975C | V18: 達思企業 | W18: K4005 | Z18: 側開槽 | AC18: Tenso P-14 卡扣式連接件 | AI18: 350 | AL18: 組
A19: =A18+1 -> 16 | C19: 抽頭 | J19: =J18+1 -> 16 | M19: 李安 | N19: V320-5 | O19: 水染胡桃 | P19: V320-5 | Q19: 水染胡桃 | R19: 李安 | S19: 達思企業 | T19: 75753C | V19: 達思企業 | W19: HB180 | Z19: 面、側開槽 | AC19: Tenso P-10 卡扣式連接件 | AI19: 420 | AJ19: =CONCATENATE(P30,Q30) -> V313-3檜木 | AK19: 270 | AL19: 組
A20: =A19+1 -> 17 | C20: 左抽牆 | J20: =J19+1 -> 17 | M20: 李安 | N20: V320-8 | O20: 京都栓木 | P20: V320-8 | Q20: 京都栓木 | R20: 李安 | S20: 達思企業 | T20: R4262C | U20: 75753C | V20: 達思企業 | W20: K31957 | Z20: 絞鏈孔 | AC20: Divario P-18 連接件 | AI20: 420 | AJ20: =CONCATENATE(P31,Q31) -> V313-2紅粉佳人 | AK20: 270 | AL20: 組
A21: =A20+1 -> 18 | C21: 右抽牆 | J21: =J20+1 -> 18 | M21: 李安 | N21: V3143 | O21: 摩卡橡木 | P21: V3143 | Q21: 摩卡橡木 | R21: 李安 | S21: 達思企業 | T21: SF9081C | V21: 達思企業 | W21: SF9930 | Z21: 絞鏈孔 下孔上升1公分 | AC21: 30公分三節式緩衝滑軌(非重型) | AD21: 30 | AG21: 1000 | AI21: 420 | AJ21: =CONCATENATE(P32,Q32) -> V313-1白橡 | AK21: 270 | AL21: 組
A22: =A21+1 -> 19 | C22: 前抽牆 | J22: =J21+1 -> 19 | M22: 李安 | N22: V3142 | O22: 黑桃 | P22: V3142 | Q22: 黑桃 | R22: 李安 | S22: 達思企業 | T22: JM1424C | V22: 達思企業 | W22: K306 | Z22: 絞鏈孔 下孔上升15公分 | AC22: 35公分三節式緩衝滑軌(非重型) | AD22: 35 | AG22: 1000 | AI22: 420 | AJ22: =CONCATENATE(P33,Q33) -> V313-0白木紋 | AK22: 270 | AL22: 組
A23: =A22+1 -> 20 | C23: 後抽牆 | J23: =J22+1 -> 20 | M23: 李安 | N23: V3141 | O23: 胡桃 | P23: V3141 | Q23: 胡桃 | R23: 李安 | S23: 達思企業 | T23: AD5033C | V23: 達思企業 | W23: K37769 | X23: K37854 | Y23: K306 | Z23: 絞鏈孔 外把手 | AC23: 40公分三節式緩衝滑軌(非重型) | AD23: 40 | AG23: 1000 | AI23: 420 | AJ23: =CONCATENATE(P43,Q43) -> P8716砂面淺灰 | AK23: 270 | AL23: 組
A24: =A23+1 -> 21 | C24: 抽底 | J24: =J23+1 -> 21 | M24: 李安 | N24: V313-9 | O24: 黑木紋 | P24: V313-9 | Q24: 黑木紋 | R24: 李安 | S24: 達思企業 | T24: AD1185C | V24: 達思企業 | W24: AD1185 | Z24: 絞鏈孔 嵌把手 | AC24: 45公分三節式緩衝滑軌(非重型) | AD24: 45 | AG24: 1000 | AI24: 420 | AJ24: =CONCATENATE(P46,Q46) -> P8719砂面銅灰 | AK24: 270 | AL24: 組
A25: =A24+1 -> 22 | C25: 上前拉桿 | J25: =J24+1 -> 22 | M25: 李安 | N25: V313-8 | O25: 灰銀狐 | P25: V313-8 | Q25: 灰銀狐 | R25: 李安 | S25: 達思企業 | T25: JM201H2C | V25: 達思企業 | W25: 952 | Z25: 絞鏈孔 打型 | AC25: 50公分三節式緩衝滑軌(非重型) | AD25: 50 | AG25: 1000 | AI25: 420 | AJ25: =CONCATENATE(P66,Q66) -> P8752鏽斑栗咖 | AK25: 270 | AL25: 組
A26: =A25+1 -> 23 | C26: 下前拉桿 | J26: =J25+1 -> 23 | M26: 李安 | N26: V313-7 | O26: 清水模 | P26: V313-7 | Q26: 清水模 | R26: 李安 | Z26: 挖\絞鏈孔 斜把 | AC26: 55公分三節式緩衝滑軌(非重型) | AD26: 55 | AG26: 1250 | AI26: 420 | AJ26: =CONCATENATE(P67,Q67) -> P8753卡其荔枝紋 | AK26: 290 | AL26: 組
A27: =A26+1 -> 24 | C27: 上後拉桿 | J27: =J26+1 -> 24 | M27: 李安 | N27: V313-6 | O27: 肯柚 | P27: V313-6 | Q27: 肯柚 | R27: 李安 | Z27: 打型 | AC27: 60公分三節式緩衝滑軌(非重型) | AD27: 60 | AG27: 1250 | AI27: 420 | AJ27: =CONCATENATE(P68,Q68) -> P8005膚感鈦銀 | AK27: 290 | AL27: 組
A28: =A27+1 -> 25 | C28: 下後拉桿 | J28: =J27+1 -> 25 | M28: 李安 | N28: V313-5 | O28: 鋸齒柚木 | P28: V313-5 | Q28: 鋸齒柚木 | R28: 李安 | Z28: 上斜把手 | AC28: 長調整腳(公頭) | AD28: 長 | AI28: 440 | AJ28: =CONCATENATE(P82,Q82) -> P8018膚感栗咖 | AK28: 290 | AL28: 組
A29: =A28+1 -> 26 | C29: 左側落板 | J29: =J28+1 -> 26 | M29: 李安 | N29: V313-4 | O29: 紫羅蘭 | P29: V313-4 | Q29: 紫羅蘭 | R29: 李安 | Z29: 絞鏈孔 上斜把手 | AC29: 中調整腳(公頭) | AD29: 中 | AI29: 440 | AJ29: =CONCATENATE(P83,Q83) -> P8019膚感墨黑 | AL29: 組
A30: =A29+1 -> 27 | C30: 右側落板 | J30: =J29+1 -> 27 | M30: 李安 | N30: V313-3 | O30: 檜木 | P30: V313-3 | Q30: 檜木 | R30: 李安 | Z30: 下斜把手 | AC30: 短調整腳(公頭) | AD30: 短 | AG30: 50 | AI30: 440 | AJ30: =CONCATENATE(P84,Q84) -> P8020膚感灰綠 | AL30: 組
A31: =A30+1 -> 28 | C31: 外蓋背板 | J31: =J30+1 -> 28 | M31: 李安 | N31: V313-2 | O31: 紅粉佳人 | P31: V313-2 | Q31: 紅粉佳人 | R31: 李安 | Z31: 絞鏈孔 下斜把手 | AC31: 調整腳(母頭) | AJ31: =CONCATENATE(P85,Q85) -> P8021膚感黃褐
A32: =A31+1 -> 29 | C32: 內柱背板 | J32: =J31+1 -> 29 | M32: 李安 | N32: V313-1 | O32: 白橡 | P32: V313-1 | Q32: 白橡 | R32: 李安 | Z32: 側斜把手 | AC32: 緩衝鉸鏈(blun) 六分 | AD32: 6分 | AG32: 380 | AJ32: =CONCATENATE(P86,Q86) -> P8022膚感鐵灰 | AL32: 顆
A33: =A32+1 -> 30 | C33: 壁板 | J33: =J32+1 -> 30 | M33: 李安 | N33: V313-0 | O33: 白木紋 | P33: V313-0 | Q33: 白木紋 | R33: 李安 | Z33: 絞鏈孔 側斜把手 | AC33: 緩衝鉸鏈(blun) 三分 | AD33: 3分 | AG33: 380 | AJ33: =CONCATENATE(P87,Q87) -> P8023膚感米金 | AL33: 顆
A34: =A33+1 -> 31 | C34: 桌板 | J34: =J33+1 -> 31 | M34: 李安 | N34: V801-0 | O34: 結晶面板（白色） | P34: V801-0 | Q34: 結晶面板（白色） | R34: 李安 | Z34: 外把手 | AC34: 緩衝鉸鏈(blun) 入柱 | AD34: 入柱 | AJ34: =CONCATENATE(P88,Q88) -> P8404膚感杏灰 | AL34: 顆
A35: =A34+1 -> 32 | C35: 台面 | J35: =J34+1 -> 32 | M35: 板橋木業 | N35: A53 | O35: 埃及亞麻織 | P35: A53 | Q35: 埃及亞麻織 | R35: 板橋木業 | Z35: 崁把手 | AC35: 緩衝鉸鏈(blun) 負90度 | AD35: 負90度 | AJ35: =CONCATENATE(P89,Q89) -> P8305膚感卡其 | AL35: 顆
A36: =A35+1 -> 33 | C36: 床板 | J36: =J35+1 -> 33 | M36: 科定 | N36: P8706F | O36: 栗灰珍珠紋 | P36: P8709 | Q36: 栗灰珍珠紋 | R36: 科定 | Z36: 挖孔 下凸取手 | AC36: 緩衝鉸鏈(blun) 180度 | AD36: 180度 | AJ36: =CONCATENATE(P90,Q90) -> P8409膚感米灰 | AL36: 顆
A37: =A36+1 -> 34 | C37: 左右側板 | J37: =J36+1 -> 34 | M37: 科定 | N37: P8709F | O37: 墨黑珍珠紋 | P37: P8710 | Q37: 墨黑珍珠紋 | R37: 科定 | Z37: 三向開槽 | AC37: 緩衝鉸鏈(blun)厚門板用 六分 | AD37: 6分 | AG37: 450 | AJ37: =CONCATENATE(P91,Q91) -> P8024膚感黑雲石 | AL37: 顆
A38: =A37+1 -> 35 | C38: 頂底板 | J38: =J37+1 -> 35 | M38: 科定 | N38: P8705F | O38: 卡其珍珠紋 | P38: P8711 | Q38: 奶茶 | R38: 科定 | Z38: 四向開槽 | AC38: 緩衝鉸鏈(blun)厚門板用 三分 | AD38: 3分 | AG38: 450 | AJ38: =CONCATENATE(P92,Q92) -> P7320玻瑰金髮絲紋 | AL38: 顆
C39: 前側板 | J39: =J38+1 -> 36 | M39: 科定 | N39: P8702F | O39: 雪白珍珠紋 | P39: P8712 | Q39: 白雪 | R39: 科定 | Z39: 注意圖面 | AC39: 緩衝鉸鏈(blun)厚門板用 入柱 | AD39: 入柱 | AG39: 450 | AJ39: =CONCATENATE(P93,Q93) -> P7321黃銅髮絲紋 | AL39: 顆
C40: 後側板 | J40: =J39+1 -> 37 | M40: 科定 | N40: P8040C | O40: 砂面霧藍 | P40: P8713 | Q40: 砂面藍 | R40: 科定 | Z40: 同紋 | AC40: 緩衝鉸鏈(blun)厚門板用 負90度 | AD40: 負90度 | AL40: 顆
C41: 側板 | J41: =J40+1 -> 38 | M41: 科定 | N41: P8003C | O41: 砂面駝黃 | P41: P8714 | Q41: 砂面金 | R41: 科定 | AC41: 緩衝鉸鏈(blun)厚門板用 180度 | AD41: 180度 | AL41: 顆
C42: 封板 | J42: =J41+1 -> 39 | M42: 科定 | N42: P8002C | O42: 砂面雪白 | P42: P8715 | Q42: 砂面白 | R42: 科定 | Z42: 四面斜45 | AC42: KHS絞鏈(台製) 六分 | AD42: 六分 | AG42: =45*1.5/0.41 -> 164.63415 | AL42: 顆
C43: 假門板 | J43: =J42+1 -> 40 | M43: 科定 | N43: P8001C | O43: 砂面淺灰 | P43: P8716 | Q43: 砂面淺灰 | R43: 科定 | Z43: 背板溝 面開槽 打型 | AC43: KHS絞鏈(台製) 三分 | AD43: 三分 | AG43: =45*1.5/0.41 -> 164.63415 | AL43: 顆
C44: 假抽頭 | J44: =J43+1 -> 41 | M44: 科定 | N44: P8021C | O44: 砂面暖灰 | P44: P8717 | Q44: 砂面暖灰 | R44: 科定 | Z44: 背板溝 側開槽 打型 | AC44: KHS絞鏈(台製) 入柱 | AD44: 入柱 | AG44: =45*1.5/0.41 -> 164.63415 | AL44: 顆
C45: 上掀門板 | J45: =J44+1 -> 42 | M45: 科定 | N45: P8030C | O45: 砂面灰綠 | P45: P8718 | Q45: 砂面灰綠 | R45: 科定 | AC45: 四邊籃(40公分) | AD45: 40公分 | AG45: 1200 | AL45: 組
C46: 補板 | J46: =J45+1 -> 43 | M46: 科定 | N46: P8208C | O46: 砂面銅灰 | P46: P8719 | Q46: 砂面銅灰 | R46: 科定 | AC46: 四邊籃(45公分) | AD46: 45公分 | AG46: 1230 | AL46: 組
C47: 補角料 | J47: =J46+1 -> 44 | M47: 科定 | N47: P8808H | O47: 栗咖皮革紋 | P47: P8720 | Q47: 栗咖皮革 | R47: 科定 | AC47: 四邊籃(50公分) | AD47: 50公分 | AG47: 1260 | AL47: 組
C48: 指縫擋板 | J48: =J47+1 -> 45 | M48: 科定 | N48: P8011C | O48: 砂面灰白 | P48: P8721 | Q48: 砂面灰白 | R48: 科定 | AC48: 四邊籃(60公分) | AD48: 60公分 | AG48: 1340 | AL48: 組
C49: 前後側板 | J49: =J48+1 -> 46 | M49: 科定 | N49: P8009C | O49: 砂面墨黑 | P49: P8722 | Q49: 砂面墨黑 | R49: 科定 | AC49: 四邊籃(70公分) | AD49: 70公分 | AG49: 1400 | AL49: 組
C50: 前拉桿 | J50: =J49+1 -> 47 | M50: 科定 | N50: P8218C | O50: 砂面鐵灰 | P50: P8723 | Q50: 砂面鐵灰 | R50: 科定 | AC50: 四邊籃(72公分) | AD50: 72公分 | AG50: 1430 | AL50: 組
C51: 鋁框拉門 | J51: =J50+1 -> 48 | M51: 科定 | N51: P9005K | O51: 卡其泥作紋 | P51: P8730 | Q51: 卡其泥紋 | R51: 科定 | AC51: 四邊籃(75公分) | AD51: 75公分 | AG51: 1500 | AL51: 組
C52: 壁面層板 | J52: =J51+1 -> 49 | M52: 科定 | N52: P9105M | O52: 卡其直布紋 | P52: P8731 | Q52: 卡其直布紋 | R52: 科定 | AC52: 四邊籃(80公分) | AD52: 80公分 | AG52: 1500 | AL52: 組
C53: 內左側板 | J53: =J52+1 -> 50 | M53: 科定 | N53: P9207N | O53: 秋香斜布紋 | P53: P8732 | Q53: 秋香斜布紋 | R53: 科定 | AC53: 四邊籃(90公分) | AD53: 90公分 | AG53: 1580 | AL53: 組
C54: 內右側板 | J54: =J53+1 -> 51 | M54: 科定 | N54: P7002L | O54: 銀狐石 | P54: P8740 | Q54: 銀狐石 | R54: 科定 | AC54: 四邊籃(100公分) | AD54: 100公分 | AG54: 1650 | AL54: 組
C55: 外左側板 | J55: =J54+1 -> 52 | M55: 科定 | N55: P7154L | O55: 米白麻布紋 | P55: P8741 | Q55: 米白麻布紋 | R55: 科定 | AC55: 木螺綜 | AD55: 5公分 | AG55: 5 | AL55: 支
C56: 外右側板 | J56: =J55+1 -> 53 | M56: 科定 | N56: P7205L | O56: 卡其牛皮紙 | P56: P8742 | Q56: 卡其牛皮紙 | R56: 科定 | AC56: 木螺絲 大 | AD56: 4公分 | AG56: 4 | AL56: 支
C57: 配重板 | J57: =J56+1 -> 54 | M57: 科定 | N57: P7012E | O57: 白石紋 | P57: P8743 | Q57: 白石紋 | R57: 科定 | AC57: 木螺絲 中 | AD57: 3公分 | AG57: 3 | AL57: 支
J58: =J57+1 -> 55 | M58: 科定 | N58: P7052L | O58: 灰白清水模 | P58: P8744 | Q58: 灰白清水模 | R58: 科定 | AC58: 木螺絲 小 | AD58: 1.5公分 | AG58: 2 | AL58: 支
C59: 五金 | J59: =J58+1 -> 56 | M59: 科定 | N59: P7051L | O59: 暖灰清水模 | P59: P8745 | Q59: 暖灰清水模 | R59: 科定 | AC59: 六角縲絲 | AG59: 20 | AL59: 支
C60: w0 | J60: =J59+1 -> 57 | M60: 科定 | N60: P7013E | O60: 木紋石 | P60: P8746 | Q60: 木紋石 | R60: 科定 | AC60: 修飾蓋 (白) | AG60: 12 | AL60: 顆
C61: w1 | J61: =J60+1 -> 58 | M61: 科定 | N61: P9405S | O61: 卡其點陣紋 | P61: P8747 | Q61: 卡其點陣紋 | R61: 科定 | AC61: O型吊衣桿(60公分) | AG61: 300 | AL61: 支
C62: w2 | J62: =J61+1 -> 59 | M62: 科定 | N62: P9471S | O62: 銀白點陣紋 | P62: P8748 | Q62: 銀白點陣紋 | R62: 科定 | AC62: O型吊衣桿(90公分) | AG62: 450 | AL62: 支
C63: w3 | J63: =J62+1 -> 60 | M63: 科定 | N63: P9478S | O63: 銅灰點陣紋 | P63: P8749 | Q63: 銅灰點陣紋 | R63: 科定 | AC63: O型吊衣桿(120公分) | AG63: 600 | AL63: 支
C64: w4 | J64: =J63+1 -> 61 | M64: 科定 | N64: P9378P | O64: 鐵灰圓波紋 | P64: P8750 | Q64: 鐵灰圓波紋 | R64: 科定 | AC64: 橢圓吊衣桿(60公分) | AG64: 300
C65: Cabineo 12 | J65: =J64+1 -> 62 | M65: 科定 | N65: P7107L | O65: 鏽斑秋香 | P65: P8751 | Q65: 鏽斑秋香 | R65: 科定 | AC65: 橢圓吊衣桿(90公分) | AG65: 450
C66: Cabineo 8 | J66: =J65+1 -> 63 | M66: 科定 | N66: P7108L | O66: 鏽斑栗咖 | P66: P8752 | Q66: 鏽斑栗咖 | R66: 科定 | AC66: 橢圓吊衣桿(120公分) | AG66: 600 | AL66: 支
C67: Clamex P-15 | J67: =J66+1 -> 64 | M67: 科定 | N67: P8905J | O67: 卡其荔枝紋 | P67: P8753 | Q67: 卡其荔枝紋 | R67: 科定 | AC67: 吊衣桿中通 | AG67: 190 | AL67: 片
C68: Clamex P-14 | J68: =J67+1 -> 65 | M68: 科定 | N68: P8501D | O68: 膚感鈦銀 | P68: P8005 | Q68: 膚感鈦銀 | R68: 科定 | AC68: 目玉 | AG68: 30 | AL68: 片
C69: Clamex P-10 | J69: =J68+1 -> 66 | M69: 科定 | N69: P8511D | O69: 膚感銀白 | P69: P8006 | Q69: 膚感銀白 | R69: 科定 | AC69: 管塞 | AG69: 18 | AL69: 顆
C70: Clamex P-15/10 | J70: =J69+1 -> 67 | M70: 科定 | N70: P8520D | O70: 膚感玻瑰金 | P70: P8007 | Q70: 膚感玻瑰金 | R70: 科定 | AC70: 圓柱拍拍手 | AD70: 310 | AG70: 450 | AL70: 顆
C71: Clamex P-14 Flexus 連接件 | J71: =J70+1 -> 68 | M71: 科定 | N71: P8504D | O71: 膚感鈦白 | P71: P8008 | Q71: 膚感鈦白 | R71: 科定 | AC71: L片 鐵製 | AG71: 10 | AL71: 支
C72: Bisco P14 連接件 | J72: =J71+1 -> 69 | M72: 科定 | N72: P8506D | O72: 膚感銀灰 | P72: P8009 | Q72: 膚感銀灰 | R72: 科定 | AC72: L片 塑膠製 | AG72: 5 | AL72: 組
C73: Bisco P10 連接件 | J73: =J72+1 -> 70 | M73: 科定 | N73: P8507D | O73: 膚感香檳 | P73: P8010 | Q73: 膚感香檳 | R73: 科定 | AC73: 活隔粒 | AD73: 10 | AG73: 6 | AL73: 組
C74: Tenso P-14 卡扣式連接件 | J74: =J73+1 -> 71 | M74: 科定 | N74: P8508D | O74: 膚感鈦灰 | P74: P8011 | Q74: 鈦灰 | R74: 科定 | AC74: 活隔粒(有膠圈) | AD74: 10 | AG74: 10 | AL74: 組
C75: Tenso P-10 卡扣式連接件 | J75: =J74+1 -> 72 | M75: 科定 | N75: P8320D | O75: 膚感玻瑰 | P75: P8012 | Q75: 玻瑰 | R75: 科定 | AC75: 任意停 | AG75: 1230 | AL75: 組
C76: Divario P-18 連接件 | J76: =J75+1 -> 73 | M76: 科定 | N76: P8302D | O76: 膚感雪白 | P76: P8013 | Q76: 雪白 | R76: 科定 | AC76: 側掀軌道 | AG76: 1000 | AL76: 支
C77: 30公分三節式緩衝滑軌(非重型) | J77: =J76+1 -> 74 | M77: 科定 | N77: P8303 | O77: 膚感米黃 | P77: P8303 | Q77: 膚感米黃 | R77: 科定 | AC77: 雙臂吊衣架 短 | AD77: 45-60公分 | AG77: 3300 | AL77: 支
C78: 35公分三節式緩衝滑軌(非重型) | J78: =J77+1 -> 75 | M78: 科定 | N78: P8304D | O78: 膚感米白 | P78: P8014 | Q78: 膚感米白 | R78: 科定 | AC78: 雙臂吊衣架 中 | AD78: 60-83公分 | AG78: 3700 | AL78: 支
C79: 40公分三節式緩衝滑軌(非重型) | J79: =J78+1 -> 76 | M79: 科定 | N79: P8305D | O79: 膚感卡其 | P79: P8015 | Q79: 膚感卡其 | R79: 科定 | AC79: 雙臂吊衣架 長 | AD79: 83-115公分 | AG79: 4100 | AI79: 540 | AL79: 支
C80: 45公分三節式緩衝滑軌(非重型) | J80: =J79+1 -> 77 | M80: 科定 | N80: P8306D | O80: 膚感象灰 | P80: P8016 | Q80: 膚感象灰 | R80: 科定 | AC80: 層板縲絲 | AG80: 30 | AI80: 410 | AL80: 顆
C81: 50公分三節式緩衝滑軌(非重型) | J81: =J80+1 -> 78 | M81: 科定 | N81: P8307D | O81: 膚感秋香 | P81: P8017 | Q81: 膚感秋香 | R81: 科定 | AC81: 壁掛器 | AG81: 60 | AI81: 230
C82: 55公分三節式緩衝滑軌(非重型) | J82: =J81+1 -> 79 | M82: 科定 | N82: P8308D | O82: 膚感栗咖 | P82: P8018 | Q82: 膚感栗咖 | R82: 科定 | AC82: 川湖緩衝軌道 300 | AD82: 300 | AG82: 1300 | AL82: 組
C83: 60公分三節式緩衝滑軌(非重型) | J83: =J82+1 -> 80 | M83: 科定 | N83: P8309D | O83: 膚感墨黑 | P83: P8019 | Q83: 膚感墨黑 | R83: 科定 | AC83: 川湖緩衝軌道 350 | AD83: 350 | AG83: 1310 | AL83: 組
C84: 長調整腳(公頭) | J84: =J83+1 -> 81 | M84: 科定 | N84: P8330D | O84: 膚感灰綠 | P84: P8020 | Q84: 膚感灰綠 | R84: 科定 | AC84: 川湖緩衝軌道 400 | AD84: 400 | AG84: 1320 | AL84: 組
C85: 中調整腳(公頭) | J85: =J84+1 -> 82 | M85: 科定 | N85: P8326D | O85: 膚感黃褐 | P85: P8021 | Q85: 膚感黃褐 | R85: 科定 | AC85: 川湖緩衝軌道 450 | AD85: 450 | AG85: 1330 | AL85: 組
C86: 短調整腳(公頭) | J86: =J85+1 -> 83 | M86: 科定 | N86: P8318D | O86: 膚感鐵灰 | P86: P8022 | Q86: 膚感鐵灰 | R86: 科定 | AC86: 川湖緩衝軌道 500 | AD86: 500 | AG86: 1340 | AL86: 組
C87: 調整腳(母頭) | J87: =J86+1 -> 84 | M87: 科定 | N87: P8316D | O87: 膚感米金 | P87: P8023 | Q87: 膚感米金 | R87: 科定 | AC87: 川湖緩衝軌道 550 | AD87: 550 | AG87: 1350 | AL87: 組
C88: 緩衝鉸鏈(blun) 六分 | J88: =J87+1 -> 85 | M88: 科定 | N88: P8404 | O88: 膚感杏灰 | P88: P8404 | Q88: 膚感杏灰 | R88: 科定 | AC88: 川湖緩衝軌道 600 | AD88: 600 | AG88: 1360 | AL88: 組
C89: 緩衝鉸鏈(blun) 三分 | J89: =J88+1 -> 86 | M89: 科定 | N89: P8305 | O89: 膚感卡其 | P89: P8305 | Q89: 膚感卡其 | R89: 科定 | AC89: 三公分螺絲 | AG89: 3 | AL89: 顆
C90: 緩衝鉸鏈(blun) 入柱 | J90: =J89+1 -> 87 | M90: 科定 | N90: P8409 | O90: 膚感米灰 | P90: P8409 | Q90: 膚感米灰 | R90: 科定 | AC90: 鉸鍊螺絲 | AG90: 1 | AL90: 顆
C91: 緩衝鉸鏈(blun) 負90度 | J91: =J90+1 -> 88 | M91: 科定 | N91: P7009D | O91: 膚感黑雲石 | P91: P8024 | Q91: 膚感黑雲石 | R91: 科定 | AC91: 六分螺絲 | AG91: 6 | AL91: 顆
C92: 緩衝鉸鏈(blun) 180度 | J92: =J91+1 -> 89 | M92: 科定 | N92: P7320L | O92: 玻瑰金髮絲紋 | P92: P7320 | Q92: 玻瑰金髮絲紋 | R92: 科定 | AC92: 平掀桿 | AG92: 714 | AL92: 支
C93: 緩衝鉸鏈(blun)厚門板用 六分 | J93: =J92+1 -> 90 | M93: 科定 | N93: P7306L | O93: 黃銅髮絲紋 | P93: P7321 | Q93: 黃銅髮絲紋 | R93: 科定
C94: 緩衝鉸鏈(blun)厚門板用 三分 | J94: =J93+1 -> 91 | M94: 科定 | N94: P160FA | O94: 尤加利 | P94: P160FA | Q94: 尤加利 | R94: 科定
C95: 緩衝鉸鏈(blun)厚門板用 入柱 | J95: =J94+1 -> 92 | M95: 科定 | P95: P8218C | Q95: 砂面鐵灰 | R95: 科定
C96: 緩衝鉸鏈(blun)厚門板用 負90度 | J96: =J95+1 -> 93 | M96: 科定 | R96: 科定
C97: 緩衝鉸鏈(blun)厚門板用 180度 | J97: =J96+1 -> 94 | M97: 科定 | N97: ebi | R97: 科定
C98: KHS絞鏈(台製) 六分 | J98: =J97+1 -> 95 | M98: 科定 | N98: L7320 | O98: 玫瑰金髮絲紋 | P98: L7320 | Q98: 玫瑰金髮絲紋 | R98: 科定
C99: KHS絞鏈(台製) 三分 | J99: =J98+1 -> 96 | M99: 科定 | N99: L8303 | O99: 膚感米黃 | P99: L8303 | Q99: 膚感米黃 | R99: 科定
C100: KHS絞鏈(台製) 入柱 | J100: =J99+1 -> 97 | M100: 科定 | N100: L177P | O100: 白鐵刀木 | P100: L177P | Q100: 白鐵刀木 | R100: 科定
...

Sheet 五金配件
A1: 經辦業務 | B1: 業務員 | C1: 廠商名稱 | D1: 產品名稱(廠牌) | E1: 廠商目錄型號 | F1: 規格 | I1: 進貨單位 | J1: 銷貨單位 | K1: 備註 | L1: 牌價金額 | M1: 進貨金額 | N1: 進貨日期 | O1: 進貨數量 | P1: 退貨數量 | Q1: 傳票編號 | R1: 銷貨日期 | S1: 銷貨數量 | T1: 退貨數量 | U1: 銷貨案場 | V1: 傳票編號
F2: 長H x 寬W x 深D (公分)
A3: 吳冠裕 | B3: 張家銘 | C3: 拉米諾 | D3: w0 | I3: 箱(1000/組) | J3: 組
A4: 吳冠裕 | B4: 張家銘 | C4: 拉米諾 | D4: w1 | I4: 箱(1000/組) | J4: 組
A5: 吳冠裕 | B5: 張家銘 | C5: 拉米諾 | D5: w2 | I5: 箱(1000/組) | J5: 組
A6: 吳冠裕 | B6: 張家銘 | C6: 拉米諾 | D6: w3 | I6: 箱(1000/組) | J6: 組
A7: 吳冠裕 | B7: 張家銘 | C7: 拉米諾 | D7: w4 | I7: 箱(1000/組) | J7: 組
A8: 吳冠裕 | B8: 張家銘 | C8: 拉米諾 | D8: Cabineo 12 | I8: 箱(1000/組) | J8: 組
A9: 吳冠裕 | B9: 張家銘 | C9: 拉米諾 | D9: Cabineo 8 | I9: 箱(1000/組) | J9: 組
A10: 吳冠裕 | B10: 張家銘 | C10: 拉米諾 | D10: Clamex P-15 | I10: 箱(1000/組) | J10: 組
A11: 吳冠裕 | B11: 張家銘 | C11: 拉米諾 | D11: Clamex P-14 | I11: 箱(1000/組) | J11: 組
A12: 吳冠裕 | B12: 張家銘 | C12: 拉米諾 | D12: Clamex P-10 | I12: 箱(1000/組) | J12: 組
A13: 吳冠裕 | B13: 張家銘 | C13: 拉米諾 | D13: Clamex P-15/10 | I13: 箱(1000/組) | J13: 組
A14: 吳冠裕 | B14: 張家銘 | C14: 拉米諾 | D14: Clamex P-14 Flexus 連接件 | I14: 箱(1000/組) | J14: 組
... A22: 吳冠裕 | B22: 張家銘 | C22: 拉米諾 | D22: Divario P-18 連接件 | I22: 箱(1000/組) | J22: 組
A23: 劉軒魁 | C23: 積甲 | D23: 三節式緩衝滑軌(非重型) | F23: 30 | I23: 箱(15/組) | J23: 組
A24: 劉軒魁 | C24: 積甲 | D24: 三節式緩衝滑軌(非重型) | F24: 35 | I24: 箱(15/組) | J24: 組
A25: 劉軒魁 | C25: 積甲 | D25: 三節式緩衝滑軌(非重型) | F25: 40 | I25: 箱(15/組) | J25: 組
A26: 劉軒魁 | C26: 積甲 | D26: 三節式緩衝滑軌(非重型) | F26: 45 | I26: 箱(15/組) | J26: 組
A27: 劉軒魁 | C27: 積甲 | D27: 三節式緩衝滑軌(非重型) | F27: 50 | I27: 箱(15/組) | J27: 組
A28: 劉軒魁 | C28: 積甲 | D28: 三節式緩衝滑軌(非重型) | F28: 55 | I28: 箱(15/組) | J28: 組
A29: 劉軒魁 | C29: 積甲 | D29: 三節式緩衝滑軌(非重型) | F29: 60 | I29: 箱(15/組) | J29: 組 | K29: 含母頭
A30: 劉軒魁 | C30: 積甲 | D30: 調整腳(公頭) | F30: 長 | I30: 袋(100/顆) | J30: 組 | K30: 含母頭
A31: 劉軒魁 | C31: 積甲 | D31: 調整腳(公頭) | F31: 中 | I31: 袋(100/顆) | J31: 組 | K31: 含母頭
A32: 劉軒魁 | C32: 積甲 | D32: 調整腳(公頭) | F32: 短 | I32: 袋(100/顆) | J32: 組 | K32: 含母頭
A33: 劉軒魁 | C33: 積甲 | D33: 調整腳(母頭) | I33: 袋(300/顆)
A34: 劉軒魁 | C34: 積甲 | D34: 緩衝鉸鏈(blun) | F34: 6分 | I34: 箱
A35: 劉軒魁 | C35: 積甲 | D35: 緩衝鉸鏈(blun) | F35: 3分 | I35: 箱
A36: 劉軒魁 | C36: 積甲 | D36: 緩衝鉸鏈(blun) | F36: 入柱 | I36: 箱
A37: 劉軒魁 | C37: 積甲 | D37: 緩衝鉸鏈(blun) | F37: 負90度 | I37: 箱
A38: 劉軒魁 | C38: 積甲 | D38: 緩衝鉸鏈(blun) | F38: 180度 | I38: 箱
A39: 吳冠裕 | C39: 建泰 | D39: 緩衝鉸鏈(blun)厚門板用 | F39: 6分 | I39: 箱
D40: 緩衝鉸鏈(blun)厚門板用 | F40: 3分 | I40: 箱
D41: 緩衝鉸鏈(blun)厚門板用 | F41: 入柱 | I41: 箱
D42: 緩衝鉸鏈(blun)厚門板用 | F42: 負90度 | I42: 箱
D43: 緩衝鉸鏈(blun)厚門板用 | F43: 180度 | I43: 箱
A44: 劉軒魁 | D44: KHS絞鏈 | F44: 六分 | I44: 箱
A45: 劉軒魁 | D45: KHS絞鏈 | F45: 三分 | I45: 箱
A46: 劉軒魁 | D46: KHS絞鏈 | F46: 入柱 | I46: 箱
A47: 劉軒魁 | C47: 積甲 | D47: 木螺絲 | F47: 5 | I47: 件
A48: 劉軒魁 | C48: 積甲 | D48: 木螺絲 | F48: 4 | I48: 件
A49: 劉軒魁 | C49: 積甲 | D49: 木螺絲 | F49: 3 | I49: 件
A50: 劉軒魁 | C50: 積甲 | D50: 木螺絲 | F50: 1.5 | I50: 件
A51: 吳冠裕 | C51: 九江 | D51: O型吊衣桿 | F51: 300 | I51: 支 | K51: 含目玉及管塞
A52: 吳冠裕 | D52: 目玉 | I52: 個
A53: 吳冠裕 | D53: 管塞 | I53: 個
A54: 吳冠裕 | D54: 圓柱拍拍手 | I54: 支
A55: 劉軒魁 | D55: L片 | F55: 鐵製
A56: 劉軒魁 | D56: L片 | F56: 塑膠製
A57: 劉軒魁 | D57: 活隔粒
A58: 劉軒魁 | D58: 活隔粒 | F58: 圓柱型(含膠圈)
D59: 德式四邊拉籃 | E59: A4040 | F59: 363mm
D60: 德式四邊拉籃 | E60: A4045 | F60: 413mm
D61: 德式四邊拉籃 | E61: A4050 | F61: 463mm
D62: 德式四邊拉籃 | E62: A4060 | F62: 563mm
D63: 德式四邊拉籃 | E63: A4070 | F63: 663mm
D64: 德式四邊拉籃 | E64: A4072 | F64: 683mm
D65: 德式四邊拉籃 | E65: A4075 | F65: 713mm
D66: 德式四邊拉籃 | E66: A4080 | F66: 763mm
D67: 德式四邊拉籃 | E67: A4090 | F67: 863mm
D68: 德式四邊拉籃 | E68: A4100 | F68: 963mm

Sheet 色號
A1: 板材色號 | B1: 色號 板名 | C1: 板材 廠商_1 | D1: 封邊色號 | E1: 欄1
A2: 9999 | B2: 發泡板
A3: 1 | B3: 白身
A4: 1434 | B4: 晨星白橡 | C4: 翰可
A5: 1614 | B5: 銀白核桃 | C5: 翰可 | D5: P276N
A6: 1633 | B6: 清新楓木 | C6: 翰可 | D6: P245B
A7: 1644 | B7: 歐洲橡木 | C7: 翰可 | D7: P279F
A8: 1703 | B8: 幻影黑橡 | C8: 翰可 | D8: P140B
A9: 1754 | B9: 南洋玉檀 | C9: 翰可
A10: 1764 | B10: 古典白橡 | C10: 翰可 | D10: P276H
A11: 1774 | B11: 淺棕橡木 | C11: 翰可
A12: 1784 | B12: 鐵刀木 | C12: 翰可 | D12: P279J
A13: 1794 | B13: 皇家胡桃 | C13: 翰可 | D13: P276E
A14: 1804 | B14: 夜影檀木 | C14: 翰可 | D14: P197Q
A15: 1814 | B15: 東方栗木 | C15: 翰可 | D15: P196G
A16: 2101 | B16: 金屬灰 | C16: 翰可 | D16: P9378
A17: 2102 | B17: 和風金 | C17: 翰可
A18: 2103 | B18: 流金棕 | C18: 翰可
A19: 2104 | B19: 香檳金 | C19: 翰可
A20: 2317 | B20: 卡拉白 | C20: 翰可
A21: 2327 | B21: 絕色松華 | C21: 翰可
A22: 2330 | B22: 雪銀狐 | C22: 翰可 | D22: P705A
A23: 2353 | B23: 月雲白 | C23: 翰可
A24: 2454 | B24: 北國雪樹 | C24: 翰可 | D24: P160F
A25: 2624 | B25: 淺白榆木 | C25: 翰可 | D25: P181G
A26: 2653 | B26: 懷舊白橡 | C26: 翰可
A27: 2664 | B27: 北美櫻桃 | C27: 翰可 | D27: P214A
A28: 2673 | B28: 黃金柚木 | C28: 翰可 | D28: M69
A29: 2684 | B29: 可可櫻桃 | C29: 翰可 | D29: JM168C
A30: 2693 | B30: 英式胡桃 | C30: 翰可 | D30: P3468C
A31: 2713 | B31: 深紋棕橡 | C31: 翰可 | D31: P181D
A32: 2724 | B32: 晨影榆木 | C32: 翰可 | D32: P276M
A33: 2733 | B33: 燻染尤加利 | C33: 翰可
A34: 2744 | B34: 桃花心木 | C34: 翰可 | D34: M69
A35: 2882 | B35: 輝夜岩 | C35: 翰可
A36: 3008 | B36: 南美胡桃 | C36: 翰可
A37: 3131 | B37: 霧色榆木 | C37: 翰可
A38: 3218 | B38: 奶油澄木 | C38: 翰可 | D38: 達思SK6679C
A39: 3293 | B39: 青森雪松 | C39: 翰可
A40: 3338 | B40: 黎明橡木 | C40: 翰可
A41: 3653 | B41: 暗夜澄木 | C41: 翰可 | D41: P181H
A42: 3661 | B42: 加州胡桃 | C42: 翰可
A43: 3680 | B43: 山陰榆木 | C43: 翰可
A44: 3037 | B44: 日光淺泥 | C44: 翰可
A45: 3105 | B45: 霧島深泥 | C45: 翰可
A46: 3045 | B46: 曠野灰 | C46: 翰可
A47: 6669 | B47: 雅士白 | C47: 翰可 | D47: P7002
A48: 6533 | B48: 黑曜石 | C48: 翰可
A49: 6488 | B49: 星鑽灰 | C49: 翰可
A50: 6617 | B50: 千穗雲橡 | C50: 翰可
A51: 6446 | B51: 新岳白橡 | C51: 翰可 | D51: P169G
A52: 6589 | B52: 爵士白 | C52: 翰可 | D52: P7002
A53: 6838 | B53: 銀河白 | C53: 翰可
A54: 6121 | B54: 莫蘭迪灰像 | C54: 翰可
A55: 8046 | B55: 米蘭針織 | C55: 翰可
A56: 8081 | B56: 亞麻布紋 | C56: 翰可
A57: 8150 | B57: 灰布編織 | C57: 翰可 | D57: SK4979C
A58: 8069 | B58: 咖啡棕 | C58: 翰可
A59: 8213 | B59: 拿鐵色 | C59: 翰可 | D59: P9622
A60: 8215 | B60: 時尚灰 | C60: 翰可 | D60: P8482
A61: 8255 | B61: 摩卡黑 | C61: 翰可
A62: 8299 | B62: 霜白色 | C62: 翰可
A63: 8454 | B63: 象牙白 | C63: 翰可
A64: 6285 | B64: 倉米織紋 | C64: 翰可
A65: 6830 | B65: 山茶織布 | C65: 翰可
A66: 6515 | B66: 橫紋白理 | C66: 翰可 | D66: P160F
A67: 6234 | B67: 雪點壁布 | C67: 翰可
A68: 6643 | B68: 雪山橡木 | C68: 翰可
A69: 6472 | B69: 山紋灰橡 | C69: 翰可 | D69: M75
A70: 6781 | B70: 山形白橡 | C70: 翰可 | D70: P196G
A71: 6763 | B71: 栗色胡桃 | C71: 翰可
A72: 6691 | B72: 暮色白橡 | C72: 翰可
A73: 6732 | B73: 影灰胡桃 | C73: 翰可 | D73: P187J
A74: 6415 | B74: 日陰杉木 | C74: 翰可 | D74: P197M
A75: 6803 | B75: 風華胡桃 | C75: 翰可
A76: 6409 | B76: 金絲白橡 | C76: 翰可
A77: 6805 | B77: 水青橡木 | C77: 翰可
A78: 6491 | B78: 藍山橡木 | C78: 翰可 | D78: P269N
A79: 8478 | B79: 純灰木紋 | C79: 翰可 | D79: p8414
A80: 8227 | B80: 純白木紋 | C80: 翰可
A81: 8932 | B81: 椰奶色 | C81: 翰可 | D81: P8104
A82: 8083 | B82: 杏仁灰 | C82: 翰可 | D82: P8409
A83: 8464 | B83: 暖白色 | C83: 翰可
A84: 8086 | B84: 山嵐灰 | C84: 翰可 | D84: P7206
A85: 8155 | B85: 石英灰 | C85: 翰可 | D85: JM543
A86: 3035 | B86: 仲夏榆木 | C86: 翰可
A87: 3443 | B87: 尼斯櫻桃 | C87: 翰可
A88: 6703 | B88: 雪映岩 | C88: 翰可
A89: 6706 | B89: 金紋岩 | C89: 翰可
A90: 6708 | B90: 初光柔沙 | C90: 翰可
A91: 6712 | B91: 曜石幻影 | C91: 翰可 | D91: P7218
A92: 8201 | B92: 柔米白 | C92: 翰可
A93: 8210 | B93: 淺大地 | C93: 翰可
A94: 8222 | B94: 霧藍星 | C94: 翰可
A95: 8234 | B95: 曙光白 | C95: 翰可
A96: 3017 | B96: 灰凝彩邑 | C96: 翰可
A97: 3450 | B97: 水墨丹青 | C97: 翰可 | D97: P8402
A98: 3552 | B98: 富山胡桃 | C98: 翰可
A99: 3406 | B99: 北岳胡桃 | C99: 翰可
A100: 3081 | B100: 岩灰梣木 | C100: 翰可
...

Sheet 拆單用
A1: Column1 | B1: Column2 | C1: Column3 | D1: Column4 | E1: Column5 | F1: Column6 | G1: Column7 | H1: Column8 | I1: Column9 | J1: Column10 | K1: Column11 | L1: Column12
A2: 桶身 | B2: 內部 | C2: 外部 | D2: 抽屜 | E2: 抽箱 | F2: 抽盤_不見軌道 | G2: 床架_臥塌 | H2: 內部五金 | I2: 外部五金 | J2: 抽屜五金 | K2: 其它五金 | L2: 衣廚五金
A3: 頂板 | B3: 固隔 | C3: 踢腳板 | D3: 抽頭 | E3: 左側板 | F3: 抽盤 | G3: 左側板 | H3: 活隔粒 | I3: 調整腳(10-12cm) | J3: 20公分三節式滑軌 | K3: 大頭螺絲 | L3: 吊衣桿
A4: 底板 | B4: 活隔 | C4: 左門板 | D4: 左抽牆 | E4: 右側板 | F4: 抽盤抽頭 | G4: 右側板 | H4: 固隔器(金屬)含螺絲 | I4: 調整腳(8-10cm) | J4: 25公分三節式緩衝滑軌 | K4: 木螺絲 1.5cm | L4: 吊 耳
A5: 左側板 | B5: 中立板 | C5: 右門板 | D5: 右抽牆 | E5: 頂板 | F5: 左右抽盤骨料（對切） | G5: 上支桿 | I5: 平行鉸鏈(-90°) | J5: 30公分三節式緩衝滑軌 | K5: 木螺絲 3cm | L5: 吊衣桿(不鏽鋼)
A6: 右側板 | B6: 中立板(退) | C6: 指縫擋板 | D6: 前抽牆 | E6: 底板 | F6: 前後抽盤骨料（對切） | G6: 下支桿 | I6: 緩衝鉸鏈 三分 | J6: 35公分三節式緩衝滑軌 | K6: 木螺絲 4cm | L6: 吊 耳(不鏽鋼)
A7: 背板 | B7: 固隔(退) | C7: 指縫擋板(對切) | D7: 後抽牆 | E7: 上前拉桿 | G7: 踢腳骨料 | I7: KHS絞鏈(台製) 六分 | J7: 40公分三節式緩衝滑軌 | K7: 木螺絲 5cm | L7: 吊衣桿中通
A8: 背拉桿 | B8: 活固隔 | C8: 木滑門 | D8: 抽底 | E8: 下前拉桿 | G8: 入柱背板 | I8: 川湖緩衝鉸鏈 六分 | J8: 45公分三節式緩衝滑軌 | K8: 六角縲絲7cm
A9: 底板(退) | B9: 內頂板 | D9: 抽屜拉桿 | E9: 上後拉桿 | I9: 川湖緩衝鉸鏈 三分 | J9: 50公分三節式緩衝滑軌 | K9: 拉米諾
A10: 天地蓋頂板 | B10: 內左側落板 | C10: 線板 | D10: 指縫擋板 | E10: 下後拉桿 | I10: 川湖緩衝鉸鏈 入柱 | J10: 55公分三節式緩衝滑軌 | K10: 通風片(鋁合金)
A11: 天地蓋底板 | B11: 內右側落板 | C11: 層板 | D11: 入柱抽頭 | E11: 中立板 | I11: Blun緩衝鉸鏈 六分 | J11: 60公分三節式緩衝滑軌 | K11: 出線孔圓 5.5公分
A12: 天地蓋左側板 | B12: 內底板 | C12: 壁面層板 | D12: 入柱抽底 | E12: 入柱背板 | I12: Blun緩衝鉸鏈 三分 | J12: 30公分川湖緩衝軌道 | K12: 出線孔 長方形
A13: 天地蓋右側板 | B13: 內左側板 | C13: 桌板 | D13: 外蓋抽底 | I13: Blun緩衝鉸鏈 入柱 | J13: 35公分川湖緩衝軌道
A14: 天地蓋左側落板 | B14: 內右側板 | C14: 台面 | D14: 假抽頭 | I14: 寸15厚門緩衝鉸鏈 六分 | J14: 40公分川湖緩衝軌道 | K14: 油煙機
A15: 天地蓋右側落板 | B15: 上前平肢 | C15: 床板 | D15: 格子抽(直) | I15: 圓柱拍拍手 | J15: 45公分川湖緩衝軌道 | K15: 檯面爐
A16: 左側落板 | B16: 上後平肢 | C16: 假門板 | D16: 格子抽(橫) | I16: L片 鐵製 | J16: 50公分川湖緩衝軌道 | K16: 烘碗機
A17: 右側落板 | B17: 上前立肢 | C17: 上掀門板 | I17: L片 塑膠製 | J17: 30公分坐式緩衝滑軌 | K17: 水槽
A18: 入柱背板 | B18: 上後立肢 | C18: 平掀門板 | I18: 檯面輔助支撐架 | J18: 35公分坐式緩衝滑軌 | K18: 水龍頭
A19: 外蓋背板 | B19: 下前立肢 | C19: 下掀門板 | I19: 層板L架（白烤） | J19: 40公分坐式緩衝滑軌 | K19: 人造石檯面
A20: 入柱底板 | B20: 下後立肢 | C20: 拉籃門板 | I20: 層板縲絲 | J20: 45公分坐式緩衝滑軌
A21: 外蓋底板 | B21: 下前平肢 | C21: 補板 | I21: 深22mm肚臍鎖(門片用) | J21: 50公分坐式緩衝滑軌
A22: 前側板 | B22: 下後平肢 | C22: 封板 | I22: 深36mm肚臍鎖(抽頭用) | J22: 30公分彈壓式緩衝滑軌
A23: 後側板 | B23: 內補板 | C23: 上封板 | I23: 平掀桿 | J23: 35公分彈壓式緩衝滑軌
A24: 外左側板 | B24: 內補板(對切) | C24: 下封板 | I24: 上掀桿 | J24: 40公分彈壓式緩衝滑軌
A25: 外右側板 | B25: 橫撐 | C25: 前封板 | I25: 任意停 | J25: 45公分彈壓式緩衝滑軌
B26: 立板 | C26: 後封板 | I26: 崁把手 | J26: 50公分彈壓式緩衝滑軌
C27: 左封板 | I27: 上軌(A339鋁擠) | J27: 55公分彈壓式緩衝滑軌
C28: 右封板 | I28: 雙下軌(平輪77鋁擠) | J28: 15公分瓶罐側拉架(座式）
C29: 外蓋封板 | I29: 雙培林上輪 | J29: 20公分瓶罐側拉架(座式）
C30: 入柱封板 | I30: 白鐵輪 | J30: 高身櫃拉籃
C31: 上蓋板 | I31: 鋁飾條 | J31: 鋁抽(小抽84)
C32: 直立板 | I32: 毛刷條（短） | J32: 鋁抽(薄高抽116)
C33: 補角料 | I33: 毛刷條（長） | J33: 鋁抽(薄高高抽167)
C34: 燈擋板 | I34: 上軌(ㄇ型)
C35: 燈擋板(對切) | I35: 下軌(V型)
C36: 鋁框滑門 | I36: 上輪(塑膠)
I37: 下V輪(塑膠)
C38: 上軌道板
C39: 下軌道板
C40: 左軌道板
C41: 右軌道板
C42: 左圓角側板
C43: 右圓角側板
C44: 電箱門片
C45: 格柵
C46: 踏板

Sheet 標記
A1: Column1 | B1: Column2 | C1: Column3 | D1: Column4 | G1: 設計師
A2: 背板溝 | B2: A | C2: 4 | G2: 吳心彤
A3: 側 | B3: AA | C3: 8 | G3: 溫培堯
A4: 面 | B4: AP | C4: 12 | G4: 張修睿
A5: 排 | C5: 17 | G5: 郭博豪
A6: 二排 | B6: PP | C6: 18 | G6: 呂映澄
A7: 打型 | B7: P | C7: 20 | G7: 陳昭宇
A8: 固 | B8: A | C8: 23
A9: 鉸2 | C9: 25 | G9: JEFF 宋綻威
A10: 鉸3 | C10: 30
A11: 鉸4 | C11: 34
A12: 上斜 | C12: 40
A13: 下斜 | C13: 51
A14: 側斜 | C14: 50
A15: 崁 | C15: 1
A16: Z
A17: 輪
A18: 軌道
A19: 退20
A20: 燈溝

Sheet 料單
C1: =_xlfn.IFNA(CONCATENATE(TEXT(K2,"yyyymmdd"),G1),"") -> 2026101401 | F1: 流水號： | G1: 01
A2: 案場： | J2: 訂貨日期： | K2: =TODAY() -> 46309 | N2: 1修改日期：
A3: 業務/設計師： | J3: 交貨日期： | L3: 拉、KD | N3: 2修改日期：
A4: 板材總片數： | C4: =L8+L46+L85+L124+L163+L202+L241+L280+L319+L358+L397+L436+L475+L514+L553+L592+L631+L670+L709+L748+L787+L826+L865+L904+L943+L982+L1021+L1060+L1099+L1138+L1177+L1216+L1255+L1294+L1333+L1372+L1411+L1450+L1489+L1528+L1567+L1606+L1645+L1684+L1723+L1762+L1801+L1840+L1879+L1918 -> 0 | J4: 送貨地址： | N4: 3修改日期：
A5: 板材總才數： | B5: =ROUND(SUM(板材才數分析.!P:P),0) -> 0
A7: 櫃體名稱 | D7: {=_xlfn.IFS(OR(C7="水槽櫃",C7="爐台櫃"),"無頂板",C7="油機吊櫃","無底板",TRUE,0)} -> 0
A8: 櫃號 | C8: 1 | K8: 板材片數： | L8: =SUMIF(D14:D43,"<>*五金",K14:K43) -> 0
A9: 櫃高 | K9: 板材才數： | L9: =板材才數分析.!P31 -> 0 | T9: =IF(AND(OR($E14="右側板",$E14="左側板"),COUNTIF($E$14:$E$43,"活隔")>0),"排孔","")
A10: 櫃深 | D10: 不含門 | K10: 批次： | L10: 1
A11: 櫃寬
A12: 櫃名 | C12: 專案 | D12: 類別 | E12: 板材名稱 | F12: 開板尺寸 | K12: 生產 數量 | L12: 板材 色號 | M12: 色號 名稱 | N12: 板商 | O12: 封邊 色號 | P12: 備註 | Q12: 備註 | R12: 備註 | S12: 備註 | T12: 提醒 | U12: 批次
F13: 長(同紋) | G13: 封邊 | H13: 寬 | I13: 封邊 | J13: 厚
A14: =$C$7 -> 0 | C14: =(C8*1000)+1 -> 1001 | D14: 桶身 | E14: 頂板 | F14: =C11-35 -> -35 | G14: =IF( OR( $E14="頂板",$E14="底板",$E14="右側板",$E14="左側板", $E14="天地蓋頂板",$E14="天地蓋底板",$E14="天地蓋右側板",$E14="天地蓋左側板", $E14="前抽牆",$E14="後抽牆",$E14="左抽牆",$E14="右抽牆", $E14="踢腳板",$E14="補板",$E14="固隔",$E14="活隔", $E14="中立板",$E14="中立板(退)",$E14="固隔(退)",$E14="活固隔",$E14="立板", $E14="內頂板",$E14="內左側落板",$E14="內右側落板",$E14="內底板", $E14="內左側板",$E14="內右側板", $E14="上前平肢",$E14="上後平肢",$E14="上前立肢",$E14="上後立肢", $E14="下前立肢",$E14="下後立肢",$E14="下前平肢",$E14="下後平肢", $E14="左側落板",$E14="右側落板", $E14="外蓋背板",$E14="台面",$E14="床板",$E14="假門板", $E14="上掀門板",$E14="平掀門板",$E14="下掀門板", $E14="左門板",$E14="右門板", $E14="抽盤",$E14="抽盤抽頭", $E14="上軌道板",$E14="下軌道板",$E14="左軌道板",$E14="右軌道板",$E14="指縫擋板",$E14="左木框滑門",$E14="右木框滑門", $E14="層板",$E14="壁面層板",$E14="桌板",$E14="上封板",$E14="下封板",$E14="左封板",$E14="右封板", $E14="左圓角側板",$E14="右圓角側板",$E14="抽頭",$E14="入柱抽頭",$E14="假抽頭",$E14="背拉桿",$E14="木滑門",$E14="抽屜拉桿" ), "AA", "" ) -> AA | H14: =C10 -> 0 | I14: =IF( OR( $E14="右側板",$E14="左側板",$E14="活隔", $E14="天地蓋頂板",$E14="天地蓋底板", $E14="左門板",$E14="右門板", $E14="左側落板",$E14="右側落板", $E14="外蓋背板",$E14="活固隔", $E14="左木框滑門",$E14="右木框滑門", $E14="左鋁框滑門",$E14="右鋁框滑門", $E14="桌板",$E14="台面",$E14="床板",$E14="假門板", $E14="上掀門板",$E14="平掀門板",$E14="下掀門板", $E14="抽盤抽頭",$E14="抽盤",$E14="層板",$E14="壁面層板", $E14="上封板",$E14="下封板",$E14="左封板",$E14="右封板", $E14="抽頭",$E14="踢腳板",$E14="補板",$E14="木滑門" ), "AA", "" ) | J14: 18 | M14: =IFERROR(VLOOKUP(L14,色號!A:B,2,FALSE),"") | N14: =IFERROR(VLOOKUP(M14,色號!B:C,2,FALSE),"") | O14: =IFERROR(VLOOKUP(L14,色號!A:D,4,FALSE),"") | P14: =IF( OR($E14="左門板", $E14="右門板"), "鉸" & IF($F14<=1000, 2, IF($F14<=1800, 3, 4)), IF( $E14="入柱背板", "側", IF( $E14="外蓋背板", "面", IF( AND(COUNTIF($E$14:$E$43,"入柱背板")>0, OR($E14="頂板", $E14="底板")), "面", IF( AND(COUNTIF($E$14:$E$43,"外蓋背板")>0, OR($E14="左側板", $E14="右側板")), "側", IF( AND( COUNTIF($E$14:$E$43,"入柱背板")=0, COUNTIF($E$14:$E$43,"外蓋背板")=0, OR( AND(COUNTIF($E$14:$E$43,"背板")>0, OR($E14="左側板",$E14="右側板",$E14="頂板",$E14="底板",$E14="天地蓋右側板",$E14="天地蓋左側板",$E14="天地蓋底板",$E14="天地蓋頂板")), AND(COUNTIF($E$14:$E$43,"抽底")>0, OR($E14="右抽牆",$E14="左抽牆",$E14="前抽牆",$E14="後抽牆")) ) ), "背板溝", "" ) ) ) ) ) ) -> 背板溝 | Q14: =IF(OR($E14="天地蓋右側板",$E14="天地蓋左側板"), "側 面", IF(OR($E14="背拉桿",$E14="中立板",$E14="頂板",$E14="底板",$E14="前抽牆",$E14="後抽牆",$E14="內左側落板",$E14="內右側落板",$E14="抽屜拉桿",$E14="立板"), "側", IF(OR($E14="木滑門",$E14="鋁框滑門"), "輪", IF(OR($E14="右側板",$E14="左側板",$E14="右抽牆",$E14="左抽牆",$E14="天地蓋頂板",$E14="天地蓋底板",$E14="內頂板"), "面", IF($E14="固隔","固","") ) ) ) ) -> 側 | R14: =IF( OR($E14="左側板",$E14="右側板",$E14="天地蓋左側板",$E14="天地蓋右側板",$E14="中立板",$E14="立板"), "排","") | T14: =IF($E14="中立板","面開槽？排孔？", IF($E14="木框滑門","前排孔要退喔！", IF(OR($E14="左門板",$E14="右門板",$E14="抽頭"),"把手？", IF(OR($E14="左側板",$E14="右側板",$E14="天地蓋右側板",$E14="天地蓋左側板"),"排孔？","")))) | U14: =IF(E14="","",$L$10) -> 1
A15: =$C$7 -> 0 | C15: =C14+1 -> 1002 | D15: 桶身 | E15: 底板 | F15: =C11-35 -> -35 | G15: =IF( OR( $E15="頂板",$E15="底板",$E15="右側板",$E15="左側板", $E15="天地蓋頂板",$E15="天地蓋底板",$E15="天地蓋右側板",$E15="天地蓋左側板", $E15="前抽牆",$E15="後抽牆",$E15="左抽牆",$E15="右抽牆", $E15="踢腳板",$E15="補板",$E15="固隔",$E15="活隔", $E15="中立板",$E15="中立板(退)",$E15="固隔(退)",$E15="活固隔",$E15="立板", $E15="內頂板",$E15="內左側落板",$E15="內右側落板",$E15="內底板", $E15="內左側板",$E15="內右側板", $E15="上前平肢",$E15="上後平肢",$E15="上前立肢",$E15="上後立肢", $E15="下前立肢",$E15="下後立肢",$E15="下前平肢",$E15="下後平肢", $E15="左側落板",$E15="右側落板", $E15="外蓋背板",$E15="台面",$E15="床板",$E15="假門板", $E15="上掀門板",$E15="平掀門板",$E15="下掀門板", $E15="左門板",$E15="右門板", $E15="抽盤",$E15="抽盤抽頭", $E15="上軌道板",$E15="下軌道板",$E15="左軌道板",$E15="右軌道板",$E15="指縫擋板",$E15="左木框滑門",$E15="右木框滑門", $E15="層板",$E15="壁面層板",$E15="桌板",$E15="上封板",$E15="下封板",$E15="左封板",$E15="右封板", $E15="左圓角側板",$E15="右圓角側板",$E15="抽頭",$E15="入柱抽頭",$E15="假抽頭",$E15="背拉桿",$E15="木滑門",$E15="抽屜拉桿" ), "AA", "" ) -> AA | H15: =C10 -> 0 | I15: =IF( OR( $E15="右側板",$E15="左側板",$E15="活隔", $E15="天地蓋頂板",$E15="天地蓋底板", $E15="左門板",$E15="右門板", $E15="左側落板",$E15="右側落板", $E15="外蓋背板",$E15="活固隔", $E15="左木框滑門",$E15="右木框滑門", $E15="左鋁框滑門",$E15="右鋁框滑門", $E15="桌板",$E15="台面",$E15="床板",$E15="假門板", $E15="上掀門板",$E15="平掀門板",$E15="下掀門板", $E15="抽盤抽頭",$E15="抽盤",$E15="層板",$E15="壁面層板", $E15="上封板",$E15="下封板",$E15="左封板",$E15="右封板", $E15="抽頭",$E15="踢腳板",$E15="補板",$E15="木滑門" ), "AA", "" ) | J15: 18 | M15: =IFERROR(VLOOKUP(L15,色號!A:B,2,FALSE),"") | N15: =IFERROR(VLOOKUP(M15,色號!B:C,2,FALSE),"") | O15: =IFERROR(VLOOKUP(L15,色號!A:D,4,FALSE),"") | P15: =IF( OR($E15="左門板", $E15="右門板"), "鉸" & IF($F15<=1000, 2, IF($F15<=1800, 3, 4)), IF( $E15="入柱背板", "側", IF( $E15="外蓋背板", "面", IF( AND(COUNTIF($E$14:$E$43,"入柱背板")>0, OR($E15="頂板", $E15="底板")), "面", IF( AND(COUNTIF($E$14:$E$43,"外蓋背板")>0, OR($E15="左側板", $E15="右側板")), "側", IF( AND( COUNTIF($E$14:$E$43,"入柱背板")=0, COUNTIF($E$14:$E$43,"外蓋背板")=0, OR( AND(COUNTIF($E$14:$E$43,"背板")>0, OR($E15="左側板",$E15="右側板",$E15="頂板",$E15="底板",$E15="天地蓋右側板",$E15="天地蓋左側板",$E15="天地蓋底板",$E15="天地蓋頂板")), AND(COUNTIF($E$14:$E$43,"抽底")>0, OR($E15="右抽牆",$E15="左抽牆",$E15="前抽牆",$E15="後抽牆")) ) ), "背板溝", "" ) ) ) ) ) ) -> 背板溝 | Q15: =IF(OR($E15="天地蓋右側板",$E15="天地蓋左側板"), "側 面", IF(OR($E15="背拉桿",$E15="中立板",$E15="頂板",$E15="底板",$E15="前抽牆",$E15="後抽牆",$E15="內左側落板",$E15="內右側落板",$E15="抽屜拉桿",$E15="立板"), "側", IF(OR($E15="木滑門",$E15="鋁框滑門"), "輪", IF(OR($E15="右側板",$E15="左側板",$E15="右抽牆",$E15="左抽牆",$E15="天地蓋頂板",$E15="天地蓋底板",$E15="內頂板"), "面", IF($E15="固隔","固","") ) ) ) ) -> 側 | R15: =IF( OR($E15="左側板",$E15="右側板",$E15="天地蓋左側板",$E15="天地蓋右側板",$E15="中立板",$E15="立板"), "排","") | T15: =IF($E15="中立板","面開槽？排孔？", IF($E15="木框滑門","前排孔要退喔！", IF(OR($E15="左門板",$E15="右門板",$E15="抽頭"),"把手？", IF(OR($E15="左側板",$E15="右側板",$E15="天地蓋右側板",$E15="天地蓋左側板"),"排孔？","")))) | U15: =IF(E15="","",$L$10) -> 1
A16: =$C$7 -> 0 | C16: =C15+1 -> 1003 | D16: 桶身 | E16: 左側板 | F16: =C9 -> 0 | G16: =IF( OR( $E16="頂板",$E16="底板",$E16="右側板",$E16="左側板", $E16="天地蓋頂板",$E16="天地蓋底板",$E16="天地蓋右側板",$E16="天地蓋左側板", $E16="前抽牆",$E16="後抽牆",$E16="左抽牆",$E16="右抽牆", $E16="踢腳板",$E16="補板",$E16="固隔",$E16="活隔", $E16="中立板",$E16="中立板(退)",$E16="固隔(退)",$E16="活固隔",$E16="立板", $E16="內頂板",$E16="內左側落板",$E16="內右側落板",$E16="內底板", $E16="內左側板",$E16="內右側板", $E16="上前平肢",$E16="上後平肢",$E16="上前立肢",$E16="上後立肢", $E16="下前立肢",$E16="下後立肢",$E16="下前平肢",$E16="下後平肢", $E16="左側落板",$E16="右側落板", $E16="外蓋背板",$E16="台面",$E16="床板",$E16="假門板", $E16="上掀門板",$E16="平掀門板",$E16="下掀門板", $E16="左門板",$E16="右門板", $E16="抽盤",$E16="抽盤抽頭", $E16="上軌道板",$E16="下軌道板",$E16="左軌道板",$E16="右軌道板",$E16="指縫擋板",$E16="左木框滑門",$E16="右木框滑門", $E16="層板",$E16="壁面層板",$E16="桌板",$E16="上封板",$E16="下封板",$E16="左封板",$E16="右封板", $E16="左圓角側板",$E16="右圓角側板",$E16="抽頭",$E16="入柱抽頭",$E16="假抽頭",$E16="背拉桿",$E16="木滑門",$E16="抽屜拉桿" ), "AA", "" ) -> AA | H16: =C10 -> 0 | I16: =IF( OR( $E16="右側板",$E16="左側板",$E16="活隔", $E16="天地蓋頂板",$E16="天地蓋底板", $E16="左門板",$E16="右門板", $E16="左側落板",$E16="右側落板", $E16="外蓋背板",$E16="活固隔", $E16="左木框滑門",$E16="右木框滑門", $E16="左鋁框滑門",$E16="右鋁框滑門", $E16="桌板",$E16="台面",$E16="床板",$E16="假門板", $E16="上掀門板",$E16="平掀門板",$E16="下掀門板", $E16="抽盤抽頭",$E16="抽盤",$E16="層板",$E16="壁面層板", $E16="上封板",$E16="下封板",$E16="左封板",$E16="右封板", $E16="抽頭",$E16="踢腳板",$E16="補板",$E16="木滑門" ), "AA", "" ) -> AA | J16: 18 | M16: =IFERROR(VLOOKUP(L16,色號!A:B,2,FALSE),"") | N16: =IFERROR(VLOOKUP(M16,色號!B:C,2,FALSE),"") | O16: =IFERROR(VLOOKUP(L16,色號!A:D,4,FALSE),"") | P16: =IF( OR($E16="左門板", $E16="右門板"), "鉸" & IF($F16<=1000, 2, IF($F16<=1800, 3, 4)), IF( $E16="入柱背板", "側", IF( $E16="外蓋背板", "面", IF( AND(COUNTIF($E$14:$E$43,"入柱背板")>0, OR($E16="頂板", $E16="底板")), "面", IF( AND(COUNTIF($E$14:$E$43,"外蓋背板")>0, OR($E16="左側板", $E16="右側板")), "側", IF( AND( COUNTIF($E$14:$E$43,"入柱背板")=0, COUNTIF($E$14:$E$43,"外蓋背板")=0, OR( AND(COUNTIF($E$14:$E$43,"背板")>0, OR($E16="左側板",$E16="右側板",$E16="頂板",$E16="底板",$E16="天地蓋右側板",$E16="天地蓋左側板",$E16="天地蓋底板",$E16="天地蓋頂板")), AND(COUNTIF($E$14:$E$43,"抽底")>0, OR($E16="右抽牆",$E16="左抽牆",$E16="前抽牆",$E16="後抽牆")) ) ), "背板溝", "" ) ) ) ) ) ) -> 背板溝 | Q16: =IF(OR($E16="天地蓋右側板",$E16="天地蓋左側板"), "側 面", IF(OR($E16="背拉桿",$E16="中立板",$E16="頂板",$E16="底板",$E16="前抽牆",$E16="後抽牆",$E16="內左側落板",$E16="內右側落板",$E16="抽屜拉桿",$E16="立板"), "側", IF(OR($E16="木滑門",$E16="鋁框滑門"), "輪", IF(OR($E16="右側板",$E16="左側板",$E16="右抽牆",$E16="左抽牆",$E16="天地蓋頂板",$E16="天地蓋底板",$E16="內頂板"), "面", IF($E16="固隔","固","") ) ) ) ) -> 面 | R16: =IF( OR($E16="左側板",$E16="右側板",$E16="天地蓋左側板",$E16="天地蓋右側板",$E16="中立板",$E16="立板"), "排","") -> 排 | T16: =IF($E16="中立板","面開槽？排孔？", IF($E16="木框滑門","前排孔要退喔！", IF(OR($E16="左門板",$E16="右門板",$E16="抽頭"),"把手？", IF(OR($E16="左側板",$E16="右側板",$E16="天地蓋右側板",$E16="天地蓋左側板"),"排孔？","")))) -> 排孔？ | U16: =IF(E16="","",$L$10) -> 1
A17: =$C$7 -> 0 | C17: =C16+1 -> 1004 | D17: 桶身 | E17: 右側板 | F17: =C9 -> 0 | G17: =IF( OR( $E17="頂板",$E17="底板",$E17="右側板",$E17="左側板", $E17="天地蓋頂板",$E17="天地蓋底板",$E17="天地蓋右側板",$E17="天地蓋左側板", $E17="前抽牆",$E17="後抽牆",$E17="左抽牆",$E17="右抽牆", $E17="踢腳板",$E17="補板",$E17="固隔",$E17="活隔", $E17="中立板",$E17="中立板(退)",$E17="固隔(退)",$E17="活固隔",$E17="立板", $E17="內頂板",$E17="內左側落板",$E17="內右側落板",$E17="內底板", $E17="內左側板",$E17="內右側板", $E17="上前平肢",$E17="上後平肢",$E17="上前立肢",$E17="上後立肢", $E17="下前立肢",$E17="下後立肢",$E17="下前平肢",$E17="下後平肢", $E17="左側落板",$E17="右側落板", $E17="外蓋背板",$E17="台面",$E17="床板",$E17="假門板", $E17="上掀門板",$E17="平掀門板",$E17="下掀門板", $E17="左門板",$E17="右門板", $E17="抽盤",$E17="抽盤抽頭", $E17="上軌道板",$E17="下軌道板",$E17="左軌道板",$E17="右軌道板",$E17="指縫擋板",$E17="左木框滑門",$E17="右木框滑門", $E17="層板",$E17="壁面層板",$E17="桌板",$E17="上封板",$E17="下封板",$E17="左封板",$E17="右封板", $E17="左圓角側板",$E17="右圓角側板",$E17="抽頭",$E17="入柱抽頭",$E17="假抽頭",$E17="背拉桿",$E17="木滑門",$E17="抽屜拉桿" ), "AA", "" ) -> AA | H17: =C10 -> 0 | I17: =IF( OR( $E17="右側板",$E17="左側板",$E17="活隔", $E17="天地蓋頂板",$E17="天地蓋底板", $E17="左門板",$E17="右門板", $E17="左側落板",$E17="右側落板", $E17="外蓋背板",$E17="活固隔", $E17="左木框滑門",$E17="右木框滑門", $E17="左鋁框滑門",$E17="右鋁框滑門", $E17="桌板",$E17="台面",$E17="床板",$E17="假門板", $E17="上掀門板",$E17="平掀門板",$E17="下掀門板", $E17="抽盤抽頭",$E17="抽盤",$E17="層板",$E17="壁面層板", $E17="上封板",$E17="下封板",$E17="左封板",$E17="右封板", $E17="抽頭",$E17="踢腳板",$E17="補板",$E17="木滑門" ), "AA", "" ) -> AA | J17: 18 | M17: =IFERROR(VLOOKUP(L17,色號!A:B,2,FALSE),"") | N17: =IFERROR(VLOOKUP(M17,色號!B:C,2,FALSE),"") | O17: =IFERROR(VLOOKUP(L17,色號!A:D,4,FALSE),"") | P17: =IF( OR($E17="左門板", $E17="右門板"), "鉸" & IF($F17<=1000, 2, IF($F17<=1800, 3, 4)), IF( $E17="入柱背板", "側", IF( $E17="外蓋背板", "面", IF( AND(COUNTIF($E$14:$E$43,"入柱背板")>0, OR($E17="頂板", $E17="底板")), "面", IF( AND(COUNTIF($E$14:$E$43,"外蓋背板")>0, OR($E17="左側板", $E17="右側板")), "側", IF( AND( COUNTIF($E$14:$E$43,"入柱背板")=0, COUNTIF($E$14:$E$43,"外蓋背板")=0, OR( AND(COUNTIF($E$14:$E$43,"背板")>0, OR($E17="左側板",$E17="右側板",$E17="頂板",$E17="底板",$E17="天地蓋右側板",$E17="天地蓋左側板",$E17="天地蓋底板",$E17="天地蓋頂板")), AND(COUNTIF($E$14:$E$43,"抽底")>0, OR($E17="右抽牆",$E17="左抽牆",$E17="前抽牆",$E17="後抽牆")) ) ), "背板溝", "" ) ) ) ) ) ) -> 背板溝 | Q17: =IF(OR($E17="天地蓋右側板",$E17="天地蓋左側板"), "側 面", IF(OR($E17="背拉桿",$E17="中立板",$E17="頂板",$E17="底板",$E17="前抽牆",$E17="後抽牆",$E17="內左側落板",$E17="內右側落板",$E17="抽屜拉桿",$E17="立板"), "側", IF(OR($E17="木滑門",$E17="鋁框滑門"), "輪", IF(OR($E17="右側板",$E17="左側板",$E17="右抽牆",$E17="左抽牆",$E17="天地蓋頂板",$E17="天地蓋底板",$E17="內頂板"), "面", IF($E17="固隔","固","") ) ) ) ) -> 面 | R17: =IF( OR($E17="左側板",$E17="右側板",$E17="天地蓋左側板",$E17="天地蓋右側板",$E17="中立板",$E17="立板"), "排","") -> 排 | T17: =IF($E17="中立板","面開槽？排孔？", IF($E17="木框滑門","前排孔要退喔！", IF(OR($E17="左門板",$E17="右門板",$E17="抽頭"),"把手？", IF(OR($E17="左側板",$E17="右側板",$E17="天地蓋右側板",$E17="天地蓋左側板"),"排孔？","")))) -> 排孔？ | U17: =IF(E17="","",$L$10) -> 1
A18: =$C$7 -> 0 | C18: =C17+1 -> 1005 | D18: 桶身 | E18: 背板 | F18: =C9-22 -> -22 | G18: =IF( OR( $E18="頂板",$E18="底板",$E18="右側板",$E18="左側板", $E18="天地蓋頂板",$E18="天地蓋底板",$E18="天地蓋右側板",$E18="天地蓋左側板", $E18="前抽牆",$E18="後抽牆",$E18="左抽牆",$E18="右抽牆", $E18="踢腳板",$E18="補板",$E18="固隔",$E18="活隔", $E18="中立板",$E18="中立板(退)",$E18="固隔(退)",$E18="活固隔",$E18="立板", $E18="內頂板",$E18="內左側落板",$E18="內右側落板",$E18="內底板", $E18="內左側板",$E18="內右側板", $E18="上前平肢",$E18="上後平肢",$E18="上前立肢",$E18="上後立肢", $E18="下前立肢",$E18="下後立肢",$E18="下前平肢",$E18="下後平肢", $E18="左側落板",$E18="右側落板", $E18="外蓋背板",$E18="台面",$E18="床板",$E18="假門板", $E18="上掀門板",$E18="平掀門板",$E18="下掀門板", $E18="左門板",$E18="右門板", $E18="抽盤",$E18="抽盤抽頭", $E18="上軌道板",$E18="下軌道板",$E18="左軌道板",$E18="右軌道板",$E18="指縫擋板",$E18="左木框滑門",$E18="右木框滑門", $E18="層板",$E18="壁面層板",$E18="桌板",$E18="上封板",$E18="下封板",$E18="左封板",$E18="右封板", $E18="左圓角側板",$E18="右圓角側板",$E18="抽頭",$E18="入柱抽頭",$E18="假抽頭",$E18="背拉桿",$E18="木滑門",$E18="抽屜拉桿" ), "AA", "" ) | H18: =C11-22 -> -22 | I18: =IF( OR( $E18="右側板",$E18="左側板",$E18="活隔", $E18="天地蓋頂板",$E18="天地蓋底板", $E18="左門板",$E18="右門板", $E18="左側落板",$E18="右側落板", $E18="外蓋背板",$E18="活固隔", $E18="左木框滑門",$E18="右木框滑門", $E18="左鋁框滑門",$E18="右鋁框滑門", $E18="桌板",$E18="台面",$E18="床板",$E18="假門板", $E18="上掀門板",$E18="平掀門板",$E18="下掀門板", $E18="抽盤抽頭",$E18="抽盤",$E18="層板",$E18="壁面層板", $E18="上封板",$E18="下封板",$E18="左封板",$E18="右封板", $E18="抽頭",$E18="踢腳板",$E18="補板",$E18="木滑門" ), "AA", "" ) | J18: 4 | M18: =IFERROR(VLOOKUP(L18,色號!A:B,2,FALSE),"") | N18: =IFERROR(VLOOKUP(M18,色號!B:C,2,FALSE),"") | O18: =IFERROR(VLOOKUP(L18,色號!A:D,4,FALSE),"") | P18: =IF( OR($E18="左門板", $E18="右門板"), "鉸" & IF($F18<=1000, 2, IF($F18<=1800, 3, 4)), IF( $E18="入柱背板", "側", IF( $E18="外蓋背板", "面", IF( AND(COUNTIF($E$14:$E$43,"入柱背板")>0, OR($E18="頂板", $E18="底板")), "面", IF( AND(COUNTIF($E$14:$E$43,"外蓋背板")>0, OR($E18="左側板", $E18="右側板")), "側", IF( AND( COUNTIF($E$14:$E$43,"入柱背板")=0, COUNTIF($E$14:$E$43,"外蓋背板")=0, OR( AND(COUNTIF($E$14:$E$43,"背板")>0, OR($E18="左側板",$E18="右側板",$E18="頂板",$E18="底板",$E18="天地蓋右側板",$E18="天地蓋左側板",$E18="天地蓋底板",$E18="天地蓋頂板")), AND(COUNTIF($E$14:$E$43,"抽底")>0, OR($E18="右抽牆",$E18="左抽牆",$E18="前抽牆",$E18="後抽牆")) ) ), "背板溝", "" ) ) ) ) ) ) | Q18: =IF(OR($E18="天地蓋右側板",$E18="天地蓋左側板"), "側 面", IF(OR($E18="背拉桿",$E18="中立板",$E18="頂板",$E18="底板",$E18="前抽牆",$E18="後抽牆",$E18="內左側落板",$E18="內右側落板",$E18="抽屜拉桿",$E18="立板"), "側", IF(OR($E18="木滑門",$E18="鋁框滑門"), "輪", IF(OR($E18="右側板",$E18="左側板",$E18="右抽牆",$E18="左抽牆",$E18="天地蓋頂板",$E18="天地蓋底板",$E18="內頂板"), "面", IF($E18="固隔","固","") ) ) ) ) | R18: =IF( OR($E18="左側板",$E18="右側板",$E18="天地蓋左側板",$E18="天地蓋右側板",$E18="中立板",$E18="立板"), "排","") | T18: =IF($E18="中立板","面開槽？排孔？", IF($E18="木框滑門","前排孔要退喔！", IF(OR($E18="左門板",$E18="右門板",$E18="抽頭"),"把手？", IF(OR($E18="左側板",$E18="右側板",$E18="天地蓋右側板",$E18="天地蓋左側板"),"排孔？","")))) | U18: =IF(E18="","",$L$10) -> 1
A19: =$C$7 -> 0 | C19: =C18+1 -> 1006 | D19: 桶身 | E19: 背拉桿 | F19: =F14 -> -35 | G19: =IF( OR( $E19="頂板",$E19="底板",$E19="右側板",$E19="左側板", $E19="天地蓋頂板",$E19="天地蓋底板",$E19="天地蓋右側板",$E19="天地蓋左側板", $E19="前抽牆",$E19="後抽牆",$E19="左抽牆",$E19="右抽牆", $E19="踢腳板",$E19="補板",$E19="固隔",$E19="活隔", $E19="中立板",$E19="中立板(退)",$E19="固隔(退)",$E19="活固隔",$E19="立板", $E19="內頂板",$E19="內左側落板",$E19="內右側落板",$E19="內底板", $E19="內左側板",$E19="內右側板", $E19="上前平肢",$E19="上後平肢",$E19="上前立肢",$E19="上後立肢", $E19="下前立肢",$E19="下後立肢",$E19="下前平肢",$E19="下後平肢", $E19="左側落板",$E19="右側落板", $E19="外蓋背板",$E19="台面",$E19="床板",$E19="假門板", $E19="上掀門板",$E19="平掀門板",$E19="下掀門板", $E19="左門板",$E19="右門板", $E19="抽盤",$E19="抽盤抽頭", $E19="上軌道板",$E19="下軌道板",$E19="左軌道板",$E19="右軌道板",$E19="指縫擋板",$E19="左木框滑門",$E19="右木框滑門", $E19="層板",$E19="壁面層板",$E19="桌板",$E19="上封板",$E19="下封板",$E19="左封板",$E19="右封板", $E19="左圓角側板",$E19="右圓角側板",$E19="抽頭",$E19="入柱抽頭",$E19="假抽頭",$E19="背拉桿",$E19="木滑門",$E19="抽屜拉桿" ), "AA", "" ) -> AA | H19: 120 | I19: =IF( OR( $E19="右側板",$E19="左側板",$E19="活隔", $E19="天地蓋頂板",$E19="天地蓋底板", $E19="左門板",$E19="右門板", $E19="左側落板",$E19="右側落板", $E19="外蓋背板",$E19="活固隔", $E19="左木框滑門",$E19="右木框滑門", $E19="左鋁框滑門",$E19="右鋁框滑門", $E19="桌板",$E19="台面",$E19="床板",$E19="假門板", $E19="上掀門板",$E19="平掀門板",$E19="下掀門板", $E19="抽盤抽頭",$E19="抽盤",$E19="層板",$E19="壁面層板", $E19="上封板",$E19="下封板",$E19="左封板",$E19="右封板", $E19="抽頭",$E19="踢腳板",$E19="補板",$E19="木滑門" ), "AA", "" ) | J19: 18 | M19: =IFERROR(VLOOKUP(L19,色號!A:B,2,FALSE),"") | N19: =IFERROR(VLOOKUP(M19,色號!B:C,2,FALSE),"") | O19: =IFERROR(VLOOKUP(L19,色號!A:D,4,FALSE),"") | P19: =IF( OR($E19="左門板", $E19="右門板"), "鉸" & IF($F19<=1000, 2, IF($F19<=1800, 3, 4)), IF( $E19="入柱背板", "側", IF( $E19="外蓋背板", "面", IF( AND(COUNTIF($E$14:$E$43,"入柱背板")>0, OR($E19="頂板", $E19="底板")), "面", IF( AND(COUNTIF($E$14:$E$43,"外蓋背板")>0, OR($E19="左側板", $E19="右側板")), "側", IF( AND( COUNTIF($E$14:$E$43,"入柱背板")=0, COUNTIF($E$14:$E$43,"外蓋背板")=0, OR( AND(COUNTIF($E$14:$E$43,"背板")>0, OR($E19="左側板",$E19="右側板",$E19="頂板",$E19="底板",$E19="天地蓋右側板",$E19="天地蓋左側板",$E19="天地蓋底板",$E19="天地蓋頂板")), AND(COUNTIF($E$14:$E$43,"抽底")>0, OR($E19="右抽牆",$E19="左抽牆",$E19="前抽牆",$E19="後抽牆")) ) ), "背板溝", "" ) ) ) ) ) ) | Q19: =IF(OR($E19="天地蓋右側板",$E19="天地蓋左側板"), "側 面", IF(OR($E19="背拉桿",$E19="中立板",$E19="頂板",$E19="底板",$E19="前抽牆",$E19="後抽牆",$E19="內左側落板",$E19="內右側落板",$E19="抽屜拉桿",$E19="立板"), "側", IF(OR($E19="木滑門",$E19="鋁框滑門"), "輪", IF(OR($E19="右側板",$E19="左側板",$E19="右抽牆",$E19="左抽牆",$E19="天地蓋頂板",$E19="天地蓋底板",$E19="內頂板"), "面", IF($E19="固隔","固","") ) ) ) ) -> 側 | R19: =IF( OR($E19="左側板",$E19="右側板",$E19="天地蓋左側板",$E19="天地蓋右側板",$E19="中立板",$E19="立板"), "排","") | T19: =IF($E19="中立板","面開槽？排孔？", IF($E19="木框滑門","前排孔要退喔！", IF(OR($E19="左門板",$E19="右門板",$E19="抽頭"),"把手？", IF(OR($E19="左側板",$E19="右側板",$E19="天地蓋右側板",$E19="天地蓋左側板"),"排孔？","")))) | U19: =IF(E19="","",$L$10) -> 1
A20: =$C$7 -> 0 | C20: =C19+1 -> 1007 | D20: 內部 | E20: 中立板 | F20: =F14 -> -35 | G20: =IF( OR( $E20="頂板",$E20="底板",$E20="右側板",$E20="左側板", $E20="天地蓋頂板",$E20="天地蓋底板",$E20="天地蓋右側板",$E20="天地蓋左側板", $E20="前抽牆",$E20="後抽牆",$E20="左抽牆",$E20="右抽牆", $E20="踢腳板",$E20="補板",$E20="固隔",$E20="活隔", $E20="中立板",$E20="中立板(退)",$E20="固隔(退)",$E20="活固隔",$E20="立板", $E20="內頂板",$E20="內左側落板",$E20="內右側落板",$E20="內底板", $E20="內左側板",$E20="內右側板", $E20="上前平肢",$E20="上後平肢",$E20="上前立肢",$E20="上後立肢", $E20="下前立肢",$E20="下後立肢",$E20="下前平肢",$E20="下後平肢", $E20="左側落板",$E20="右側落板", $E20="外蓋背板",$E20="台面",$E20="床板",$E20="假門板", $E20="上掀門板",$E20="平掀門板",$E20="下掀門板", $E20="左門板",$E20="右門板", $E20="抽盤",$E20="抽盤抽頭", $E20="上軌道板",$E20="下軌道板",$E20="左軌道板",$E20="右軌道板",$E20="指縫擋板",$E20="左木框滑門",$E20="右木框滑門", $E20="層板",$E20="壁面層板",$E20="桌板",$E20="上封板",$E20="下封板",$E20="左封板",$E20="右封板", $E20="左圓角側板",$E20="右圓角側板",$E20="抽頭",$E20="入柱抽頭",$E20="假抽頭",$E20="背拉桿",$E20="木滑門",$E20="抽屜拉桿" ), "AA", "" ) -> AA | H20: =C10-22 -> -22 | I20: =IF( OR( $E20="右側板",$E20="左側板",$E20="活隔", $E20="天地蓋頂板",$E20="天地蓋底板", $E20="左門板",$E20="右門板", $E20="左側落板",$E20="右側落板", $E20="外蓋背板",$E20="活固隔", $E20="左木框滑門",$E20="右木框滑門", $E20="左鋁框滑門",$E20="右鋁框滑門", $E20="桌板",$E20="台面",$E20="床板",$E20="假門板", $E20="上掀門板",$E20="平掀門板",$E20="下掀門板", $E20="抽盤抽頭",$E20="抽盤",$E20="層板",$E20="壁面層板", $E20="上封板",$E20="下封板",$E20="左封板",$E20="右封板", $E20="抽頭",$E20="踢腳板",$E20="補板",$E20="木滑門" ), "AA", "" ) | J20: 18 | M20: =IFERROR(VLOOKUP(L20,色號!A:B,2,FALSE),"") | N20: =IFERROR(VLOOKUP(M20,色號!B:C,2,FALSE),"") | O20: =IFERROR(VLOOKUP(L20,色號!A:D,4,FALSE),"") | P20: =IF( OR($E20="左門板", $E20="右門板"), "鉸" & IF($F20<=1000, 2, IF($F20<=1800, 3, 4)), IF( $E20="入柱背板", "側", IF( $E20="外蓋背板", "面", IF( AND(COUNTIF($E$14:$E$43,"入柱背板")>0, OR($E20="頂板", $E20="底板")), "面", IF( AND(COUNTIF($E$14:$E$43,"外蓋背板")>0, OR($E20="左側板", $E20="右側板")), "側", IF( AND( COUNTIF($E$14:$E$43,"入柱背板")=0, COUNTIF($E$14:$E$43,"外蓋背板")=0, OR( AND(COUNTIF($E$14:$E$43,"背板")>0, OR($E20="左側板",$E20="右側板",$E20="頂板",$E20="底板",$E20="天地蓋右側板",$E20="天地蓋左側板",$E20="天地蓋底板",$E20="天地蓋頂板")), AND(COUNTIF($E$14:$E$43,"抽底")>0, OR($E20="右抽牆",$E20="左抽牆",$E20="前抽牆",$E20="後抽牆")) ) ), "背板溝", "" ) ) ) ) ) ) | Q20: =IF(OR($E20="天地蓋右側板",$E20="天地蓋左側板"), "側 面", IF(OR($E20="背拉桿",$E20="中立板",$E20="頂板",$E20="底板",$E20="前抽牆",$E20="後抽牆",$E20="內左側落板",$E20="內右側落板",$E20="抽屜拉桿",$E20="立板"), "側", IF(OR($E20="木滑門",$E20="鋁框滑門"), "輪", IF(OR($E20="右側板",$E20="左側板",$E20="右抽牆",$E20="左抽牆",$E20="天地蓋頂板",$E20="天地蓋底板",$E20="內頂板"), "面", IF($E20="固隔","固","") ) ) ) ) -> 側 | R20: =IF( OR($E20="左側板",$E20="右側板",$E20="天地蓋左側板",$E20="天地蓋右側板",$E20="中立板",$E20="立板"), "排","") -> 排 | T20: =IF($E20="中立板","面開槽？排孔？", IF($E20="木框滑門","前排孔要退喔！", IF(OR($E20="左門板",$E20="右門板",$E20="抽頭"),"把手？", IF(OR($E20="左側板",$E20="右側板",$E20="天地蓋右側板",$E20="天地蓋左側板"),"排孔？","")))) -> 面開槽？排孔？ | U20: =IF(E20="","",$L$10) -> 1
A21: =$C$7 -> 0 | C21: =C20+1 -> 1008 | D21: 內部 | E21: 活隔 | G21: =IF( OR( $E21="頂板",$E21="底板",$E21="右側板",$E21="左側板", $E21="天地蓋頂板",$E21="天地蓋底板",$E21="天地蓋右側板",$E21="天地蓋左側板", $E21="前抽牆",$E21="後抽牆",$E21="左抽牆",$E21="右抽牆", $E21="踢腳板",$E21="補板",$E21="固隔",$E21="活隔", $E21="中立板",$E21="中立板(退)",$E21="固隔(退)",$E21="活固隔",$E21="立板", $E21="內頂板",$E21="內左側落板",$E21="內右側落板",$E21="內底板", $E21="內左側板",$E21="內右側板", $E21="上前平肢",$E21="上後平肢",$E21="上前立肢",$E21="上後立肢", $E21="下前立肢",$E21="下後立肢",$E21="下前平肢",$E21="下後平肢", $E21="左側落板",$E21="右側落板", $E21="外蓋背板",$E21="台面",$E21="床板",$E21="假門板", $E21="上掀門板",$E21="平掀門板",$E21="下掀門板", $E21="左門板",$E21="右門板", $E21="抽盤",$E21="抽盤抽頭", $E21="上軌道板",$E21="下軌道板",$E21="左軌道板",$E21="右軌道板",$E21="指縫擋板",$E21="左木框滑門",$E21="右木框滑門", $E21="層板",$E21="壁面層板",$E21="桌板",$E21="上封板",$E21="下封板",$E21="左封板",$E21="右封板", $E21="左圓角側板",$E21="右圓角側板",$E21="抽頭",$E21="入柱抽頭",$E21="假抽頭",$E21="背拉桿",$E21="木滑門",$E21="抽屜拉桿" ), "AA", "" ) -> AA | H21: =C10-22-10 -> -32 | I21: =IF( OR( $E21="右側板",$E21="左側板",$E21="活隔", $E21="天地蓋頂板",$E21="天地蓋底板", $E21="左門板",$E21="右門板", $E21="左側落板",$E21="右側落板", $E21="外蓋背板",$E21="活固隔", $E21="左木框滑門",$E21="右木框滑門", $E21="左鋁框滑門",$E21="右鋁框滑門", $E21="桌板",$E21="台面",$E21="床板",$E21="假門板", $E21="上掀門板",$E21="平掀門板",$E21="下掀門板", $E21="抽盤抽頭",$E21="抽盤",$E21="層板",$E21="壁面層板", $E21="上封板",$E21="下封板",$E21="左封板",$E21="右封板", $E21="抽頭",$E21="踢腳板",$E21="補板",$E21="木滑門" ), "AA", "" ) -> AA | J21: 18 | M21: =IFERROR(VLOOKUP(L21,色號!A:B,2,FALSE),"") | N21: =IFERROR(VLOOKUP(M21,色號!B:C,2,FALSE),"") | O21: =IFERROR(VLOOKUP(L21,色號!A:D,4,FALSE),"") | P21: =IF( OR($E21="左門板", $E21="右門板"), "鉸" & IF($F21<=1000, 2, IF($F21<=1800, 3, 4)), IF( $E21="入柱背板", "側", IF( $E21="外蓋背板", "面", IF( AND(COUNTIF($E$14:$E$43,"入柱背板")>0, OR($E21="頂板", $E21="底板")), "面", IF( AND(COUNTIF($E$14:$E$43,"外蓋背板")>0, OR($E21="左側板", $E21="右側板")), "側", IF( AND( COUNTIF($E$14:$E$43,"入柱背板")=0, COUNTIF($E$14:$E$43,"外蓋背板")=0, OR( AND(COUNTIF($E$14:$E$43,"背板")>0, OR($E21="左側板",$E21="右側板",$E21="頂板",$E21="底板",$E21="天地蓋右側板",$E21="天地蓋左側板",$E21="天地蓋底板",$E21="天地蓋頂板")), AND(COUNTIF($E$14:$E$43,"抽底")>0, OR($E21="右抽牆",$E21="左抽牆",$E21="前抽牆",$E21="後抽牆")) ) ), "背板溝", "" ) ) ) ) ) ) | Q21: =IF(OR($E21="天地蓋右側板",$E21="天地蓋左側板"), "側 面", IF(OR($E21="背拉桿",$E21="中立板",$E21="頂板",$E21="底板",$E21="前抽牆",$E21="後抽牆",$E21="內左側落板",$E21="內右側落板",$E21="抽屜拉桿",$E21="立板"), "側", IF(OR($E21="木滑門",$E21="鋁框滑門"), "輪", IF(OR($E21="右側板",$E21="左側板",$E21="右抽牆",$E21="左抽牆",$E21="天地蓋頂板",$E21="天地蓋底板",$E21="內頂板"), "面", IF($E21="固隔","固","") ) ) ) ) | R21: =IF( OR($E21="左側板",$E21="右側板",$E21="天地蓋左側板",$E21="天地蓋右側板",$E21="中立板",$E21="立板"), "排","") | T21: =IF($E21="中立板","面開槽？排孔？", IF($E21="木框滑門","前排孔要退喔！", IF(OR($E21="左門板",$E21="右門板",$E21="抽頭"),"把手？", IF(OR($E21="左側板",$E21="右側板",$E21="天地蓋右側板",$E21="天地蓋左側板"),"排孔？","")))) | U21: =IF(E21="","",$L$10) -> 1
A22: =$C$7 -> 0 | C22: =C21+1 -> 1009 | D22: 內部 | E22: 固隔 | G22: =IF( OR( $E22="頂板",$E22="底板",$E22="右側板",$E22="左側板", $E22="天地蓋頂板",$E22="天地蓋底板",$E22="天地蓋右側板",$E22="天地蓋左側板", $E22="前抽牆",$E22="後抽牆",$E22="左抽牆",$E22="右抽牆", $E22="踢腳板",$E22="補板",$E22="固隔",$E22="活隔", $E22="中立板",$E22="中立板(退)",$E22="固隔(退)",$E22="活固隔",$E22="立板", $E22="內頂板",$E22="內左側落板",$E22="內右側落板",$E22="內底板", $E22="內左側板",$E22="內右側板", $E22="上前平肢",$E22="上後平肢",$E22="上前立肢",$E22="上後立肢", $E22="下前立肢",$E22="下後立肢",$E22="下前平肢",$E22="下後平肢", $E22="左側落板",$E22="右側落板", $E22="外蓋背板",$E22="台面",$E22="床板",$E22="假門板", $E22="上掀門板",$E22="平掀門板",$E22="下掀門板", $E22="左門板",$E22="右門板", $E22="抽盤",$E22="抽盤抽頭", $E22="上軌道板",$E22="下軌道板",$E22="左軌道板",$E22="右軌道板",$E22="指縫擋板",$E22="左木框滑門",$E22="右木框滑門", $E22="層板",$E22="壁面層板",$E22="桌板",$E22="上封板",$E22="下封板",$E22="左封板",$E22="右封板", $E22="左圓角側板",$E22="右圓角側板",$E22="抽頭",$E22="入柱抽頭",$E22="假抽頭",$E22="背拉桿",$E22="木滑門",$E22="抽屜拉桿" ), "AA", "" ) -> AA | H22: =C10-22 -> -22 | I22: =IF( OR( $E22="右側板",$E22="左側板",$E22="活隔", $E22="天地蓋頂板",$E22="天地蓋底板", $E22="左門板",$E22="右門板", $E22="左側落板",$E22="右側落板", $E22="外蓋背板",$E22="活固隔", $E22="左木框滑門",$E22="右木框滑門", $E22="左鋁框滑門",$E22="右鋁框滑門", $E22="桌板",$E22="台面",$E22="床板",$E22="假門板", $E22="上掀門板",$E22="平掀門板",$E22="下掀門板", $E22="抽盤抽頭",$E22="抽盤",$E22="層板",$E22="壁面層板", $E22="上封板",$E22="下封板",$E22="左封板",$E22="右封板", $E22="抽頭",$E22="踢腳板",$E22="補板",$E22="木滑門" ), "AA", "" ) | J22: 18 | M22: =IFERROR(VLOOKUP(L22,色號!A:B,2,FALSE),"") | N22: =IFERROR(VLOOKUP(M22,色號!B:C,2,FALSE),"") | O22: =IFERROR(VLOOKUP(L22,色號!A:D,4,FALSE),"") | P22: =IF( OR($E22="左門板", $E22="右門板"), "鉸" & IF($F22<=1000, 2, IF($F22<=1800, 3, 4)), IF( $E22="入柱背板", "側", IF( $E22="外蓋背板", "面", IF( AND(COUNTIF($E$14:$E$43,"入柱背板")>0, OR($E22="頂板", $E22="底板")), "面", IF( AND(COUNTIF($E$14:$E$43,"外蓋背板")>0, OR($E22="左側板", $E22="右側板")), "側", IF( AND( COUNTIF($E$14:$E$43,"入柱背板")=0, COUNTIF($E$14:$E$43,"外蓋背板")=0, OR( AND(COUNTIF($E$14:$E$43,"背板")>0, OR($E22="左側板",$E22="右側板",$E22="頂板",$E22="底板",$E22="天地蓋右側板",$E22="天地蓋左側板",$E22="天地蓋底板",$E22="天地蓋頂板")), AND(COUNTIF($E$14:$E$43,"抽底")>0, OR($E22="右抽牆",$E22="左抽牆",$E22="前抽牆",$E22="後抽牆")) ) ), "背板溝", "" ) ) ) ) ) ) | Q22: =IF(OR($E22="天地蓋右側板",$E22="天地蓋左側板"), "側 面", IF(OR($E22="背拉桿",$E22="中立板",$E22="頂板",$E22="底板",$E22="前抽牆",$E22="後抽牆",$E22="內左側落板",$E22="內右側落板",$E22="抽屜拉桿",$E22="立板"), "側", IF(OR($E22="木滑門",$E22="鋁框滑門"), "輪", IF(OR($E22="右側板",$E22="左側板",$E22="右抽牆",$E22="左抽牆",$E22="天地蓋頂板",$E22="天地蓋底板",$E22="內頂板"), "面", IF($E22="固隔","固","") ) ) ) ) -> 固 | R22: =IF( OR($E22="左側板",$E22="右側板",$E22="天地蓋左側板",$E22="天地蓋右側板",$E22="中立板",$E22="立板"), "排","") | T22: =IF($E22="中立板","面開槽？排孔？", IF($E22="木框滑門","前排孔要退喔！", IF(OR($E22="左門板",$E22="右門板",$E22="抽頭"),"把手？", IF(OR($E22="左側板",$E22="右側板",$E22="天地蓋右側板",$E22="天地蓋左側板"),"排孔？","")))) | U22: =IF(E22="","",$L$10) -> 1
A23: =$C$7 -> 0 | C23: =C22+1 -> 1010 | D23: 外部 | E23: 左門板 | G23: =IF( OR( $E23="頂板",$E23="底板",$E23="右側板",$E23="左側板", $E23="天地蓋頂板",$E23="天地蓋底板",$E23="天地蓋右側板",$E23="天地蓋左側板", $E23="前抽牆",$E23="後抽牆",$E23="左抽牆",$E23="右抽牆", $E23="踢腳板",$E23="補板",$E23="固隔",$E23="活隔", $E23="中立板",$E23="中立板(退)",$E23="固隔(退)",$E23="活固隔",$E23="立板", $E23="內頂板",$E23="內左側落板",$E23="內右側落板",$E23="內底板", $E23="內左側板",$E23="內右側板", $E23="上前平肢",$E23="上後平肢",$E23="上前立肢",$E23="上後立肢", $E23="下前立肢",$E23="下後立肢",$E23="下前平肢",$E23="下後平肢", $E23="左側落板",$E23="右側落板", $E23="外蓋背板",$E23="台面",$E23="床板",$E23="假門板", $E23="上掀門板",$E23="平掀門板",$E23="下掀門板", $E23="左門板",$E23="右門板", $E23="抽盤",$E23="抽盤抽頭", $E23="上軌道板",$E23="下軌道板",$E23="左軌道板",$E23="右軌道板",$E23="指縫擋板",$E23="左木框滑門",$E23="右木框滑門", $E23="層板",$E23="壁面層板",$E23="桌板",$E23="上封板",$E23="下封板",$E23="左封板",$E23="右封板", $E23="左圓角側板",$E23="右圓角側板",$E23="抽頭",$E23="入柱抽頭",$E23="假抽頭",$E23="背拉桿",$E23="木滑門",$E23="抽屜拉桿" ), "AA", "" ) -> AA | H23: =C11/2-4 -> -4 | I23: =IF( OR( $E23="右側板",$E23="左側板",$E23="活隔", $E23="天地蓋頂板",$E23="天地蓋底板", $E23="左門板",$E23="右門板", $E23="左側落板",$E23="右側落板", $E23="外蓋背板",$E23="活固隔", $E23="左木框滑門",$E23="右木框滑門", $E23="左鋁框滑門",$E23="右鋁框滑門", $E23="桌板",$E23="台面",$E23="床板",$E23="假門板", $E23="上掀門板",$E23="平掀門板",$E23="下掀門板", $E23="抽盤抽頭",$E23="抽盤",$E23="層板",$E23="壁面層板", $E23="上封板",$E23="下封板",$E23="左封板",$E23="右封板", $E23="抽頭",$E23="踢腳板",$E23="補板",$E23="木滑門" ), "AA", "" ) -> AA | J23: 18 | M23: =IFERROR(VLOOKUP(L23,色號!A:B,2,FALSE),"") | N23: =IFERROR(VLOOKUP(M23,色號!B:C,2,FALSE),"") | O23: =IFERROR(VLOOKUP(L23,色號!A:D,4,FALSE),"") | P23: =IF( OR($E23="左門板", $E23="右門板"), "鉸" & IF($F23<=1000, 2, IF($F23<=1800, 3, 4)), IF( $E23="入柱背板", "側", IF( $E23="外蓋背板", "面", IF( AND(COUNTIF($E$14:$E$43,"入柱背板")>0, OR($E23="頂板", $E23="底板")), "面", IF( AND(COUNTIF($E$14:$E$43,"外蓋背板")>0, OR($E23="左側板", $E23="右側板")), "側", IF( AND( COUNTIF($E$14:$E$43,"入柱背板")=0, COUNTIF($E$14:$E$43,"外蓋背板")=0, OR( AND(COUNTIF($E$14:$E$43,"背板")>0, OR($E23="左側板",$E23="右側板",$E23="頂板",$E23="底板",$E23="天地蓋右側板",$E23="天地蓋左側板",$E23="天地蓋底板",$E23="天地蓋頂板")), AND(COUNTIF($E$14:$E$43,"抽底")>0, OR($E23="右抽牆",$E23="左抽牆",$E23="前抽牆",$E23="後抽牆")) ) ), "背板溝", "" ) ) ) ) ) ) -> 鉸2 | Q23: =IF(OR($E23="天地蓋右側板",$E23="天地蓋左側板"), "側 面", IF(OR($E23="背拉桿",$E23="中立板",$E23="頂板",$E23="底板",$E23="前抽牆",$E23="後抽牆",$E23="內左側落板",$E23="內右側落板",$E23="抽屜拉桿",$E23="立板"), "側", IF(OR($E23="木滑門",$E23="鋁框滑門"), "輪", IF(OR($E23="右側板",$E23="左側板",$E23="右抽牆",$E23="左抽牆",$E23="天地蓋頂板",$E23="天地蓋底板",$E23="內頂板"), "面", IF($E23="固隔","固","") ) ) ) ) | R23: =IF( OR($E23="左側板",$E23="右側板",$E23="天地蓋左側板",$E23="天地蓋右側板",$E23="中立板",$E23="立板"), "排","") | T23: =IF($E23="中立板","面開槽？排孔？", IF($E23="木框滑門","前排孔要退喔！", IF(OR($E23="左門板",$E23="右門板",$E23="抽頭"),"把手？", IF(OR($E23="左側板",$E23="右側板",$E23="天地蓋右側板",$E23="天地蓋左側板"),"排孔？","")))) -> 把手？ | U23: =IF(E23="","",$L$10) -> 1
A24: =$C$7 -> 0 | C24: =C23+1 -> 1011 | D24: 外部 | E24: 右門板 | G24: =IF( OR( $E24="頂板",$E24="底板",$E24="右側板",$E24="左側板", $E24="天地蓋頂板",$E24="天地蓋底板",$E24="天地蓋右側板",$E24="天地蓋左側板", $E24="前抽牆",$E24="後抽牆",$E24="左抽牆",$E24="右抽牆", $E24="踢腳板",$E24="補板",$E24="固隔",$E24="活隔", $E24="中立板",$E24="中立板(退)",$E24="固隔(退)",$E24="活固隔",$E24="立板", $E24="內頂板",$E24="內左側落板",$E24="內右側落板",$E24="內底板", $E24="內左側板",$E24="內右側板", $E24="上前平肢",$E24="上後平肢",$E24="上前立肢",$E24="上後立肢", $E24="下前立肢",$E24="下後立肢",$E24="下前平肢",$E24="下後平肢", $E24="左側落板",$E24="右側落板", $E24="外蓋背板",$E24="台面",$E24="床板",$E24="假門板", $E24="上掀門板",$E24="平掀門板",$E24="下掀門板", $E24="左門板",$E24="右門板", $E24="抽盤",$E24="抽盤抽頭", $E24="上軌道板",$E24="下軌道板",$E24="左軌道板",$E24="右軌道板",$E24="指縫擋板",$E24="左木框滑門",$E24="右木框滑門", $E24="層板",$E24="壁面層板",$E24="桌板",$E24="上封板",$E24="下封板",$E24="左封板",$E24="右封板", $E24="左圓角側板",$E24="右圓角側板",$E24="抽頭",$E24="入柱抽頭",$E24="假抽頭",$E24="背拉桿",$E24="木滑門",$E24="抽屜拉桿" ), "AA", "" ) -> AA | H24: =C11/2-4 -> -4 | I24: =IF( OR( $E24="右側板",$E24="左側板",$E24="活隔", $E24="天地蓋頂板",$E24="天地蓋底板", $E24="左門板",$E24="右門板", $E24="左側落板",$E24="右側落板", $E24="外蓋背板",$E24="活固隔", $E24="左木框滑門",$E24="右木框滑門", $E24="左鋁框滑門",$E24="右鋁框滑門", $E24="桌板",$E24="台面",$E24="床板",$E24="假門板", $E24="上掀門板",$E24="平掀門板",$E24="下掀門板", $E24="抽盤抽頭",$E24="抽盤",$E24="層板",$E24="壁面層板", $E24="上封板",$E24="下封板",$E24="左封板",$E24="右封板", $E24="抽頭",$E24="踢腳板",$E24="補板",$E24="木滑門" ), "AA", "" ) -> AA | J24: 18 | M24: =IFERROR(VLOOKUP(L24,色號!A:B,2,FALSE),"") | N24: =IFERROR(VLOOKUP(M24,色號!B:C,2,FALSE),"") | O24: =IFERROR(VLOOKUP(L24,色號!A:D,4,FALSE),"") | P24: =IF( OR($E24="左門板", $E24="右門板"), "鉸" & IF($F24<=1000, 2, IF($F24<=1800, 3, 4)), IF( $E24="入柱背板", "側", IF( $E24="外蓋背板", "面", IF( AND(COUNTIF($E$14:$E$43,"入柱背板")>0, OR($E24="頂板", $E24="底板")), "面", IF( AND(COUNTIF($E$14:$E$43,"外蓋背板")>0, OR($E24="左側板", $E24="右側板")), "側", IF( AND( COUNTIF($E$14:$E$43,"入柱背板")=0, COUNTIF($E$14:$E$43,"外蓋背板")=0, OR( AND(COUNTIF($E$14:$E$43,"背板")>0, OR($E24="左側板",$E24="右側板",$E24="頂板",$E24="底板",$E24="天地蓋右側板",$E24="天地蓋左側板",$E24="天地蓋底板",$E24="天地蓋頂板")), AND(COUNTIF($E$14:$E$43,"抽底")>0, OR($E24="右抽牆",$E24="左抽牆",$E24="前抽牆",$E24="後抽牆")) ) ), "背板溝", "" ) ) ) ) ) ) -> 鉸2 | T24: =IF($E24="中立板","面開槽？排孔？", IF($E24="木框滑門","前排孔要退喔！", IF(OR($E24="左門板",$E24="右門板",$E24="抽頭"),"把手？", IF(OR($E24="左側板",$E24="右側板",$E24="天地蓋右側板",$E24="天地蓋左側板"),"排孔？","")))) -> 把手？ | U24: =IF(E24="","",$L$10) -> 1
A25: =$C$7 -> 0 | C25: =C24+1 -> 1012 | G25: =IF( OR( $E25="頂板",$E25="底板",$E25="右側板",$E25="左側板", $E25="天地蓋頂板",$E25="天地蓋底板",$E25="天地蓋右側板",$E25="天地蓋左側板", $E25="前抽牆",$E25="後抽牆",$E25="左抽牆",$E25="右抽牆", $E25="踢腳板",$E25="補板",$E25="固隔",$E25="活隔", $E25="中立板",$E25="中立板(退)",$E25="固隔(退)",$E25="活固隔",$E25="立板", $E25="內頂板",$E25="內左側落板",$E25="內右側落板",$E25="內底板", $E25="內左側板",$E25="內右側板", $E25="上前平肢",$E25="上後平肢",$E25="上前立肢",$E25="上後立肢", $E25="下前立肢",$E25="下後立肢",$E25="下前平肢",$E25="下後平肢", $E25="左側落板",$E25="右側落板", $E25="外蓋背板",$E25="台面",$E25="床板",$E25="假門板", $E25="上掀門板",$E25="平掀門板",$E25="下掀門板", $E25="左門板",$E25="右門板", $E25="抽盤",$E25="抽盤抽頭", $E25="上軌道板",$E25="下軌道板",$E25="左軌道板",$E25="右軌道板",$E25="指縫擋板",$E25="左木框滑門",$E25="右木框滑門", $E25="層板",$E25="壁面層板",$E25="桌板",$E25="上封板",$E25="下封板",$E25="左封板",$E25="右封板", $E25="左圓角側板",$E25="右圓角側板",$E25="抽頭",$E25="入柱抽頭",$E25="假抽頭",$E25="背拉桿",$E25="木滑門",$E25="抽屜拉桿" ), "AA", "" ) | I25: =IF( OR( $E25="右側板",$E25="左側板",$E25="活隔", $E25="天地蓋頂板",$E25="天地蓋底板", $E25="左門板",$E25="右門板", $E25="左側落板",$E25="右側落板", $E25="外蓋背板",$E25="活固隔", $E25="左木框滑門",$E25="右木框滑門", $E25="左鋁框滑門",$E25="右鋁框滑門", $E25="桌板",$E25="台面",$E25="床板",$E25="假門板", $E25="上掀門板",$E25="平掀門板",$E25="下掀門板", $E25="抽盤抽頭",$E25="抽盤",$E25="層板",$E25="壁面層板", $E25="上封板",$E25="下封板",$E25="左封板",$E25="右封板", $E25="抽頭",$E25="踢腳板",$E25="補板",$E25="木滑門" ), "AA", "" ) | M25: =IFERROR(VLOOKUP(L25,色號!A:B,2,FALSE),"") | N25: =IFERROR(VLOOKUP(M25,色號!B:C,2,FALSE),"") | O25: =IFERROR(VLOOKUP(L25,色號!A:D,4,FALSE),"") | P25: =IF( OR($E25="左門板", $E25="右門板"), "鉸" & IF($F25<=1000, 2, IF($F25<=1800, 3, 4)), IF( $E25="入柱背板", "側", IF( $E25="外蓋背板", "面", IF( AND(COUNTIF($E$14:$E$43,"入柱背板")>0, OR($E25="頂板", $E25="底板")), "面", IF( AND(COUNTIF($E$14:$E$43,"外蓋背板")>0, OR($E25="左側板", $E25="右側板")), "側", IF( AND( COUNTIF($E$14:$E$43,"入柱背板")=0, COUNTIF($E$14:$E$43,"外蓋背板")=0, OR( AND(COUNTIF($E$14:$E$43,"背板")>0, OR($E25="左側板",$E25="右側板",$E25="頂板",$E25="底板",$E25="天地蓋右側板",$E25="天地蓋左側板",$E25="天地蓋底板",$E25="天地蓋頂板")), AND(COUNTIF($E$14:$E$43,"抽底")>0, OR($E25="右抽牆",$E25="左抽牆",$E25="前抽牆",$E25="後抽牆")) ) ), "背板溝", "" ) ) ) ) ) ) | T25: =IF($E25="中立板","面開槽？排孔？", IF($E25="木框滑門","前排孔要退喔！", IF(OR($E25="左門板",$E25="右門板",$E25="抽頭"),"把手？", IF(OR($E25="左側板",$E25="右側板",$E25="天地蓋右側板",$E25="天地蓋左側板"),"排孔？","")))) | U25: =IF(E25="","",$L$10)
A26: =$C$7 -> 0 | C26: =C25+1 -> 1013 | G26: =IF( OR( $E26="頂板",$E26="底板",$E26="右側板",$E26="左側板", $E26="天地蓋頂板",$E26="天地蓋底板",$E26="天地蓋右側板",$E26="天地蓋左側板", $E26="前抽牆",$E26="後抽牆",$E26="左抽牆",$E26="右抽牆", $E26="踢腳板",$E26="補板",$E26="固隔",$E26="活隔", $E26="中立板",$E26="中立板(退)",$E26="固隔(退)",$E26="活固隔",$E26="立板", $E26="內頂板",$E26="內左側落板",$E26="內右側落板",$E26="內底板", $E26="內左側板",$E26="內右側板", $E26="上前平肢",$E26="上後平肢",$E26="上前立肢",$E26="上後立肢", $E26="下前立肢",$E26="下後立肢",$E26="下前平肢",$E26="下後平肢", $E26="左側落板",$E26="右側落板", $E26="外蓋背板",$E26="台面",$E26="床板",$E26="假門板", $E26="上掀門板",$E26="平掀門板",$E26="下掀門板", $E26="左門板",$E26="右門板", $E26="抽盤",$E26="抽盤抽頭", $E26="上軌道板",$E26="下軌道板",$E26="左軌道板",$E26="右軌道板",$E26="指縫擋板",$E26="左木框滑門",$E26="右木框滑門", $E26="層板",$E26="壁面層板",$E26="桌板",$E26="上封板",$E26="下封板",$E26="左封板",$E26="右封板", $E26="左圓角側板",$E26="右圓角側板",$E26="抽頭",$E26="入柱抽頭",$E26="假抽頭",$E26="背拉桿",$E26="木滑門",$E26="抽屜拉桿" ), "AA", "" ) | I26: =IF( OR( $E26="右側板",$E26="左側板",$E26="活隔", $E26="天地蓋頂板",$E26="天地蓋底板", $E26="左門板",$E26="右門板", $E26="左側落板",$E26="右側落板", $E26="外蓋背板",$E26="活固隔", $E26="左木框滑門",$E26="右木框滑門", $E26="左鋁框滑門",$E26="右鋁框滑門", $E26="桌板",$E26="台面",$E26="床板",$E26="假門板", $E26="上掀門板",$E26="平掀門板",$E26="下掀門板", $E26="抽盤抽頭",$E26="抽盤",$E26="層板",$E26="壁面層板", $E26="上封板",$E26="下封板",$E26="左封板",$E26="右封板", $E26="抽頭",$E26="踢腳板",$E26="補板",$E26="木滑門" ), "AA", "" ) | M26: =IFERROR(VLOOKUP(L26,色號!A:B,2,FALSE),"") | N26: =IFERROR(VLOOKUP(M26,色號!B:C,2,FALSE),"") | O26: =IFERROR(VLOOKUP(L26,色號!A:D,4,FALSE),"") | P26: =IF( OR($E26="左門板", $E26="右門板"), "鉸" & IF($F26<=1000, 2, IF($F26<=1800, 3, 4)), IF( $E26="入柱背板", "側", IF( $E26="外蓋背板", "面", IF( AND(COUNTIF($E$14:$E$43,"入柱背板")>0, OR($E26="頂板", $E26="底板")), "面", IF( AND(COUNTIF($E$14:$E$43,"外蓋背板")>0, OR($E26="左側板", $E26="右側板")), "側", IF( AND( COUNTIF($E$14:$E$43,"入柱背板")=0, COUNTIF($E$14:$E$43,"外蓋背板")=0, OR( AND(COUNTIF($E$14:$E$43,"背板")>0, OR($E26="左側板",$E26="右側板",$E26="頂板",$E26="底板",$E26="天地蓋右側板",$E26="天地蓋左側板",$E26="天地蓋底板",$E26="天地蓋頂板")), AND(COUNTIF($E$14:$E$43,"抽底")>0, OR($E26="右抽牆",$E26="左抽牆",$E26="前抽牆",$E26="後抽牆")) ) ), "背板溝", "" ) ) ) ) ) ) | T26: =IF($E26="中立板","面開槽？排孔？", IF($E26="木框滑門","前排孔要退喔！", IF(OR($E26="左門板",$E26="右門板",$E26="抽頭"),"把手？", IF(OR($E26="左側板",$E26="右側板",$E26="天地蓋右側板",$E26="天地蓋左側板"),"排孔？","")))) | U26: =IF(E26="","",$L$10)
A27: =$C$7 -> 0 | C27: =C26+1 -> 1014 | G27: =IF( OR( $E27="頂板",$E27="底板",$E27="右側板",$E27="左側板", $E27="天地蓋頂板",$E27="天地蓋底板",$E27="天地蓋右側板",$E27="天地蓋左側板", $E27="前抽牆",$E27="後抽牆",$E27="左抽牆",$E27="右抽牆", $E27="踢腳板",$E27="補板",$E27="固隔",$E27="活隔", $E27="中立板",$E27="中立板(退)",$E27="固隔(退)",$E27="活固隔",$E27="立板", $E27="內頂板",$E27="內左側落板",$E27="內右側落板",$E27="內底板", $E27="內左側板",$E27="內右側板", $E27="上前平肢",$E27="上後平肢",$E27="上前立肢",$E27="上後立肢", $E27="下前立肢",$E27="下後立肢",$E27="下前平肢",$E27="下後平肢", $E27="左側落板",$E27="右側落板", $E27="外蓋背板",$E27="台面",$E27="床板",$E27="假門板", $E27="上掀門板",$E27="平掀門板",$E27="下掀門板", $E27="左門板",$E27="右門板", $E27="抽盤",$E27="抽盤抽頭", $E27="上軌道板",$E27="下軌道板",$E27="左軌道板",$E27="右軌道板",$E27="指縫擋板",$E27="左木框滑門",$E27="右木框滑門", $E27="層板",$E27="壁面層板",$E27="桌板",$E27="上封板",$E27="下封板",$E27="左封板",$E27="右封板", $E27="左圓角側板",$E27="右圓角側板",$E27="抽頭",$E27="入柱抽頭",$E27="假抽頭",$E27="背拉桿",$E27="木滑門",$E27="抽屜拉桿" ), "AA", "" ) | I27: =IF( OR( $E27="右側板",$E27="左側板",$E27="活隔", $E27="天地蓋頂板",$E27="天地蓋底板", $E27="左門板",$E27="右門板", $E27="左側落板",$E27="右側落板", $E27="外蓋背板",$E27="活固隔", $E27="左木框滑門",$E27="右木框滑門", $E27="左鋁框滑門",$E27="右鋁框滑門", $E27="桌板",$E27="台面",$E27="床板",$E27="假門板", $E27="上掀門板",$E27="平掀門板",$E27="下掀門板", $E27="抽盤抽頭",$E27="抽盤",$E27="層板",$E27="壁面層板", $E27="上封板",$E27="下封板",$E27="左封板",$E27="右封板", $E27="抽頭",$E27="踢腳板",$E27="補板",$E27="木滑門" ), "AA", "" ) | M27: =IFERROR(VLOOKUP(L27,色號!A:B,2,FALSE),"") | N27: =IFERROR(VLOOKUP(M27,色號!B:C,2,FALSE),"") | O27: =IFERROR(VLOOKUP(L27,色號!A:D,4,FALSE),"") | P27: =IF( OR($E27="左門板", $E27="右門板"), "鉸" & IF($F27<=1000, 2, IF($F27<=1800, 3, 4)), IF( $E27="入柱背板", "側", IF( $E27="外蓋背板", "面", IF( AND(COUNTIF($E$14:$E$43,"入柱背板")>0, OR($E27="頂板", $E27="底板")), "面", IF( AND(COUNTIF($E$14:$E$43,"外蓋背板")>0, OR($E27="左側板", $E27="右側板")), "側", IF( AND( COUNTIF($E$14:$E$43,"入柱背板")=0, COUNTIF($E$14:$E$43,"外蓋背板")=0, OR( AND(COUNTIF($E$14:$E$43,"背板")>0, OR($E27="左側板",$E27="右側板",$E27="頂板",$E27="底板",$E27="天地蓋右側板",$E27="天地蓋左側板",$E27="天地蓋底板",$E27="天地蓋頂板")), AND(COUNTIF($E$14:$E$43,"抽底")>0, OR($E27="右抽牆",$E27="左抽牆",$E27="前抽牆",$E27="後抽牆")) ) ), "背板溝", "" ) ) ) ) ) ) | T27: =IF($E27="中立板","面開槽？排孔？", IF($E27="木框滑門","前排孔要退喔！", IF(OR($E27="左門板",$E27="右門板",$E27="抽頭"),"把手？", IF(OR($E27="左側板",$E27="右側板",$E27="天地蓋右側板",$E27="天地蓋左側板"),"排孔？","")))) | U27: =IF(E27="","",$L$10)
A28: =$C$7 -> 0 | C28: =C27+1 -> 1015 | G28: =IF( OR( $E28="頂板",$E28="底板",$E28="右側板",$E28="左側板", $E28="天地蓋頂板",$E28="天地蓋底板",$E28="天地蓋右側板",$E28="天地蓋左側板", $E28="前抽牆",$E28="後抽牆",$E28="左抽牆",$E28="右抽牆", $E28="踢腳板",$E28="補板",$E28="固隔",$E28="活隔", $E28="中立板",$E28="中立板(退)",$E28="固隔(退)",$E28="活固隔",$E28="立板", $E28="內頂板",$E28="內左側落板",$E28="內右側落板",$E28="內底板", $E28="內左側板",$E28="內右側板", $E28="上前平肢",$E28="上後平肢",$E28="上前立肢",$E28="上後立肢", $E28="下前立肢",$E28="下後立肢",$E28="下前平肢",$E28="下後平肢", $E28="左側落板",$E28="右側落板", $E28="外蓋背板",$E28="台面",$E28="床板",$E28="假門板", $E28="上掀門板",$E28="平掀門板",$E28="下掀門板", $E28="左門板",$E28="右門板", $E28="抽盤",$E28="抽盤抽頭", $E28="上軌道板",$E28="下軌道板",$E28="左軌道板",$E28="右軌道板",$E28="指縫擋板",$E28="左木框滑門",$E28="右木框滑門", $E28="層板",$E28="壁面層板",$E28="桌板",$E28="上封板",$E28="下封板",$E28="左封板",$E28="右封板", $E28="左圓角側板",$E28="右圓角側板",$E28="抽頭",$E28="入柱抽頭",$E28="假抽頭",$E28="背拉桿",$E28="木滑門",$E28="抽屜拉桿" ), "AA", "" ) | I28: =IF( OR( $E28="右側板",$E28="左側板",$E28="活隔", $E28="天地蓋頂板",$E28="天地蓋底板", $E28="左門板",$E28="右門板", $E28="左側落板",$E28="右側落板", $E28="外蓋背板",$E28="活固隔", $E28="左木框滑門",$E28="右木框滑門", $E28="左鋁框滑門",$E28="右鋁框滑門", $E28="桌板",$E28="台面",$E28="床板",$E28="假門板", $E28="上掀門板",$E28="平掀門板",$E28="下掀門板", $E28="抽盤抽頭",$E28="抽盤",$E28="層板",$E28="壁面層板", $E28="上封板",$E28="下封板",$E28="左封板",$E28="右封板", $E28="抽頭",$E28="踢腳板",$E28="補板",$E28="木滑門" ), "AA", "" ) | M28: =IFERROR(VLOOKUP(L28,色號!A:B,2,FALSE),"") | N28: =IFERROR(VLOOKUP(M28,色號!B:C,2,FALSE),"") | O28: =IFERROR(VLOOKUP(L28,色號!A:D,4,FALSE),"") | P28: =IF( OR($E28="左門板", $E28="右門板"), "鉸" & IF($F28<=1000, 2, IF($F28<=1800, 3, 4)), IF( $E28="入柱背板", "側", IF( $E28="外蓋背板", "面", IF( AND(COUNTIF($E$14:$E$43,"入柱背板")>0, OR($E28="頂板", $E28="底板")), "面", IF( AND(COUNTIF($E$14:$E$43,"外蓋背板")>0, OR($E28="左側板", $E28="右側板")), "側", IF( AND( COUNTIF($E$14:$E$43,"入柱背板")=0, COUNTIF($E$14:$E$43,"外蓋背板")=0, OR( AND(COUNTIF($E$14:$E$43,"背板")>0, OR($E28="左側板",$E28="右側板",$E28="頂板",$E28="底板",$E28="天地蓋右側板",$E28="天地蓋左側板",$E28="天地蓋底板",$E28="天地蓋頂板")), AND(COUNTIF($E$14:$E$43,"抽底")>0, OR($E28="右抽牆",$E28="左抽牆",$E28="前抽牆",$E28="後抽牆")) ) ), "背板溝", "" ) ) ) ) ) ) | T28: =IF($E28="中立板","面開槽？排孔？", IF($E28="木框滑門","前排孔要退喔！", IF(OR($E28="左門板",$E28="右門板",$E28="抽頭"),"把手？", IF(OR($E28="左側板",$E28="右側板",$E28="天地蓋右側板",$E28="天地蓋左側板"),"排孔？","")))) | U28: =IF(E28="","",$L$10)
A29: =$C$7 -> 0 | C29: =C28+1 -> 1016 | G29: =IF( OR( $E29="頂板",$E29="底板",$E29="右側板",$E29="左側板", $E29="天地蓋頂板",$E29="天地蓋底板",$E29="天地蓋右側板",$E29="天地蓋左側板", $E29="前抽牆",$E29="後抽牆",$E29="左抽牆",$E29="右抽牆", $E29="踢腳板",$E29="補板",$E29="固隔",$E29="活隔", $E29="中立板",$E29="中立板(退)",$E29="固隔(退)",$E29="活固隔",$E29="立板", $E29="內頂板",$E29="內左側落板",$E29="內右側落板",$E29="內底板", $E29="內左側板",$E29="內右側板", $E29="上前平肢",$E29="上後平肢",$E29="上前立肢",$E29="上後立肢", $E29="下前立肢",$E29="下後立肢",$E29="下前平肢",$E29="下後平肢", $E29="左側落板",$E29="右側落板", $E29="外蓋背板",$E29="台面",$E29="床板",$E29="假門板", $E29="上掀門板",$E29="平掀門板",$E29="下掀門板", $E29="左門板",$E29="右門板", $E29="抽盤",$E29="抽盤抽頭", $E29="上軌道板",$E29="下軌道板",$E29="左軌道板",$E29="右軌道板",$E29="指縫擋板",$E29="左木框滑門",$E29="右木框滑門", $E29="層板",$E29="壁面層板",$E29="桌板",$E29="上封板",$E29="下封板",$E29="左封板",$E29="右封板", $E29="左圓角側板",$E29="右圓角側板",$E29="抽頭",$E29="入柱抽頭",$E29="假抽頭",$E29="背拉桿",$E29="木滑門",$E29="抽屜拉桿" ), "AA", "" ) | I29: =IF( OR( $E29="右側板",$E29="左側板",$E29="活隔", $E29="天地蓋頂板",$E29="天地蓋底板", $E29="左門板",$E29="右門板", $E29="左側落板",$E29="右側落板", $E29="外蓋背板",$E29="活固隔", $E29="左木框滑門",$E29="右木框滑門", $E29="左鋁框滑門",$E29="右鋁框滑門", $E29="桌板",$E29="台面",$E29="床板",$E29="假門板", $E29="上掀門板",$E29="平掀門板",$E29="下掀門板", $E29="抽盤抽頭",$E29="抽盤",$E29="層板",$E29="壁面層板", $E29="上封板",$E29="下封板",$E29="左封板",$E29="右封板", $E29="抽頭",$E29="踢腳板",$E29="補板",$E29="木滑門" ), "AA", "" ) | M29: =IFERROR(VLOOKUP(L29,色號!A:B,2,FALSE),"") | N29: =IFERROR(VLOOKUP(M29,色號!B:C,2,FALSE),"") | O29: =IFERROR(VLOOKUP(L29,色號!A:D,4,FALSE),"") | P29: =IF( OR($E29="左門板", $E29="右門板"), "鉸" & IF($F29<=1000, 2, IF($F29<=1800, 3, 4)), IF( $E29="入柱背板", "側", IF( $E29="外蓋背板", "面", IF( AND(COUNTIF($E$14:$E$43,"入柱背板")>0, OR($E29="頂板", $E29="底板")), "面", IF( AND(COUNTIF($E$14:$E$43,"外蓋背板")>0, OR($E29="左側板", $E29="右側板")), "側", IF( AND( COUNTIF($E$14:$E$43,"入柱背板")=0, COUNTIF($E$14:$E$43,"外蓋背板")=0, OR( AND(COUNTIF($E$14:$E$43,"背板")>0, OR($E29="左側板",$E29="右側板",$E29="頂板",$E29="底板",$E29="天地蓋右側板",$E29="天地蓋左側板",$E29="天地蓋底板",$E29="天地蓋頂板")), AND(COUNTIF($E$14:$E$43,"抽底")>0, OR($E29="右抽牆",$E29="左抽牆",$E29="前抽牆",$E29="後抽牆")) ) ), "背板溝", "" ) ) ) ) ) ) | T29: =IF($E29="中立板","面開槽？排孔？", IF($E29="木框滑門","前排孔要退喔！", IF(OR($E29="左門板",$E29="右門板",$E29="抽頭"),"把手？", IF(OR($E29="左側板",$E29="右側板",$E29="天地蓋右側板",$E29="天地蓋左側板"),"排孔？","")))) | U29: =IF(E29="","",$L$10)
A30: =$C$7 -> 0 | C30: =C29+1 -> 1017 | G30: =IF( OR( $E30="頂板",$E30="底板",$E30="右側板",$E30="左側板", $E30="天地蓋頂板",$E30="天地蓋底板",$E30="天地蓋右側板",$E30="天地蓋左側板", $E30="前抽牆",$E30="後抽牆",$E30="左抽牆",$E30="右抽牆", $E30="踢腳板",$E30="補板",$E30="固隔",$E30="活隔", $E30="中立板",$E30="中立板(退)",$E30="固隔(退)",$E30="活固隔",$E30="立板", $E30="內頂板",$E30="內左側落板",$E30="內右側落板",$E30="內底板", $E30="內左側板",$E30="內右側板", $E30="上前平肢",$E30="上後平肢",$E30="上前立肢",$E30="上後立肢", $E30="下前立肢",$E30="下後立肢",$E30="下前平肢",$E30="下後平肢", $E30="左側落板",$E30="右側落板", $E30="外蓋背板",$E30="台面",$E30="床板",$E30="假門板", $E30="上掀門板",$E30="平掀門板",$E30="下掀門板", $E30="左門板",$E30="右門板", $E30="抽盤",$E30="抽盤抽頭", $E30="上軌道板",$E30="下軌道板",$E30="左軌道板",$E30="右軌道板",$E30="指縫擋板",$E30="左木框滑門",$E30="右木框滑門", $E30="層板",$E30="壁面層板",$E30="桌板",$E30="上封板",$E30="下封板",$E30="左封板",$E30="右封板", $E30="左圓角側板",$E30="右圓角側板",$E30="抽頭",$E30="入柱抽頭",$E30="假抽頭",$E30="背拉桿",$E30="木滑門",$E30="抽屜拉桿" ), "AA", "" ) | I30: =IF( OR( $E30="右側板",$E30="左側板",$E30="活隔", $E30="天地蓋頂板",$E30="天地蓋底板", $E30="左門板",$E30="右門板", $E30="左側落板",$E30="右側落板", $E30="外蓋背板",$E30="活固隔", $E30="左木框滑門",$E30="右木框滑門", $E30="左鋁框滑門",$E30="右鋁框滑門", $E30="桌板",$E30="台面",$E30="床板",$E30="假門板", $E30="上掀門板",$E30="平掀門板",$E30="下掀門板", $E30="抽盤抽頭",$E30="抽盤",$E30="層板",$E30="壁面層板", $E30="上封板",$E30="下封板",$E30="左封板",$E30="右封板", $E30="抽頭",$E30="踢腳板",$E30="補板",$E30="木滑門" ), "AA", "" ) | M30: =IFERROR(VLOOKUP(L30,色號!A:B,2,FALSE),"") | N30: =IFERROR(VLOOKUP(M30,色號!B:C,2,FALSE),"") | O30: =IFERROR(VLOOKUP(L30,色號!A:D,4,FALSE),"") | P30: =IF( OR($E30="左門板", $E30="右門板"), "鉸" & IF($F30<=1000, 2, IF($F30<=1800, 3, 4)), IF( $E30="入柱背板", "側", IF( $E30="外蓋背板", "面", IF( AND(COUNTIF($E$14:$E$43,"入柱背板")>0, OR($E30="頂板", $E30="底板")), "面", IF( AND(COUNTIF($E$14:$E$43,"外蓋背板")>0, OR($E30="左側板", $E30="右側板")), "側", IF( AND( COUNTIF($E$14:$E$43,"入柱背板")=0, COUNTIF($E$14:$E$43,"外蓋背板")=0, OR( AND(COUNTIF($E$14:$E$43,"背板")>0, OR($E30="左側板",$E30="右側板",$E30="頂板",$E30="底板",$E30="天地蓋右側板",$E30="天地蓋左側板",$E30="天地蓋底板",$E30="天地蓋頂板")), AND(COUNTIF($E$14:$E$43,"抽底")>0, OR($E30="右抽牆",$E30="左抽牆",$E30="前抽牆",$E30="後抽牆")) ) ), "背板溝", "" ) ) ) ) ) ) | Q30: =IF(OR($E30="天地蓋右側板",$E30="天地蓋左側板"), "側 面", IF(OR($E30="背拉桿",$E30="中立板",$E30="頂板",$E30="底板",$E30="前抽牆",$E30="後抽牆",$E30="內左側落板",$E30="內右側落板",$E30="抽屜拉桿",$E30="立板"), "側", IF(OR($E30="木滑門",$E30="鋁框滑門"), "輪", IF(OR($E30="右側板",$E30="左側板",$E30="右抽牆",$E30="左抽牆",$E30="天地蓋頂板",$E30="天地蓋底板",$E30="內頂板"), "面", IF($E30="固隔","固","") ) ) ) ) | R30: =IF( OR($E30="左側板",$E30="右側板",$E30="天地蓋左側板",$E30="天地蓋右側板",$E30="中立板",$E30="立板"), "排","") | T30: =IF($E30="中立板","面開槽？排孔？", IF($E30="木框滑門","前排孔要退喔！", IF(OR($E30="左門板",$E30="右門板",$E30="抽頭"),"把手？", IF(OR($E30="左側板",$E30="右側板",$E30="天地蓋右側板",$E30="天地蓋左側板"),"排孔？","")))) | U30: =IF(E30="","",$L$10)
A31: =$C$7 -> 0 | C31: =C30+1 -> 1018 | G31: =IF( OR( $E31="頂板",$E31="底板",$E31="右側板",$E31="左側板", $E31="天地蓋頂板",$E31="天地蓋底板",$E31="天地蓋右側板",$E31="天地蓋左側板", $E31="前抽牆",$E31="後抽牆",$E31="左抽牆",$E31="右抽牆", $E31="踢腳板",$E31="補板",$E31="固隔",$E31="活隔", $E31="中立板",$E31="中立板(退)",$E31="固隔(退)",$E31="活固隔",$E31="立板", $E31="內頂板",$E31="內左側落板",$E31="內右側落板",$E31="內底板", $E31="內左側板",$E31="內右側板", $E31="上前平肢",$E31="上後平肢",$E31="上前立肢",$E31="上後立肢", $E31="下前立肢",$E31="下後立肢",$E31="下前平肢",$E31="下後平肢", $E31="左側落板",$E31="右側落板", $E31="外蓋背板",$E31="台面",$E31="床板",$E31="假門板", $E31="上掀門板",$E31="平掀門板",$E31="下掀門板", $E31="左門板",$E31="右門板", $E31="抽盤",$E31="抽盤抽頭", $E31="上軌道板",$E31="下軌道板",$E31="左軌道板",$E31="右軌道板",$E31="指縫擋板",$E31="左木框滑門",$E31="右木框滑門", $E31="層板",$E31="壁面層板",$E31="桌板",$E31="上封板",$E31="下封板",$E31="左封板",$E31="右封板", $E31="左圓角側板",$E31="右圓角側板",$E31="抽頭",$E31="入柱抽頭",$E31="假抽頭",$E31="背拉桿",$E31="木滑門",$E31="抽屜拉桿" ), "AA", "" ) | I31: =IF( OR( $E31="右側板",$E31="左側板",$E31="活隔", $E31="天地蓋頂板",$E31="天地蓋底板", $E31="左門板",$E31="右門板", $E31="左側落板",$E31="右側落板", $E31="外蓋背板",$E31="活固隔", $E31="左木框滑門",$E31="右木框滑門", $E31="左鋁框滑門",$E31="右鋁框滑門", $E31="桌板",$E31="台面",$E31="床板",$E31="假門板", $E31="上掀門板",$E31="平掀門板",$E31="下掀門板", $E31="抽盤抽頭",$E31="抽盤",$E31="層板",$E31="壁面層板", $E31="上封板",$E31="下封板",$E31="左封板",$E31="右封板", $E31="抽頭",$E31="踢腳板",$E31="補板",$E31="木滑門" ), "AA", "" ) | M31: =IFERROR(VLOOKUP(L31,色號!A:B,2,FALSE),"") | N31: =IFERROR(VLOOKUP(M31,色號!B:C,2,FALSE),"") | O31: =IFERROR(VLOOKUP(L31,色號!A:D,4,FALSE),"") | P31: =IF( OR($E31="左門板", $E31="右門板"), "鉸" & IF($F31<=1000, 2, IF($F31<=1800, 3, 4)), IF( $E31="入柱背板", "側", IF( $E31="外蓋背板", "面", IF( AND(COUNTIF($E$14:$E$43,"入柱背板")>0, OR($E31="頂板", $E31="底板")), "面", IF( AND(COUNTIF($E$14:$E$43,"外蓋背板")>0, OR($E31="左側板", $E31="右側板")), "側", IF( AND( COUNTIF($E$14:$E$43,"入柱背板")=0, COUNTIF($E$14:$E$43,"外蓋背板")=0, OR( AND(COUNTIF($E$14:$E$43,"背板")>0, OR($E31="左側板",$E31="右側板",$E31="頂板",$E31="底板",$E31="天地蓋右側板",$E31="天地蓋左側板",$E31="天地蓋底板",$E31="天地蓋頂板")), AND(COUNTIF($E$14:$E$43,"抽底")>0, OR($E31="右抽牆",$E31="左抽牆",$E31="前抽牆",$E31="後抽牆")) ) ), "背板溝", "" ) ) ) ) ) ) | Q31: =IF(OR($E31="天地蓋右側板",$E31="天地蓋左側板"), "側 面", IF(OR($E31="背拉桿",$E31="中立板",$E31="頂板",$E31="底板",$E31="前抽牆",$E31="後抽牆",$E31="內左側落板",$E31="內右側落板",$E31="抽屜拉桿",$E31="立板"), "側", IF(OR($E31="木滑門",$E31="鋁框滑門"), "輪", IF(OR($E31="右側板",$E31="左側板",$E31="右抽牆",$E31="左抽牆",$E31="天地蓋頂板",$E31="天地蓋底板",$E31="內頂板"), "面", IF($E31="固隔","固","") ) ) ) ) | R31: =IF( OR($E31="左側板",$E31="右側板",$E31="天地蓋左側板",$E31="天地蓋右側板",$E31="中立板",$E31="立板"), "排","") | T31: =IF($E31="中立板","面開槽？排孔？", IF($E31="木框滑門","前排孔要退喔！", IF(OR($E31="左門板",$E31="右門板",$E31="抽頭"),"把手？", IF(OR($E31="左側板",$E31="右側板",$E31="天地蓋右側板",$E31="天地蓋左側板"),"排孔？","")))) | U31: =IF(E31="","",$L$10)
A32: =$C$7 -> 0 | C32: =C31+1 -> 1019 | G32: =IF( OR( $E32="頂板",$E32="底板",$E32="右側板",$E32="左側板", $E32="天地蓋頂板",$E32="天地蓋底板",$E32="天地蓋右側板",$E32="天地蓋左側板", $E32="前抽牆",$E32="後抽牆",$E32="左抽牆",$E32="右抽牆", $E32="踢腳板",$E32="補板",$E32="固隔",$E32="活隔", $E32="中立板",$E32="中立板(退)",$E32="固隔(退)",$E32="活固隔",$E32="立板", $E32="內頂板",$E32="內左側落板",$E32="內右側落板",$E32="內底板", $E32="內左側板",$E32="內右側板", $E32="上前平肢",$E32="上後平肢",$E32="上前立肢",$E32="上後立肢", $E32="下前立肢",$E32="下後立肢",$E32="下前平肢",$E32="下後平肢", $E32="左側落板",$E32="右側落板", $E32="外蓋背板",$E32="台面",$E32="床板",$E32="假門板", $E32="上掀門板",$E32="平掀門板",$E32="下掀門板", $E32="左門板",$E32="右門板", $E32="抽盤",$E32="抽盤抽頭", $E32="上軌道板",$E32="下軌道板",$E32="左軌道板",$E32="右軌道板",$E32="指縫擋板",$E32="左木框滑門",$E32="右木框滑門", $E32="層板",$E32="壁面層板",$E32="桌板",$E32="上封板",$E32="下封板",$E32="左封板",$E32="右封板", $E32="左圓角側板",$E32="右圓角側板",$E32="抽頭",$E32="入柱抽頭",$E32="假抽頭",$E32="背拉桿",$E32="木滑門",$E32="抽屜拉桿" ), "AA", "" ) | I32: =IF( OR( $E32="右側板",$E32="左側板",$E32="活隔", $E32="天地蓋頂板",$E32="天地蓋底板", $E32="左門板",$E32="右門板", $E32="左側落板",$E32="右側落板", $E32="外蓋背板",$E32="活固隔", $E32="左木框滑門",$E32="右木框滑門", $E32="左鋁框滑門",$E32="右鋁框滑門", $E32="桌板",$E32="台面",$E32="床板",$E32="假門板", $E32="上掀門板",$E32="平掀門板",$E32="下掀門板", $E32="抽盤抽頭",$E32="抽盤",$E32="層板",$E32="壁面層板", $E32="上封板",$E32="下封板",$E32="左封板",$E32="右封板", $E32="抽頭",$E32="踢腳板",$E32="補板",$E32="木滑門" ), "AA", "" ) | M32: =IFERROR(VLOOKUP(L32,色號!A:B,2,FALSE),"") | N32: =IFERROR(VLOOKUP(M32,色號!B:C,2,FALSE),"") | O32: =IFERROR(VLOOKUP(L32,色號!A:D,4,FALSE),"") | P32: =IF( OR($E32="左門板", $E32="右門板"), "鉸" & IF($F32<=1000, 2, IF($F32<=1800, 3, 4)), IF( $E32="入柱背板", "側", IF( $E32="外蓋背板", "面", IF( AND(COUNTIF($E$14:$E$43,"入柱背板")>0, OR($E32="頂板", $E32="底板")), "面", IF( AND(COUNTIF($E$14:$E$43,"外蓋背板")>0, OR($E32="左側板", $E32="右側板")), "側", IF( AND( COUNTIF($E$14:$E$43,"入柱背板")=0, COUNTIF($E$14:$E$43,"外蓋背板")=0, OR( AND(COUNTIF($E$14:$E$43,"背板")>0, OR($E32="左側板",$E32="右側板",$E32="頂板",$E32="底板",$E32="天地蓋右側板",$E32="天地蓋左側板",$E32="天地蓋底板",$E32="天地蓋頂板")), AND(COUNTIF($E$14:$E$43,"抽底")>0, OR($E32="右抽牆",$E32="左抽牆",$E32="前抽牆",$E32="後抽牆")) ) ), "背板溝", "" ) ) ) ) ) ) | Q32: =IF(OR($E32="天地蓋右側板",$E32="天地蓋左側板"), "側 面", IF(OR($E32="背拉桿",$E32="中立板",$E32="頂板",$E32="底板",$E32="前抽牆",$E32="後抽牆",$E32="內左側落板",$E32="內右側落板",$E32="抽屜拉桿",$E32="立板"), "側", IF(OR($E32="木滑門",$E32="鋁框滑門"), "輪", IF(OR($E32="右側板",$E32="左側板",$E32="右抽牆",$E32="左抽牆",$E32="天地蓋頂板",$E32="天地蓋底板",$E32="內頂板"), "面", IF($E32="固隔","固","") ) ) ) ) | R32: =IF( OR($E32="左側板",$E32="右側板",$E32="天地蓋左側板",$E32="天地蓋右側板",$E32="中立板",$E32="立板"), "排","") | T32: =IF($E32="中立板","面開槽？排孔？", IF($E32="木框滑門","前排孔要退喔！", IF(OR($E32="左門板",$E32="右門板",$E32="抽頭"),"把手？", IF(OR($E32="左側板",$E32="右側板",$E32="天地蓋右側板",$E32="天地蓋左側板"),"排孔？","")))) | U32: =IF(E32="","",$L$10)
A33: =$C$7 -> 0 | C33: =C32+1 -> 1020 | G33: =IF( OR( $E33="頂板",$E33="底板",$E33="右側板",$E33="左側板", $E33="天地蓋頂板",$E33="天地蓋底板",$E33="天地蓋右側板",$E33="天地蓋左側板", $E33="前抽牆",$E33="後抽牆",$E33="左抽牆",$E33="右抽牆", $E33="踢腳板",$E33="補板",$E33="固隔",$E33="活隔", $E33="中立板",$E33="中立板(退)",$E33="固隔(退)",$E33="活固隔",$E33="立板", $E33="內頂板",$E33="內左側落板",$E33="內右側落板",$E33="內底板", $E33="內左側板",$E33="內右側板", $E33="上前平肢",$E33="上後平肢",$E33="上前立肢",$E33="上後立肢", $E33="下前立肢",$E33="下後立肢",$E33="下前平肢",$E33="下後平肢", $E33="左側落板",$E33="右側落板", $E33="外蓋背板",$E33="台面",$E33="床板",$E33="假門板", $E33="上掀門板",$E33="平掀門板",$E33="下掀門板", $E33="左門板",$E33="右門板", $E33="抽盤",$E33="抽盤抽頭", $E33="上軌道板",$E33="下軌道板",$E33="左軌道板",$E33="右軌道板",$E33="指縫擋板",$E33="左木框滑門",$E33="右木框滑門", $E33="層板",$E33="壁面層板",$E33="桌板",$E33="上封板",$E33="下封板",$E33="左封板",$E33="右封板", $E33="左圓角側板",$E33="右圓角側板",$E33="抽頭",$E33="入柱抽頭",$E33="假抽頭",$E33="背拉桿",$E33="木滑門",$E33="抽屜拉桿" ), "AA", "" ) | I33: =IF( OR( $E33="右側板",$E33="左側板",$E33="活隔", $E33="天地蓋頂板",$E33="天地蓋底板", $E33="左門板",$E33="右門板", $E33="左側落板",$E33="右側落板", $E33="外蓋背板",$E33="活固隔", $E33="左木框滑門",$E33="右木框滑門", $E33="左鋁框滑門",$E33="右鋁框滑門", $E33="桌板",$E33="台面",$E33="床板",$E33="假門板", $E33="上掀門板",$E33="平掀門板",$E33="下掀門板", $E33="抽盤抽頭",$E33="抽盤",$E33="層板",$E33="壁面層板", $E33="上封板",$E33="下封板",$E33="左封板",$E33="右封板", $E33="抽頭",$E33="踢腳板",$E33="補板",$E33="木滑門" ), "AA", "" ) | M33: =IFERROR(VLOOKUP(L33,色號!A:B,2,FALSE),"") | N33: =IFERROR(VLOOKUP(M33,色號!B:C,2,FALSE),"") | O33: =IFERROR(VLOOKUP(L33,色號!A:D,4,FALSE),"") | P33: =IF( OR($E33="左門板", $E33="右門板"), "鉸" & IF($F33<=1000, 2, IF($F33<=1800, 3, 4)), IF( $E33="入柱背板", "側", IF( $E33="外蓋背板", "面", IF( AND(COUNTIF($E$14:$E$43,"入柱背板")>0, OR($E33="頂板", $E33="底板")), "面", IF( AND(COUNTIF($E$14:$E$43,"外蓋背板")>0, OR($E33="左側板", $E33="右側板")), "側", IF( AND( COUNTIF($E$14:$E$43,"入柱背板")=0, COUNTIF($E$14:$E$43,"外蓋背板")=0, OR( AND(COUNTIF($E$14:$E$43,"背板")>0, OR($E33="左側板",$E33="右側板",$E33="頂板",$E33="底板",$E33="天地蓋右側板",$E33="天地蓋左側板",$E33="天地蓋底板",$E33="天地蓋頂板")), AND(COUNTIF($E$14:$E$43,"抽底")>0, OR($E33="右抽牆",$E33="左抽牆",$E33="前抽牆",$E33="後抽牆")) ) ), "背板溝", "" ) ) ) ) ) ) | Q33: =IF(OR($E33="天地蓋右側板",$E33="天地蓋左側板"), "側 面", IF(OR($E33="背拉桿",$E33="中立板",$E33="頂板",$E33="底板",$E33="前抽牆",$E33="後抽牆",$E33="內左側落板",$E33="內右側落板",$E33="抽屜拉桿",$E33="立板"), "側", IF(OR($E33="木滑門",$E33="鋁框滑門"), "輪", IF(OR($E33="右側板",$E33="左側板",$E33="右抽牆",$E33="左抽牆",$E33="天地蓋頂板",$E33="天地蓋底板",$E33="內頂板"), "面", IF($E33="固隔","固","") ) ) ) ) | R33: =IF( OR($E33="左側板",$E33="右側板",$E33="天地蓋左側板",$E33="天地蓋右側板",$E33="中立板",$E33="立板"), "排","") | T33: =IF($E33="中立板","面開槽？排孔？", IF($E33="木框滑門","前排孔要退喔！", IF(OR($E33="左門板",$E33="右門板",$E33="抽頭"),"把手？", IF(OR($E33="左側板",$E33="右側板",$E33="天地蓋右側板",$E33="天地蓋左側板"),"排孔？","")))) | U33: =IF(E33="","",$L$10)
A34: =$C$7 -> 0 | C34: =C33+1 -> 1021 | G34: =IF( OR( $E34="頂板",$E34="底板",$E34="右側板",$E34="左側板", $E34="天地蓋頂板",$E34="天地蓋底板",$E34="天地蓋右側板",$E34="天地蓋左側板", $E34="前抽牆",$E34="後抽牆",$E34="左抽牆",$E34="右抽牆", $E34="踢腳板",$E34="補板",$E34="固隔",$E34="活隔", $E34="中立板",$E34="中立板(退)",$E34="固隔(退)",$E34="活固隔",$E34="立板", $E34="內頂板",$E34="內左側落板",$E34="內右側落板",$E34="內底板", $E34="內左側板",$E34="內右側板", $E34="上前平肢",$E34="上後平肢",$E34="上前立肢",$E34="上後立肢", $E34="下前立肢",$E34="下後立肢",$E34="下前平肢",$E34="下後平肢", $E34="左側落板",$E34="右側落板", $E34="外蓋背板",$E34="台面",$E34="床板",$E34="假門板", $E34="上掀門板",$E34="平掀門板",$E34="下掀門板", $E34="左門板",$E34="右門板", $E34="抽盤",$E34="抽盤抽頭", $E34="上軌道板",$E34="下軌道板",$E34="左軌道板",$E34="右軌道板",$E34="指縫擋板",$E34="左木框滑門",$E34="右木框滑門", $E34="層板",$E34="壁面層板",$E34="桌板",$E34="上封板",$E34="下封板",$E34="左封板",$E34="右封板", $E34="左圓角側板",$E34="右圓角側板",$E34="抽頭",$E34="入柱抽頭",$E34="假抽頭",$E34="背拉桿",$E34="木滑門",$E34="抽屜拉桿" ), "AA", "" ) | I34: =IF( OR( $E34="右側板",$E34="左側板",$E34="活隔", $E34="天地蓋頂板",$E34="天地蓋底板", $E34="左門板",$E34="右門板", $E34="左側落板",$E34="右側落板", $E34="外蓋背板",$E34="活固隔", $E34="左木框滑門",$E34="右木框滑門", $E34="左鋁框滑門",$E34="右鋁框滑門", $E34="桌板",$E34="台面",$E34="床板",$E34="假門板", $E34="上掀門板",$E34="平掀門板",$E34="下掀門板", $E34="抽盤抽頭",$E34="抽盤",$E34="層板",$E34="壁面層板", $E34="上封板",$E34="下封板",$E34="左封板",$E34="右封板", $E34="抽頭",$E34="踢腳板",$E34="補板",$E34="木滑門" ), "AA", "" ) | M34: =IFERROR(VLOOKUP(L34,色號!A:B,2,FALSE),"") | N34: =IFERROR(VLOOKUP(M34,色號!B:C,2,FALSE),"") | O34: =IFERROR(VLOOKUP(L34,色號!A:D,4,FALSE),"") | P34: =IF( OR($E34="左門板", $E34="右門板"), "鉸" & IF($F34<=1000, 2, IF($F34<=1800, 3, 4)), IF( $E34="入柱背板", "側", IF( $E34="外蓋背板", "面", IF( AND(COUNTIF($E$14:$E$43,"入柱背板")>0, OR($E34="頂板", $E34="底板")), "面", IF( AND(COUNTIF($E$14:$E$43,"外蓋背板")>0, OR($E34="左側板", $E34="右側板")), "側", IF( AND( COUNTIF($E$14:$E$43,"入柱背板")=0, COUNTIF($E$14:$E$43,"外蓋背板")=0, OR( AND(COUNTIF($E$14:$E$43,"背板")>0, OR($E34="左側板",$E34="右側板",$E34="頂板",$E34="底板",$E34="天地蓋右側板",$E34="天地蓋左側板",$E34="天地蓋底板",$E34="天地蓋頂板")), AND(COUNTIF($E$14:$E$43,"抽底")>0, OR($E34="右抽牆",$E34="左抽牆",$E34="前抽牆",$E34="後抽牆")) ) ), "背板溝", "" ) ) ) ) ) ) | Q34: =IF(OR($E34="天地蓋右側板",$E34="天地蓋左側板"), "側 面", IF(OR($E34="背拉桿",$E34="中立板",$E34="頂板",$E34="底板",$E34="前抽牆",$E34="後抽牆",$E34="內左側落板",$E34="內右側落板",$E34="抽屜拉桿",$E34="立板"), "側", IF(OR($E34="木滑門",$E34="鋁框滑門"), "輪", IF(OR($E34="右側板",$E34="左側板",$E34="右抽牆",$E34="左抽牆",$E34="天地蓋頂板",$E34="天地蓋底板",$E34="內頂板"), "面", IF($E34="固隔","固","") ) ) ) ) | R34: =IF( OR($E34="左側板",$E34="右側板",$E34="天地蓋左側板",$E34="天地蓋右側板",$E34="中立板",$E34="立板"), "排","") | T34: =IF($E34="中立板","面開槽？排孔？", IF($E34="木框滑門","前排孔要退喔！", IF(OR($E34="左門板",$E34="右門板",$E34="抽頭"),"把手？", IF(OR($E34="左側板",$E34="右側板",$E34="天地蓋右側板",$E34="天地蓋左側板"),"排孔？","")))) | U34: =IF(E34="","",$L$10)
A35: =$C$7 -> 0 | C35: =C34+1 -> 1022 | G35: =IF( OR( $E35="頂板",$E35="底板",$E35="右側板",$E35="左側板", $E35="天地蓋頂板",$E35="天地蓋底板",$E35="天地蓋右側板",$E35="天地蓋左側板", $E35="前抽牆",$E35="後抽牆",$E35="左抽牆",$E35="右抽牆", $E35="踢腳板",$E35="補板",$E35="固隔",$E35="活隔", $E35="中立板",$E35="中立板(退)",$E35="固隔(退)",$E35="活固隔",$E35="立板", $E35="內頂板",$E35="內左側落板",$E35="內右側落板",$E35="內底板", $E35="內左側板",$E35="內右側板", $E35="上前平肢",$E35="上後平肢",$E35="上前立肢",$E35="上後立肢", $E35="下前立肢",$E35="下後立肢",$E35="下前平肢",$E35="下後平肢", $E35="左側落板",$E35="右側落板", $E35="外蓋背板",$E35="台面",$E35="床板",$E35="假門板", $E35="上掀門板",$E35="平掀門板",$E35="下掀門板", $E35="左門板",$E35="右門板", $E35="抽盤",$E35="抽盤抽頭", $E35="上軌道板",$E35="下軌道板",$E35="左軌道板",$E35="右軌道板",$E35="指縫擋板",$E35="左木框滑門",$E35="右木框滑門", $E35="層板",$E35="壁面層板",$E35="桌板",$E35="上封板",$E35="下封板",$E35="左封板",$E35="右封板", $E35="左圓角側板",$E35="右圓角側板",$E35="抽頭",$E35="入柱抽頭",$E35="假抽頭",$E35="背拉桿",$E35="木滑門",$E35="抽屜拉桿" ), "AA", "" ) | I35: =IF( OR( $E35="右側板",$E35="左側板",$E35="活隔", $E35="天地蓋頂板",$E35="天地蓋底板", $E35="左門板",$E35="右門板", $E35="左側落板",$E35="右側落板", $E35="外蓋背板",$E35="活固隔", $E35="左木框滑門",$E35="右木框滑門", $E35="左鋁框滑門",$E35="右鋁框滑門", $E35="桌板",$E35="台面",$E35="床板",$E35="假門板", $E35="上掀門板",$E35="平掀門板",$E35="下掀門板", $E35="抽盤抽頭",$E35="抽盤",$E35="層板",$E35="壁面層板", $E35="上封板",$E35="下封板",$E35="左封板",$E35="右封板", $E35="抽頭",$E35="踢腳板",$E35="補板",$E35="木滑門" ), "AA", "" ) | M35: =IFERROR(VLOOKUP(L35,色號!A:B,2,FALSE),"") | N35: =IFERROR(VLOOKUP(M35,色號!B:C,2,FALSE),"") | O35: =IFERROR(VLOOKUP(L35,色號!A:D,4,FALSE),"") | P35: =IF( OR($E35="左門板", $E35="右門板"), "鉸" & IF($F35<=1000, 2, IF($F35<=1800, 3, 4)), IF( $E35="入柱背板", "側", IF( $E35="外蓋背板", "面", IF( AND(COUNTIF($E$14:$E$43,"入柱背板")>0, OR($E35="頂板", $E35="底板")), "面", IF( AND(COUNTIF($E$14:$E$43,"外蓋背板")>0, OR($E35="左側板", $E35="右側板")), "側", IF( AND( COUNTIF($E$14:$E$43,"入柱背板")=0, COUNTIF($E$14:$E$43,"外蓋背板")=0, OR( AND(COUNTIF($E$14:$E$43,"背板")>0, OR($E35="左側板",$E35="右側板",$E35="頂板",$E35="底板",$E35="天地蓋右側板",$E35="天地蓋左側板",$E35="天地蓋底板",$E35="天地蓋頂板")), AND(COUNTIF($E$14:$E$43,"抽底")>0, OR($E35="右抽牆",$E35="左抽牆",$E35="前抽牆",$E35="後抽牆")) ) ), "背板溝", "" ) ) ) ) ) ) | Q35: =IF(OR($E35="天地蓋右側板",$E35="天地蓋左側板"), "側 面", IF(OR($E35="背拉桿",$E35="中立板",$E35="頂板",$E35="底板",$E35="前抽牆",$E35="後抽牆",$E35="內左側落板",$E35="內右側落板",$E35="抽屜拉桿",$E35="立板"), "側", IF(OR($E35="木滑門",$E35="鋁框滑門"), "輪", IF(OR($E35="右側板",$E35="左側板",$E35="右抽牆",$E35="左抽牆",$E35="天地蓋頂板",$E35="天地蓋底板",$E35="內頂板"), "面", IF($E35="固隔","固","") ) ) ) ) | R35: =IF( OR($E35="左側板",$E35="右側板",$E35="天地蓋左側板",$E35="天地蓋右側板",$E35="中立板",$E35="立板"), "排","") | T35: =IF($E35="中立板","面開槽？排孔？", IF($E35="木框滑門","前排孔要退喔！", IF(OR($E35="左門板",$E35="右門板",$E35="抽頭"),"把手？", IF(OR($E35="左側板",$E35="右側板",$E35="天地蓋右側板",$E35="天地蓋左側板"),"排孔？","")))) | U35: =IF(E35="","",$L$10)
A36: =$C$7 -> 0 | C36: =C35+1 -> 1023 | G36: =IF( OR( $E36="頂板",$E36="底板",$E36="右側板",$E36="左側板", $E36="天地蓋頂板",$E36="天地蓋底板",$E36="天地蓋右側板",$E36="天地蓋左側板", $E36="前抽牆",$E36="後抽牆",$E36="左抽牆",$E36="右抽牆", $E36="踢腳板",$E36="補板",$E36="固隔",$E36="活隔", $E36="中立板",$E36="中立板(退)",$E36="固隔(退)",$E36="活固隔",$E36="立板", $E36="內頂板",$E36="內左側落板",$E36="內右側落板",$E36="內底板", $E36="內左側板",$E36="內右側板", $E36="上前平肢",$E36="上後平肢",$E36="上前立肢",$E36="上後立肢", $E36="下前立肢",$E36="下後立肢",$E36="下前平肢",$E36="下後平肢", $E36="左側落板",$E36="右側落板", $E36="外蓋背板",$E36="台面",$E36="床板",$E36="假門板", $E36="上掀門板",$E36="平掀門板",$E36="下掀門板", $E36="左門板",$E36="右門板", $E36="抽盤",$E36="抽盤抽頭", $E36="上軌道板",$E36="下軌道板",$E36="左軌道板",$E36="右軌道板",$E36="指縫擋板",$E36="左木框滑門",$E36="右木框滑門", $E36="層板",$E36="壁面層板",$E36="桌板",$E36="上封板",$E36="下封板",$E36="左封板",$E36="右封板", $E36="左圓角側板",$E36="右圓角側板",$E36="抽頭",$E36="入柱抽頭",$E36="假抽頭",$E36="背拉桿",$E36="木滑門",$E36="抽屜拉桿" ), "AA", "" ) | I36: =IF( OR( $E36="右側板",$E36="左側板",$E36="活隔", $E36="天地蓋頂板",$E36="天地蓋底板", $E36="左門板",$E36="右門板", $E36="左側落板",$E36="右側落板", $E36="外蓋背板",$E36="活固隔", $E36="左木框滑門",$E36="右木框滑門", $E36="左鋁框滑門",$E36="右鋁框滑門", $E36="桌板",$E36="台面",$E36="床板",$E36="假門板", $E36="上掀門板",$E36="平掀門板",$E36="下掀門板", $E36="抽盤抽頭",$E36="抽盤",$E36="層板",$E36="壁面層板", $E36="上封板",$E36="下封板",$E36="左封板",$E36="右封板", $E36="抽頭",$E36="踢腳板",$E36="補板",$E36="木滑門" ), "AA", "" ) | M36: =IFERROR(VLOOKUP(L36,色號!A:B,2,FALSE),"") | N36: =IFERROR(VLOOKUP(M36,色號!B:C,2,FALSE),"") | O36: =IFERROR(VLOOKUP(L36,色號!A:D,4,FALSE),"") | P36: =IF( OR($E36="左門板", $E36="右門板"), "鉸" & IF($F36<=1000, 2, IF($F36<=1800, 3, 4)), IF( $E36="入柱背板", "側", IF( $E36="外蓋背板", "面", IF( AND(COUNTIF($E$14:$E$43,"入柱背板")>0, OR($E36="頂板", $E36="底板")), "面", IF( AND(COUNTIF($E$14:$E$43,"外蓋背板")>0, OR($E36="左側板", $E36="右側板")), "側", IF( AND( COUNTIF($E$14:$E$43,"入柱背板")=0, COUNTIF($E$14:$E$43,"外蓋背板")=0, OR( AND(COUNTIF($E$14:$E$43,"背板")>0, OR($E36="左側板",$E36="右側板",$E36="頂板",$E36="底板",$E36="天地蓋右側板",$E36="天地蓋左側板",$E36="天地蓋底板",$E36="天地蓋頂板")), AND(COUNTIF($E$14:$E$43,"抽底")>0, OR($E36="右抽牆",$E36="左抽牆",$E36="前抽牆",$E36="後抽牆")) ) ), "背板溝", "" ) ) ) ) ) ) | Q36: =IF(OR($E36="天地蓋右側板",$E36="天地蓋左側板"), "側 面", IF(OR($E36="背拉桿",$E36="中立板",$E36="頂板",$E36="底板",$E36="前抽牆",$E36="後抽牆",$E36="內左側落板",$E36="內右側落板",$E36="抽屜拉桿",$E36="立板"), "側", IF(OR($E36="木滑門",$E36="鋁框滑門"), "輪", IF(OR($E36="右側板",$E36="左側板",$E36="右抽牆",$E36="左抽牆",$E36="天地蓋頂板",$E36="天地蓋底板",$E36="內頂板"), "面", IF($E36="固隔","固","") ) ) ) ) | R36: =IF( OR($E36="左側板",$E36="右側板",$E36="天地蓋左側板",$E36="天地蓋右側板",$E36="中立板",$E36="立板"), "排","") | T36: =IF($E36="中立板","面開槽？排孔？", IF($E36="木框滑門","前排孔要退喔！", IF(OR($E36="左門板",$E36="右門板",$E36="抽頭"),"把手？", IF(OR($E36="左側板",$E36="右側板",$E36="天地蓋右側板",$E36="天地蓋左側板"),"排孔？","")))) | U36: =IF(E36="","",$L$10)
A37: =$C$7 -> 0 | C37: =C36+1 -> 1024 | G37: =IF( OR( $E37="頂板",$E37="底板",$E37="右側板",$E37="左側板", $E37="天地蓋頂板",$E37="天地蓋底板",$E37="天地蓋右側板",$E37="天地蓋左側板", $E37="前抽牆",$E37="後抽牆",$E37="左抽牆",$E37="右抽牆", $E37="踢腳板",$E37="補板",$E37="固隔",$E37="活隔", $E37="中立板",$E37="中立板(退)",$E37="固隔(退)",$E37="活固隔",$E37="立板", $E37="內頂板",$E37="內左側落板",$E37="內右側落板",$E37="內底板", $E37="內左側板",$E37="內右側板", $E37="上前平肢",$E37="上後平肢",$E37="上前立肢",$E37="上後立肢", $E37="下前立肢",$E37="下後立肢",$E37="下前平肢",$E37="下後平肢", $E37="左側落板",$E37="右側落板", $E37="外蓋背板",$E37="台面",$E37="床板",$E37="假門板", $E37="上掀門板",$E37="平掀門板",$E37="下掀門板", $E37="左門板",$E37="右門板", $E37="抽盤",$E37="抽盤抽頭", $E37="上軌道板",$E37="下軌道板",$E37="左軌道板",$E37="右軌道板",$E37="指縫擋板",$E37="左木框滑門",$E37="右木框滑門", $E37="層板",$E37="壁面層板",$E37="桌板",$E37="上封板",$E37="下封板",$E37="左封板",$E37="右封板", $E37="左圓角側板",$E37="右圓角側板",$E37="抽頭",$E37="入柱抽頭",$E37="假抽頭",$E37="背拉桿",$E37="木滑門",$E37="抽屜拉桿" ), "AA", "" ) | I37: =IF( OR( $E37="右側板",$E37="左側板",$E37="活隔", $E37="天地蓋頂板",$E37="天地蓋底板", $E37="左門板",$E37="右門板", $E37="左側落板",$E37="右側落板", $E37="外蓋背板",$E37="活固隔", $E37="左木框滑門",$E37="右木框滑門", $E37="左鋁框滑門",$E37="右鋁框滑門", $E37="桌板",$E37="台面",$E37="床板",$E37="假門板", $E37="上掀門板",$E37="平掀門板",$E37="下掀門板", $E37="抽盤抽頭",$E37="抽盤",$E37="層板",$E37="壁面層板", $E37="上封板",$E37="下封板",$E37="左封板",$E37="右封板", $E37="抽頭",$E37="踢腳板",$E37="補板",$E37="木滑門" ), "AA", "" ) | M37: =IFERROR(VLOOKUP(L37,色號!A:B,2,FALSE),"") | N37: =IFERROR(VLOOKUP(M37,色號!B:C,2,FALSE),"") | O37: =IFERROR(VLOOKUP(L37,色號!A:D,4,FALSE),"") | P37: =IF( OR($E37="左門板", $E37="右門板"), "鉸" & IF($F37<=1000, 2, IF($F37<=1800, 3, 4)), IF( $E37="入柱背板", "側", IF( $E37="外蓋背板", "面", IF( AND(COUNTIF($E$14:$E$43,"入柱背板")>0, OR($E37="頂板", $E37="底板")), "面", IF( AND(COUNTIF($E$14:$E$43,"外蓋背板")>0, OR($E37="左側板", $E37="右側板")), "側", IF( AND( COUNTIF($E$14:$E$43,"入柱背板")=0, COUNTIF($E$14:$E$43,"外蓋背板")=0, OR( AND(COUNTIF($E$14:$E$43,"背板")>0, OR($E37="左側板",$E37="右側板",$E37="頂板",$E37="底板",$E37="天地蓋右側板",$E37="天地蓋左側板",$E37="天地蓋底板",$E37="天地蓋頂板")), AND(COUNTIF($E$14:$E$43,"抽底")>0, OR($E37="右抽牆",$E37="左抽牆",$E37="前抽牆",$E37="後抽牆")) ) ), "背板溝", "" ) ) ) ) ) ) | Q37: =IF(OR($E37="天地蓋右側板",$E37="天地蓋左側板"), "側 面", IF(OR($E37="背拉桿",$E37="中立板",$E37="頂板",$E37="底板",$E37="前抽牆",$E37="後抽牆",$E37="內左側落板",$E37="內右側落板",$E37="抽屜拉桿",$E37="立板"), "側", IF(OR($E37="木滑門",$E37="鋁框滑門"), "輪", IF(OR($E37="右側板",$E37="左側板",$E37="右抽牆",$E37="左抽牆",$E37="天地蓋頂板",$E37="天地蓋底板",$E37="內頂板"), "面", IF($E37="固隔","固","") ) ) ) ) | R37: =IF( OR($E37="左側板",$E37="右側板",$E37="天地蓋左側板",$E37="天地蓋右側板",$E37="中立板",$E37="立板"), "排","") | T37: =IF($E37="中立板","面開槽？排孔？", IF($E37="木框滑門","前排孔要退喔！", IF(OR($E37="左門板",$E37="右門板",$E37="抽頭"),"把手？", IF(OR($E37="左側板",$E37="右側板",$E37="天地蓋右側板",$E37="天地蓋左側板"),"排孔？","")))) | U37: =IF(E37="","",$L$10)
A38: =$C$7 -> 0 | C38: =C37+1 -> 1025 | G38: =IF( OR( $E38="頂板",$E38="底板",$E38="右側板",$E38="左側板", $E38="天地蓋頂板",$E38="天地蓋底板",$E38="天地蓋右側板",$E38="天地蓋左側板", $E38="前抽牆",$E38="後抽牆",$E38="左抽牆",$E38="右抽牆", $E38="踢腳板",$E38="補板",$E38="固隔",$E38="活隔", $E38="中立板",$E38="中立板(退)",$E38="固隔(退)",$E38="活固隔",$E38="立板", $E38="內頂板",$E38="內左側落板",$E38="內右側落板",$E38="內底板", $E38="內左側板",$E38="內右側板", $E38="上前平肢",$E38="上後平肢",$E38="上前立肢",$E38="上後立肢", $E38="下前立肢",$E38="下後立肢",$E38="下前平肢",$E38="下後平肢", $E38="左側落板",$E38="右側落板", $E38="外蓋背板",$E38="台面",$E38="床板",$E38="假門板", $E38="上掀門板",$E38="平掀門板",$E38="下掀門板", $E38="左門板",$E38="右門板", $E38="抽盤",$E38="抽盤抽頭", $E38="上軌道板",$E38="下軌道板",$E38="左軌道板",$E38="右軌道板",$E38="指縫擋板",$E38="左木框滑門",$E38="右木框滑門", $E38="層板",$E38="壁面層板",$E38="桌板",$E38="上封板",$E38="下封板",$E38="左封板",$E38="右封板", $E38="左圓角側板",$E38="右圓角側板",$E38="抽頭",$E38="入柱抽頭",$E38="假抽頭",$E38="背拉桿",$E38="木滑門",$E38="抽屜拉桿" ), "AA", "" ) | I38: =IF( OR( $E38="右側板",$E38="左側板",$E38="活隔", $E38="天地蓋頂板",$E38="天地蓋底板", $E38="左門板",$E38="右門板", $E38="左側落板",$E38="右側落板", $E38="外蓋背板",$E38="活固隔", $E38="左木框滑門",$E38="右木框滑門", $E38="左鋁框滑門",$E38="右鋁框滑門", $E38="桌板",$E38="台面",$E38="床板",$E38="假門板", $E38="上掀門板",$E38="平掀門板",$E38="下掀門板", $E38="抽盤抽頭",$E38="抽盤",$E38="層板",$E38="壁面層板", $E38="上封板",$E38="下封板",$E38="左封板",$E38="右封板", $E38="抽頭",$E38="踢腳板",$E38="補板",$E38="木滑門" ), "AA", "" ) | M38: =IFERROR(VLOOKUP(L38,色號!A:B,2,FALSE),"") | N38: =IFERROR(VLOOKUP(M38,色號!B:C,2,FALSE),"") | O38: =IFERROR(VLOOKUP(L38,色號!A:D,4,FALSE),"") | P38: =IF( OR($E38="左門板", $E38="右門板"), "鉸" & IF($F38<=1000, 2, IF($F38<=1800, 3, 4)), IF( $E38="入柱背板", "側", IF( $E38="外蓋背板", "面", IF( AND(COUNTIF($E$14:$E$43,"入柱背板")>0, OR($E38="頂板", $E38="底板")), "面", IF( AND(COUNTIF($E$14:$E$43,"外蓋背板")>0, OR($E38="左側板", $E38="右側板")), "側", IF( AND( COUNTIF($E$14:$E$43,"入柱背板")=0, COUNTIF($E$14:$E$43,"外蓋背板")=0, OR( AND(COUNTIF($E$14:$E$43,"背板")>0, OR($E38="左側板",$E38="右側板",$E38="頂板",$E38="底板",$E38="天地蓋右側板",$E38="天地蓋左側板",$E38="天地蓋底板",$E38="天地蓋頂板")), AND(COUNTIF($E$14:$E$43,"抽底")>0, OR($E38="右抽牆",$E38="左抽牆",$E38="前抽牆",$E38="後抽牆")) ) ), "背板溝", "" ) ) ) ) ) ) | Q38: =IF(OR($E38="天地蓋右側板",$E38="天地蓋左側板"), "側 面", IF(OR($E38="背拉桿",$E38="中立板",$E38="頂板",$E38="底板",$E38="前抽牆",$E38="後抽牆",$E38="內左側落板",$E38="內右側落板",$E38="抽屜拉桿",$E38="立板"), "側", IF(OR($E38="木滑門",$E38="鋁框滑門"), "輪", IF(OR($E38="右側板",$E38="左側板",$E38="右抽牆",$E38="左抽牆",$E38="天地蓋頂板",$E38="天地蓋底板",$E38="內頂板"), "面", IF($E38="固隔","固","") ) ) ) ) | R38: =IF( OR($E38="左側板",$E38="右側板",$E38="天地蓋左側板",$E38="天地蓋右側板",$E38="中立板",$E38="立板"), "排","") | T38: =IF($E38="中立板","面開槽？排孔？", IF($E38="木框滑門","前排孔要退喔！", IF(OR($E38="左門板",$E38="右門板",$E38="抽頭"),"把手？", IF(OR($E38="左側板",$E38="右側板",$E38="天地蓋右側板",$E38="天地蓋左側板"),"排孔？","")))) | U38: =IF(E38="","",$L$10)
A39: =$C$7 -> 0 | C39: =C38+1 -> 1026 | G39: =IF( OR( $E39="頂板",$E39="底板",$E39="右側板",$E39="左側板", $E39="天地蓋頂板",$E39="天地蓋底板",$E39="天地蓋右側板",$E39="天地蓋左側板", $E39="前抽牆",$E39="後抽牆",$E39="左抽牆",$E39="右抽牆", $E39="踢腳板",$E39="補板",$E39="固隔",$E39="活隔", $E39="中立板",$E39="中立板(退)",$E39="固隔(退)",$E39="活固隔",$E39="立板", $E39="內頂板",$E39="內左側落板",$E39="內右側落板",$E39="內底板", $E39="內左側板",$E39="內右側板", $E39="上前平肢",$E39="上後平肢",$E39="上前立肢",$E39="上後立肢", $E39="下前立肢",$E39="下後立肢",$E39="下前平肢",$E39="下後平肢", $E39="左側落板",$E39="右側落板", $E39="外蓋背板",$E39="台面",$E39="床板",$E39="假門板", $E39="上掀門板",$E39="平掀門板",$E39="下掀門板", $E39="左門板",$E39="右門板", $E39="抽盤",$E39="抽盤抽頭", $E39="上軌道板",$E39="下軌道板",$E39="左軌道板",$E39="右軌道板",$E39="指縫擋板",$E39="左木框滑門",$E39="右木框滑門", $E39="層板",$E39="壁面層板",$E39="桌板",$E39="上封板",$E39="下封板",$E39="左封板",$E39="右封板", $E39="左圓角側板",$E39="右圓角側板",$E39="抽頭",$E39="入柱抽頭",$E39="假抽頭",$E39="背拉桿",$E39="木滑門",$E39="抽屜拉桿" ), "AA", "" ) | I39: =IF( OR( $E39="右側板",$E39="左側板",$E39="活隔", $E39="天地蓋頂板",$E39="天地蓋底板", $E39="左門板",$E39="右門板", $E39="左側落板",$E39="右側落板", $E39="外蓋背板",$E39="活固隔", $E39="左木框滑門",$E39="右木框滑門", $E39="左鋁框滑門",$E39="右鋁框滑門", $E39="桌板",$E39="台面",$E39="床板",$E39="假門板", $E39="上掀門板",$E39="平掀門板",$E39="下掀門板", $E39="抽盤抽頭",$E39="抽盤",$E39="層板",$E39="壁面層板", $E39="上封板",$E39="下封板",$E39="左封板",$E39="右封板", $E39="抽頭",$E39="踢腳板",$E39="補板",$E39="木滑門" ), "AA", "" ) | M39: =IFERROR(VLOOKUP(L39,色號!A:B,2,FALSE),"") | N39: =IFERROR(VLOOKUP(M39,色號!B:C,2,FALSE),"") | O39: =IFERROR(VLOOKUP(L39,色號!A:D,4,FALSE),"") | P39: =IF( OR($E39="左門板", $E39="右門板"), "鉸" & IF($F39<=1000, 2, IF($F39<=1800, 3, 4)), IF( $E39="入柱背板", "側", IF( $E39="外蓋背板", "面", IF( AND(COUNTIF($E$14:$E$43,"入柱背板")>0, OR($E39="頂板", $E39="底板")), "面", IF( AND(COUNTIF($E$14:$E$43,"外蓋背板")>0, OR($E39="左側板", $E39="右側板")), "側", IF( AND( COUNTIF($E$14:$E$43,"入柱背板")=0, COUNTIF($E$14:$E$43,"外蓋背板")=0, OR( AND(COUNTIF($E$14:$E$43,"背板")>0, OR($E39="左側板",$E39="右側板",$E39="頂板",$E39="底板",$E39="天地蓋右側板",$E39="天地蓋左側板",$E39="天地蓋底板",$E39="天地蓋頂板")), AND(COUNTIF($E$14:$E$43,"抽底")>0, OR($E39="右抽牆",$E39="左抽牆",$E39="前抽牆",$E39="後抽牆")) ) ), "背板溝", "" ) ) ) ) ) ) | Q39: =IF(OR($E39="天地蓋右側板",$E39="天地蓋左側板"), "側 面", IF(OR($E39="背拉桿",$E39="中立板",$E39="頂板",$E39="底板",$E39="前抽牆",$E39="後抽牆",$E39="內左側落板",$E39="內右側落板",$E39="抽屜拉桿",$E39="立板"), "側", IF(OR($E39="木滑門",$E39="鋁框滑門"), "輪", IF(OR($E39="右側板",$E39="左側板",$E39="右抽牆",$E39="左抽牆",$E39="天地蓋頂板",$E39="天地蓋底板",$E39="內頂板"), "面", IF($E39="固隔","固","") ) ) ) ) | R39: =IF( OR($E39="左側板",$E39="右側板",$E39="天地蓋左側板",$E39="天地蓋右側板",$E39="中立板",$E39="立板"), "排","") | T39: =IF($E39="中立板","面開槽？排孔？", IF($E39="木框滑門","前排孔要退喔！", IF(OR($E39="左門板",$E39="右門板",$E39="抽頭"),"把手？", IF(OR($E39="左側板",$E39="右側板",$E39="天地蓋右側板",$E39="天地蓋左側板"),"排孔？","")))) | U39: =IF(E39="","",$L$10)
A40: =$C$7 -> 0 | C40: =C39+1 -> 1027 | G40: =IF( OR( $E40="頂板",$E40="底板",$E40="右側板",$E40="左側板", $E40="天地蓋頂板",$E40="天地蓋底板",$E40="天地蓋右側板",$E40="天地蓋左側板", $E40="前抽牆",$E40="後抽牆",$E40="左抽牆",$E40="右抽牆", $E40="踢腳板",$E40="補板",$E40="固隔",$E40="活隔", $E40="中立板",$E40="中立板(退)",$E40="固隔(退)",$E40="活固隔",$E40="立板", $E40="內頂板",$E40="內左側落板",$E40="內右側落板",$E40="內底板", $E40="內左側板",$E40="內右側板", $E40="上前平肢",$E40="上後平肢",$E40="上前立肢",$E40="上後立肢", $E40="下前立肢",$E40="下後立肢",$E40="下前平肢",$E40="下後平肢", $E40="左側落板",$E40="右側落板", $E40="外蓋背板",$E40="台面",$E40="床板",$E40="假門板", $E40="上掀門板",$E40="平掀門板",$E40="下掀門板", $E40="左門板",$E40="右門板", $E40="抽盤",$E40="抽盤抽頭", $E40="上軌道板",$E40="下軌道板",$E40="左軌道板",$E40="右軌道板",$E40="指縫擋板",$E40="左木框滑門",$E40="右木框滑門", $E40="層板",$E40="壁面層板",$E40="桌板",$E40="上封板",$E40="下封板",$E40="左封板",$E40="右封板", $E40="左圓角側板",$E40="右圓角側板",$E40="抽頭",$E40="入柱抽頭",$E40="假抽頭",$E40="背拉桿",$E40="木滑門",$E40="抽屜拉桿" ), "AA", "" ) | I40: =IF( OR( $E40="右側板",$E40="左側板",$E40="活隔", $E40="天地蓋頂板",$E40="天地蓋底板", $E40="左門板",$E40="右門板", $E40="左側落板",$E40="右側落板", $E40="外蓋背板",$E40="活固隔", $E40="左木框滑門",$E40="右木框滑門", $E40="左鋁框滑門",$E40="右鋁框滑門", $E40="桌板",$E40="台面",$E40="床板",$E40="假門板", $E40="上掀門板",$E40="平掀門板",$E40="下掀門板", $E40="抽盤抽頭",$E40="抽盤",$E40="層板",$E40="壁面層板", $E40="上封板",$E40="下封板",$E40="左封板",$E40="右封板", $E40="抽頭",$E40="踢腳板",$E40="補板",$E40="木滑門" ), "AA", "" ) | M40: =IFERROR(VLOOKUP(L40,色號!A:B,2,FALSE),"") | N40: =IFERROR(VLOOKUP(M40,色號!B:C,2,FALSE),"") | O40: =IFERROR(VLOOKUP(L40,色號!A:D,4,FALSE),"") | P40: =IF( OR($E40="左門板", $E40="右門板"), "鉸" & IF($F40<=1000, 2, IF($F40<=1800, 3, 4)), IF( $E40="入柱背板", "側", IF( $E40="外蓋背板", "面", IF( AND(COUNTIF($E$14:$E$43,"入柱背板")>0, OR($E40="頂板", $E40="底板")), "面", IF( AND(COUNTIF($E$14:$E$43,"外蓋背板")>0, OR($E40="左側板", $E40="右側板")), "側", IF( AND( COUNTIF($E$14:$E$43,"入柱背板")=0, COUNTIF($E$14:$E$43,"外蓋背板")=0, OR( AND(COUNTIF($E$14:$E$43,"背板")>0, OR($E40="左側板",$E40="右側板",$E40="頂板",$E40="底板",$E40="天地蓋右側板",$E40="天地蓋左側板",$E40="天地蓋底板",$E40="天地蓋頂板")), AND(COUNTIF($E$14:$E$43,"抽底")>0, OR($E40="右抽牆",$E40="左抽牆",$E40="前抽牆",$E40="後抽牆")) ) ), "背板溝", "" ) ) ) ) ) ) | Q40: =IF(OR($E40="天地蓋右側板",$E40="天地蓋左側板"), "側 面", IF(OR($E40="背拉桿",$E40="中立板",$E40="頂板",$E40="底板",$E40="前抽牆",$E40="後抽牆",$E40="內左側落板",$E40="內右側落板",$E40="抽屜拉桿",$E40="立板"), "側", IF(OR($E40="木滑門",$E40="鋁框滑門"), "輪", IF(OR($E40="右側板",$E40="左側板",$E40="右抽牆",$E40="左抽牆",$E40="天地蓋頂板",$E40="天地蓋底板",$E40="內頂板"), "面", IF($E40="固隔","固","") ) ) ) ) | R40: =IF( OR($E40="左側板",$E40="右側板",$E40="天地蓋左側板",$E40="天地蓋右側板",$E40="中立板",$E40="立板"), "排","") | T40: =IF($E40="中立板","面開槽？排孔？", IF($E40="木框滑門","前排孔要退喔！", IF(OR($E40="左門板",$E40="右門板",$E40="抽頭"),"把手？", IF(OR($E40="左側板",$E40="右側板",$E40="天地蓋右側板",$E40="天地蓋左側板"),"排孔？","")))) | U40: =IF(E40="","",$L$10)
A41: =$C$7 -> 0 | C41: =C40+1 -> 1028 | G41: =IF( OR( $E41="頂板",$E41="底板",$E41="右側板",$E41="左側板", $E41="天地蓋頂板",$E41="天地蓋底板",$E41="天地蓋右側板",$E41="天地蓋左側板", $E41="前抽牆",$E41="後抽牆",$E41="左抽牆",$E41="右抽牆", $E41="踢腳板",$E41="補板",$E41="固隔",$E41="活隔", $E41="中立板",$E41="中立板(退)",$E41="固隔(退)",$E41="活固隔",$E41="立板", $E41="內頂板",$E41="內左側落板",$E41="內右側落板",$E41="內底板", $E41="內左側板",$E41="內右側板", $E41="上前平肢",$E41="上後平肢",$E41="上前立肢",$E41="上後立肢", $E41="下前立肢",$E41="下後立肢",$E41="下前平肢",$E41="下後平肢", $E41="左側落板",$E41="右側落板", $E41="外蓋背板",$E41="台面",$E41="床板",$E41="假門板", $E41="上掀門板",$E41="平掀門板",$E41="下掀門板", $E41="左門板",$E41="右門板", $E41="抽盤",$E41="抽盤抽頭", $E41="上軌道板",$E41="下軌道板",$E41="左軌道板",$E41="右軌道板",$E41="指縫擋板",$E41="左木框滑門",$E41="右木框滑門", $E41="層板",$E41="壁面層板",$E41="桌板",$E41="上封板",$E41="下封板",$E41="左封板",$E41="右封板", $E41="左圓角側板",$E41="右圓角側板",$E41="抽頭",$E41="入柱抽頭",$E41="假抽頭",$E41="背拉桿",$E41="木滑門",$E41="抽屜拉桿" ), "AA", "" ) | I41: =IF( OR( $E41="右側板",$E41="左側板",$E41="活隔", $E41="天地蓋頂板",$E41="天地蓋底板", $E41="左門板",$E41="右門板", $E41="左側落板",$E41="右側落板", $E41="外蓋背板",$E41="活固隔", $E41="左木框滑門",$E41="右木框滑門", $E41="左鋁框滑門",$E41="右鋁框滑門", $E41="桌板",$E41="台面",$E41="床板",$E41="假門板", $E41="上掀門板",$E41="平掀門板",$E41="下掀門板", $E41="抽盤抽頭",$E41="抽盤",$E41="層板",$E41="壁面層板", $E41="上封板",$E41="下封板",$E41="左封板",$E41="右封板", $E41="抽頭",$E41="踢腳板",$E41="補板",$E41="木滑門" ), "AA", "" ) | M41: =IFERROR(VLOOKUP(L41,色號!A:B,2,FALSE),"") | N41: =IFERROR(VLOOKUP(M41,色號!B:C,2,FALSE),"") | O41: =IFERROR(VLOOKUP(L41,色號!A:D,4,FALSE),"") | P41: =IF( OR($E41="左門板", $E41="右門板"), "鉸" & IF($F41<=1000, 2, IF($F41<=1800, 3, 4)), IF( $E41="入柱背板", "側", IF( $E41="外蓋背板", "面", IF( AND(COUNTIF($E$14:$E$43,"入柱背板")>0, OR($E41="頂板", $E41="底板")), "面", IF( AND(COUNTIF($E$14:$E$43,"外蓋背板")>0, OR($E41="左側板", $E41="右側板")), "側", IF( AND( COUNTIF($E$14:$E$43,"入柱背板")=0, COUNTIF($E$14:$E$43,"外蓋背板")=0, OR( AND(COUNTIF($E$14:$E$43,"背板")>0, OR($E41="左側板",$E41="右側板",$E41="頂板",$E41="底板",$E41="天地蓋右側板",$E41="天地蓋左側板",$E41="天地蓋底板",$E41="天地蓋頂板")), AND(COUNTIF($E$14:$E$43,"抽底")>0, OR($E41="右抽牆",$E41="左抽牆",$E41="前抽牆",$E41="後抽牆")) ) ), "背板溝", "" ) ) ) ) ) ) | Q41: =IF(OR($E41="天地蓋右側板",$E41="天地蓋左側板"), "側 面", IF(OR($E41="背拉桿",$E41="中立板",$E41="頂板",$E41="底板",$E41="前抽牆",$E41="後抽牆",$E41="內左側落板",$E41="內右側落板",$E41="抽屜拉桿",$E41="立板"), "側", IF(OR($E41="木滑門",$E41="鋁框滑門"), "輪", IF(OR($E41="右側板",$E41="左側板",$E41="右抽牆",$E41="左抽牆",$E41="天地蓋頂板",$E41="天地蓋底板",$E41="內頂板"), "面", IF($E41="固隔","固","") ) ) ) ) | R41: =IF( OR($E41="左側板",$E41="右側板",$E41="天地蓋左側板",$E41="天地蓋右側板",$E41="中立板",$E41="立板"), "排","") | T41: =IF($E41="中立板","面開槽？排孔？", IF($E41="木框滑門","前排孔要退喔！", IF(OR($E41="左門板",$E41="右門板",$E41="抽頭"),"把手？", IF(OR($E41="左側板",$E41="右側板",$E41="天地蓋右側板",$E41="天地蓋左側板"),"排孔？","")))) | U41: =IF(E41="","",$L$10)
... A43: =$C$7 -> 0 | C43: =C42+1 -> 1030 | G43: =IF( OR( $E43="頂板",$E43="底板",$E43="右側板",$E43="左側板", $E43="天地蓋頂板",$E43="天地蓋底板",$E43="天地蓋右側板",$E43="天地蓋左側板", $E43="前抽牆",$E43="後抽牆",$E43="左抽牆",$E43="右抽牆", $E43="踢腳板",$E43="補板",$E43="固隔",$E43="活隔", $E43="中立板",$E43="中立板(退)",$E43="固隔(退)",$E43="活固隔",$E43="立板", $E43="內頂板",$E43="內左側落板",$E43="內右側落板",$E43="內底板", $E43="內左側板",$E43="內右側板", $E43="上前平肢",$E43="上後平肢",$E43="上前立肢",$E43="上後立肢", $E43="下前立肢",$E43="下後立肢",$E43="下前平肢",$E43="下後平肢", $E43="左側落板",$E43="右側落板", $E43="外蓋背板",$E43="台面",$E43="床板",$E43="假門板", $E43="上掀門板",$E43="平掀門板",$E43="下掀門板", $E43="左門板",$E43="右門板", $E43="抽盤",$E43="抽盤抽頭", $E43="上軌道板",$E43="下軌道板",$E43="左軌道板",$E43="右軌道板",$E43="指縫擋板",$E43="左木框滑門",$E43="右木框滑門", $E43="層板",$E43="壁面層板",$E43="桌板",$E43="上封板",$E43="下封板",$E43="左封板",$E43="右封板", $E43="左圓角側板",$E43="右圓角側板",$E43="抽頭",$E43="入柱抽頭",$E43="假抽頭",$E43="背拉桿",$E43="木滑門",$E43="抽屜拉桿" ), "AA", "" ) | I43: =IF( OR( $E43="右側板",$E43="左側板",$E43="活隔", $E43="天地蓋頂板",$E43="天地蓋底板", $E43="左門板",$E43="右門板", $E43="左側落板",$E43="右側落板", $E43="外蓋背板",$E43="活固隔", $E43="左木框滑門",$E43="右木框滑門", $E43="左鋁框滑門",$E43="右鋁框滑門", $E43="桌板",$E43="台面",$E43="床板",$E43="假門板", $E43="上掀門板",$E43="平掀門板",$E43="下掀門板", $E43="抽盤抽頭",$E43="抽盤",$E43="層板",$E43="壁面層板", $E43="上封板",$E43="下封板",$E43="左封板",$E43="右封板", $E43="抽頭",$E43="踢腳板",$E43="補板",$E43="木滑門" ), "AA", "" ) | M43: =IFERROR(VLOOKUP(L43,色號!A:B,2,FALSE),"") | N43: =IFERROR(VLOOKUP(M43,色號!B:C,2,FALSE),"") | O43: =IFERROR(VLOOKUP(L43,色號!A:D,4,FALSE),"") | P43: =IF( OR($E43="左門板", $E43="右門板"), "鉸" & IF($F43<=1000, 2, IF($F43<=1800, 3, 4)), IF( $E43="入柱背板", "側", IF( $E43="外蓋背板", "面", IF( AND(COUNTIF($E$14:$E$43,"入柱背板")>0, OR($E43="頂板", $E43="底板")), "面", IF( AND(COUNTIF($E$14:$E$43,"外蓋背板")>0, OR($E43="左側板", $E43="右側板")), "側", IF( AND( COUNTIF($E$14:$E$43,"入柱背板")=0, COUNTIF($E$14:$E$43,"外蓋背板")=0, OR( AND(COUNTIF($E$14:$E$43,"背板")>0, OR($E43="左側板",$E43="右側板",$E43="頂板",$E43="底板",$E43="天地蓋右側板",$E43="天地蓋左側板",$E43="天地蓋底板",$E43="天地蓋頂板")), AND(COUNTIF($E$14:$E$43,"抽底")>0, OR($E43="右抽牆",$E43="左抽牆",$E43="前抽牆",$E43="後抽牆")) ) ), "背板溝", "" ) ) ) ) ) ) | Q43: =IF(OR($E43="天地蓋右側板",$E43="天地蓋左側板"), "側 面", IF(OR($E43="背拉桿",$E43="中立板",$E43="頂板",$E43="底板",$E43="前抽牆",$E43="後抽牆",$E43="內左側落板",$E43="內右側落板",$E43="抽屜拉桿",$E43="立板"), "側", IF(OR($E43="木滑門",$E43="鋁框滑門"), "輪", IF(OR($E43="右側板",$E43="左側板",$E43="右抽牆",$E43="左抽牆",$E43="天地蓋頂板",$E43="天地蓋底板",$E43="內頂板"), "面", IF($E43="固隔","固","") ) ) ) ) | R43: =IF( OR($E43="左側板",$E43="右側板",$E43="天地蓋左側板",$E43="天地蓋右側板",$E43="中立板",$E43="立板"), "排","") | T43: =IF($E43="中立板","面開槽？排孔？", IF($E43="木框滑門","前排孔要退喔！", IF(OR($E43="左門板",$E43="右門板",$E43="抽頭"),"把手？", IF(OR($E43="左側板",$E43="右側板",$E43="天地蓋右側板",$E43="天地蓋左側板"),"排孔？","")))) | U43: =IF(E43="","",$L$10)
P44: =IF( OR($E44="左門板", $E44="右門板"), "鉸" & IF($F44<=1000, 2, IF($F44<=1800, 3, 4)), IF( $E44="入柱背板", "側", IF( $E44="外蓋背板", "面", IF( AND(COUNTIF($E$14:$E$43,"入柱背板")>0, OR($E44="頂板", $E44="底板")), "面", IF( AND(COUNTIF($E$14:$E$43,"外蓋背板")>0, OR($E44="左側板", $E44="右側板")), "側", IF( AND( COUNTIF($E$14:$E$43,"入柱背板")=0, COUNTIF($E$14:$E$43,"外蓋背板")=0, OR( AND(COUNTIF($E$14:$E$43,"背板")>0, OR($E44="左側板",$E44="右側板",$E44="頂板",$E44="底板")), AND(COUNTIF($E$14:$E$43,"抽底")>0, OR($E44="右抽牆",$E44="左抽牆",$E44="前抽牆",$E44="後抽牆")) ) ), "背板溝", "" ) ) ) ) ) )
A45: 櫃體名稱 | D45: {=_xlfn.IFS(OR(C45="水槽櫃",C45="爐檯櫃"),"無頂板",C45="油機吊櫃","無底板",TRUE,0)} -> 0
A46: 櫃號 | C46: =C8+1 -> 2 | K46: 板材片數： | L46: =SUMIF(D52:D81,"<>*五金",K52:K81) -> 0
A47: 櫃高 | K47: 板材才數： | L47: =板材才數分析.!P61 -> 0
A48: 櫃深 | D48: 不含門 | K48: 批次： | L48: 1
A49: 櫃寬
A50: 櫃名 | C50: 專案 | D50: 類別 | E50: 板材名稱 | F50: 開板尺寸 | K50: 生產 數量 | L50: 板材 色號 | M50: 色號 名稱 | N50: 板商 | O50: 封邊 色號 | P50: 備註 | Q50: 備註 | R50: 備註 | S50: 備註 | T50: 提醒 | U50: 批次
F51: 長(同紋) | G51: 封邊 | H51: 寬 | I51: 封邊 | J51: 厚
A52: =$C$45 -> 0 | C52: =(C46*1000)+1 -> 2001 | D52: 桶身 | E52: 頂板 | F52: =C49-36 -> -36 | G52: =IF( OR( $E52="頂板",$E52="底板",$E52="右側板",$E52="左側板", $E52="天地蓋頂板",$E52="天地蓋底板",$E52="天地蓋右側板",$E52="天地蓋左側板", $E52="前抽牆",$E52="後抽牆",$E52="左抽牆",$E52="右抽牆", $E52="踢腳板",$E52="補板",$E52="固隔",$E52="活隔", $E52="中立板",$E52="中立板(退)",$E52="固隔(退)",$E52="活固隔",$E52="立板", $E52="內頂板",$E52="內左側落板",$E52="內右側落板",$E52="內底板", $E52="內左側板",$E52="內右側板", $E52="上前平肢",$E52="上後平肢",$E52="上前立肢",$E52="上後立肢", $E52="下前立肢",$E52="下後立肢",$E52="下前平肢",$E52="下後平肢", $E52="左側落板",$E52="右側落板", $E52="外蓋背板",$E52="台面",$E52="床板",$E52="假門板", $E52="上掀門板",$E52="平掀門板",$E52="下掀門板", $E52="左門板",$E52="右門板", $E52="抽盤",$E52="抽盤抽頭", $E52="上軌道板",$E52="下軌道板",$E52="左軌道板",$E52="右軌道板",$E52="指縫擋板",$E52="左木框滑門",$E52="右木框滑門", $E52="層板",$E52="壁面層板",$E52="桌板",$E52="上封板",$E52="下封板",$E52="左封板",$E52="右封板", $E52="左圓角側板",$E52="右圓角側板",$E52="抽頭",$E52="入柱抽頭",$E52="假抽頭",$E52="背拉桿",$E52="木滑門",$E52="抽屜拉桿" ), "AA", "" ) -> AA | H52: =C48 -> 0 | I52: =IF( OR( $E52="右側板",$E52="左側板",$E52="活隔", $E52="天地蓋頂板",$E52="天地蓋底板", $E52="左門板",$E52="右門板", $E52="左側落板",$E52="右側落板", $E52="外蓋背板",$E52="活固隔", $E52="左木框滑門",$E52="右木框滑門", $E52="左鋁框滑門",$E52="右鋁框滑門", $E52="桌板",$E52="台面",$E52="床板",$E52="假門板", $E52="上掀門板",$E52="平掀門板",$E52="下掀門板", $E52="抽盤抽頭",$E52="抽盤",$E52="層板",$E52="壁面層板", $E52="上封板",$E52="下封板",$E52="左封板",$E52="右封板", $E52="抽頭",$E52="踢腳板",$E52="補板",$E52="木滑門" ), "AA", "" ) | J52: 18 | M52: =IFERROR(VLOOKUP(L52,色號!A:B,2,FALSE),"") | N52: =IFERROR(VLOOKUP(M52,色號!B:C,2,FALSE),"") | O52: =IFERROR(VLOOKUP(L52,色號!A:D,4,FALSE),"") | P52: =IF( OR($E52="左門板", $E52="右門板"), "鉸" & IF($F52<=1000, 2, IF($F52<=1800, 3, 4)), IF( $E52="入柱背板", "側", IF( $E52="外蓋背板", "面", IF( AND(COUNTIF($E$52:$E$81,"入柱背板")>0, OR($E52="頂板", $E52="底板")), "面", IF( AND(COUNTIF($E$52:$E$81,"外蓋背板")>0, OR($E52="左側板", $E52="右側板")), "側", IF( AND( COUNTIF($E$52:$E$81,"入柱背板")=0, COUNTIF($E$52:$E$81,"外蓋背板")=0, OR( AND(COUNTIF($E$52:$E$81,"背板")>0, OR($E52="左側板",$E52="右側板",$E52="頂板",$E52="底板",$E52="天地蓋左側板",$E52="天地蓋右側板",$E52="天地蓋頂板",$E52="天地蓋底板")), AND(COUNTIF($E$52:$E$81,"抽底")>0, OR($E52="右抽牆",$E52="左抽牆",$E52="前抽牆",$E52="後抽牆")) ) ), "背板溝", "" ) ) ) ) ) ) -> 背板溝 | Q52: =IF(OR($E52="天地蓋右側板",$E52="天地蓋左側板"), "側 面", IF(OR($E52="背拉桿",$E52="中立板",$E52="頂板",$E52="底板",$E52="前抽牆",$E52="後抽牆",$E52="內左側落板",$E52="內右側落板",$E52="抽屜拉桿",$E52="立板"), "側", IF(OR($E52="木滑門",$E52="鋁框滑門"), "輪", IF(OR($E52="右側板",$E52="左側板",$E52="右抽牆",$E52="左抽牆",$E52="天地蓋頂板",$E52="天地蓋底板",$E52="內頂板"), "面", IF($E52="固隔","固","") ) ) ) ) -> 側 | R52: =IF( OR($E52="左側板",$E52="右側板",$E52="天地蓋左側板",$E52="天地蓋右側板",$E52="中立板",$E52="立板"), "排","") | T52: =IF($E52="中立板","面開槽？排孔？", IF($E52="木框滑門","前排孔要退喔！", IF(OR($E52="左門板",$E52="右門板",$E52="抽頭"),"把手？", IF(OR($E52="左側板",$E52="右側板",$E52="天地蓋右側板",$E52="天地蓋左側板"),"排孔？","")))) | U52: =IF(E52="","",$L$48) -> 1
A53: =$C$45 -> 0 | C53: =C52+1 -> 2002 | D53: 桶身 | E53: 底板 | F53: =C49-36 -> -36 | G53: =IF( OR( $E53="頂板",$E53="底板",$E53="右側板",$E53="左側板", $E53="天地蓋頂板",$E53="天地蓋底板",$E53="天地蓋右側板",$E53="天地蓋左側板", $E53="前抽牆",$E53="後抽牆",$E53="左抽牆",$E53="右抽牆", $E53="踢腳板",$E53="補板",$E53="固隔",$E53="活隔", $E53="中立板",$E53="中立板(退)",$E53="固隔(退)",$E53="活固隔",$E53="立板", $E53="內頂板",$E53="內左側落板",$E53="內右側落板",$E53="內底板", $E53="內左側板",$E53="內右側板", $E53="上前平肢",$E53="上後平肢",$E53="上前立肢",$E53="上後立肢", $E53="下前立肢",$E53="下後立肢",$E53="下前平肢",$E53="下後平肢", $E53="左側落板",$E53="右側落板", $E53="外蓋背板",$E53="台面",$E53="床板",$E53="假門板", $E53="上掀門板",$E53="平掀門板",$E53="下掀門板", $E53="左門板",$E53="右門板", $E53="抽盤",$E53="抽盤抽頭", $E53="上軌道板",$E53="下軌道板",$E53="左軌道板",$E53="右軌道板",$E53="指縫擋板",$E53="左木框滑門",$E53="右木框滑門", $E53="層板",$E53="壁面層板",$E53="桌板",$E53="上封板",$E53="下封板",$E53="左封板",$E53="右封板", $E53="左圓角側板",$E53="右圓角側板",$E53="抽頭",$E53="入柱抽頭",$E53="假抽頭",$E53="背拉桿",$E53="木滑門",$E53="抽屜拉桿" ), "AA", "" ) -> AA | H53: =C48 -> 0 | I53: =IF( OR( $E53="右側板",$E53="左側板",$E53="活隔", $E53="天地蓋頂板",$E53="天地蓋底板", $E53="左門板",$E53="右門板", $E53="左側落板",$E53="右側落板", $E53="外蓋背板",$E53="活固隔", $E53="左木框滑門",$E53="右木框滑門", $E53="左鋁框滑門",$E53="右鋁框滑門", $E53="桌板",$E53="台面",$E53="床板",$E53="假門板", $E53="上掀門板",$E53="平掀門板",$E53="下掀門板", $E53="抽盤抽頭",$E53="抽盤",$E53="層板",$E53="壁面層板", $E53="上封板",$E53="下封板",$E53="左封板",$E53="右封板", $E53="抽頭",$E53="踢腳板",$E53="補板",$E53="木滑門" ), "AA", "" ) | J53: 18 | M53: =IFERROR(VLOOKUP(L53,色號!A:B,2,FALSE),"") | N53: =IFERROR(VLOOKUP(M53,色號!B:C,2,FALSE),"") | O53: =IFERROR(VLOOKUP(L53,色號!A:D,4,FALSE),"") | P53: =IF( OR($E53="左門板", $E53="右門板"), "鉸" & IF($F53<=1000, 2, IF($F53<=1800, 3, 4)), IF( $E53="入柱背板", "側", IF( $E53="外蓋背板", "面", IF( AND(COUNTIF($E$52:$E$81,"入柱背板")>0, OR($E53="頂板", $E53="底板")), "面", IF( AND(COUNTIF($E$52:$E$81,"外蓋背板")>0, OR($E53="左側板", $E53="右側板")), "側", IF( AND( COUNTIF($E$52:$E$81,"入柱背板")=0, COUNTIF($E$52:$E$81,"外蓋背板")=0, OR( AND(COUNTIF($E$52:$E$81,"背板")>0, OR($E53="左側板",$E53="右側板",$E53="頂板",$E53="底板",$E53="天地蓋左側板",$E53="天地蓋右側板",$E53="天地蓋頂板",$E53="天地蓋底板")), AND(COUNTIF($E$52:$E$81,"抽底")>0, OR($E53="右抽牆",$E53="左抽牆",$E53="前抽牆",$E53="後抽牆")) ) ), "背板溝", "" ) ) ) ) ) ) -> 背板溝 | Q53: =IF(OR($E53="天地蓋右側板",$E53="天地蓋左側板"), "側 面", IF(OR($E53="背拉桿",$E53="中立板",$E53="頂板",$E53="底板",$E53="前抽牆",$E53="後抽牆",$E53="內左側落板",$E53="內右側落板",$E53="抽屜拉桿",$E53="立板"), "側", IF(OR($E53="木滑門",$E53="鋁框滑門"), "輪", IF(OR($E53="右側板",$E53="左側板",$E53="右抽牆",$E53="左抽牆",$E53="天地蓋頂板",$E53="天地蓋底板",$E53="內頂板"), "面", IF($E53="固隔","固","") ) ) ) ) -> 側 | R53: =IF( OR($E53="左側板",$E53="右側板",$E53="天地蓋左側板",$E53="天地蓋右側板",$E53="中立板",$E53="立板"), "排","") | T53: =IF($E53="中立板","面開槽？排孔？", IF($E53="木框滑門","前排孔要退喔！", IF(OR($E53="左門板",$E53="右門板",$E53="抽頭"),"把手？", IF(OR($E53="左側板",$E53="右側板",$E53="天地蓋右側板",$E53="天地蓋左側板"),"排孔？","")))) | U53: =IF(E53="","",$L$48) -> 1
A54: =$C$45 -> 0 | C54: =C53+1 -> 2003 | D54: 桶身 | E54: 左側板 | F54: =C47 -> 0 | G54: =IF( OR( $E54="頂板",$E54="底板",$E54="右側板",$E54="左側板", $E54="天地蓋頂板",$E54="天地蓋底板",$E54="天地蓋右側板",$E54="天地蓋左側板", $E54="前抽牆",$E54="後抽牆",$E54="左抽牆",$E54="右抽牆", $E54="踢腳板",$E54="補板",$E54="固隔",$E54="活隔", $E54="中立板",$E54="中立板(退)",$E54="固隔(退)",$E54="活固隔",$E54="立板", $E54="內頂板",$E54="內左側落板",$E54="內右側落板",$E54="內底板", $E54="內左側板",$E54="內右側板", $E54="上前平肢",$E54="上後平肢",$E54="上前立肢",$E54="上後立肢", $E54="下前立肢",$E54="下後立肢",$E54="下前平肢",$E54="下後平肢", $E54="左側落板",$E54="右側落板", $E54="外蓋背板",$E54="台面",$E54="床板",$E54="假門板", $E54="上掀門板",$E54="平掀門板",$E54="下掀門板", $E54="左門板",$E54="右門板", $E54="抽盤",$E54="抽盤抽頭", $E54="上軌道板",$E54="下軌道板",$E54="左軌道板",$E54="右軌道板",$E54="指縫擋板",$E54="左木框滑門",$E54="右木框滑門", $E54="層板",$E54="壁面層板",$E54="桌板",$E54="上封板",$E54="下封板",$E54="左封板",$E54="右封板", $E54="左圓角側板",$E54="右圓角側板",$E54="抽頭",$E54="入柱抽頭",$E54="假抽頭",$E54="背拉桿",$E54="木滑門",$E54="抽屜拉桿" ), "AA", "" ) -> AA | H54: =C48 -> 0 | I54: =IF( OR( $E54="右側板",$E54="左側板",$E54="活隔", $E54="天地蓋頂板",$E54="天地蓋底板", $E54="左門板",$E54="右門板", $E54="左側落板",$E54="右側落板", $E54="外蓋背板",$E54="活固隔", $E54="左木框滑門",$E54="右木框滑門", $E54="左鋁框滑門",$E54="右鋁框滑門", $E54="桌板",$E54="台面",$E54="床板",$E54="假門板", $E54="上掀門板",$E54="平掀門板",$E54="下掀門板", $E54="抽盤抽頭",$E54="抽盤",$E54="層板",$E54="壁面層板", $E54="上封板",$E54="下封板",$E54="左封板",$E54="右封板", $E54="抽頭",$E54="踢腳板",$E54="補板",$E54="木滑門" ), "AA", "" ) -> AA | J54: 18 | M54: =IFERROR(VLOOKUP(L54,色號!A:B,2,FALSE),"") | N54: =IFERROR(VLOOKUP(M54,色號!B:C,2,FALSE),"") | O54: =IFERROR(VLOOKUP(L54,色號!A:D,4,FALSE),"") | P54: =IF( OR($E54="左門板", $E54="右門板"), "鉸" & IF($F54<=1000, 2, IF($F54<=1800, 3, 4)), IF( $E54="入柱背板", "側", IF( $E54="外蓋背板", "面", IF( AND(COUNTIF($E$52:$E$81,"入柱背板")>0, OR($E54="頂板", $E54="底板")), "面", IF( AND(COUNTIF($E$52:$E$81,"外蓋背板")>0, OR($E54="左側板", $E54="右側板")), "側", IF( AND( COUNTIF($E$52:$E$81,"入柱背板")=0, COUNTIF($E$52:$E$81,"外蓋背板")=0, OR( AND(COUNTIF($E$52:$E$81,"背板")>0, OR($E54="左側板",$E54="右側板",$E54="頂板",$E54="底板",$E54="天地蓋左側板",$E54="天地蓋右側板",$E54="天地蓋頂板",$E54="天地蓋底板")), AND(COUNTIF($E$52:$E$81,"抽底")>0, OR($E54="右抽牆",$E54="左抽牆",$E54="前抽牆",$E54="後抽牆")) ) ), "背板溝", "" ) ) ) ) ) ) -> 背板溝 | Q54: =IF(OR($E54="天地蓋右側板",$E54="天地蓋左側板"), "側 面", IF(OR($E54="背拉桿",$E54="中立板",$E54="頂板",$E54="底板",$E54="前抽牆",$E54="後抽牆",$E54="內左側落板",$E54="內右側落板",$E54="抽屜拉桿",$E54="立板"), "側", IF(OR($E54="木滑門",$E54="鋁框滑門"), "輪", IF(OR($E54="右側板",$E54="左側板",$E54="右抽牆",$E54="左抽牆",$E54="天地蓋頂板",$E54="天地蓋底板",$E54="內頂板"), "面", IF($E54="固隔","固","") ) ) ) ) -> 面 | R54: =IF( OR($E54="左側板",$E54="右側板",$E54="天地蓋左側板",$E54="天地蓋右側板",$E54="中立板",$E54="立板"), "排","") -> 排 | T54: =IF($E54="中立板","面開槽？排孔？", IF($E54="木框滑門","前排孔要退喔！", IF(OR($E54="左門板",$E54="右門板",$E54="抽頭"),"把手？", IF(OR($E54="左側板",$E54="右側板",$E54="天地蓋右側板",$E54="天地蓋左側板"),"排孔？","")))) -> 排孔？ | U54: =IF(E54="","",$L$48) -> 1
A55: =$C$45 -> 0 | C55: =C54+1 -> 2004 | D55: 桶身 | E55: 右側板 | F55: =C47 -> 0 | G55: =IF( OR( $E55="頂板",$E55="底板",$E55="右側板",$E55="左側板", $E55="天地蓋頂板",$E55="天地蓋底板",$E55="天地蓋右側板",$E55="天地蓋左側板", $E55="前抽牆",$E55="後抽牆",$E55="左抽牆",$E55="右抽牆", $E55="踢腳板",$E55="補板",$E55="固隔",$E55="活隔", $E55="中立板",$E55="中立板(退)",$E55="固隔(退)",$E55="活固隔",$E55="立板", $E55="內頂板",$E55="內左側落板",$E55="內右側落板",$E55="內底板", $E55="內左側板",$E55="內右側板", $E55="上前平肢",$E55="上後平肢",$E55="上前立肢",$E55="上後立肢", $E55="下前立肢",$E55="下後立肢",$E55="下前平肢",$E55="下後平肢", $E55="左側落板",$E55="右側落板", $E55="外蓋背板",$E55="台面",$E55="床板",$E55="假門板", $E55="上掀門板",$E55="平掀門板",$E55="下掀門板", $E55="左門板",$E55="右門板", $E55="抽盤",$E55="抽盤抽頭", $E55="上軌道板",$E55="下軌道板",$E55="左軌道板",$E55="右軌道板",$E55="指縫擋板",$E55="左木框滑門",$E55="右木框滑門", $E55="層板",$E55="壁面層板",$E55="桌板",$E55="上封板",$E55="下封板",$E55="左封板",$E55="右封板", $E55="左圓角側板",$E55="右圓角側板",$E55="抽頭",$E55="入柱抽頭",$E55="假抽頭",$E55="背拉桿",$E55="木滑門",$E55="抽屜拉桿" ), "AA", "" ) -> AA | H55: =C48 -> 0 | I55: =IF( OR( $E55="右側板",$E55="左側板",$E55="活隔", $E55="天地蓋頂板",$E55="天地蓋底板", $E55="左門板",$E55="右門板", $E55="左側落板",$E55="右側落板", $E55="外蓋背板",$E55="活固隔", $E55="左木框滑門",$E55="右木框滑門", $E55="左鋁框滑門",$E55="右鋁框滑門", $E55="桌板",$E55="台面",$E55="床板",$E55="假門板", $E55="上掀門板",$E55="平掀門板",$E55="下掀門板", $E55="抽盤抽頭",$E55="抽盤",$E55="層板",$E55="壁面層板", $E55="上封板",$E55="下封板",$E55="左封板",$E55="右封板", $E55="抽頭",$E55="踢腳板",$E55="補板",$E55="木滑門" ), "AA", "" ) -> AA | J55: 18 | M55: =IFERROR(VLOOKUP(L55,色號!A:B,2,FALSE),"") | N55: =IFERROR(VLOOKUP(M55,色號!B:C,2,FALSE),"") | O55: =IFERROR(VLOOKUP(L55,色號!A:D,4,FALSE),"") | P55: =IF( OR($E55="左門板", $E55="右門板"), "鉸" & IF($F55<=1000, 2, IF($F55<=1800, 3, 4)), IF( $E55="入柱背板", "側", IF( $E55="外蓋背板", "面", IF( AND(COUNTIF($E$52:$E$81,"入柱背板")>0, OR($E55="頂板", $E55="底板")), "面", IF( AND(COUNTIF($E$52:$E$81,"外蓋背板")>0, OR($E55="左側板", $E55="右側板")), "側", IF( AND( COUNTIF($E$52:$E$81,"入柱背板")=0, COUNTIF($E$52:$E$81,"外蓋背板")=0, OR( AND(COUNTIF($E$52:$E$81,"背板")>0, OR($E55="左側板",$E55="右側板",$E55="頂板",$E55="底板",$E55="天地蓋左側板",$E55="天地蓋右側板",$E55="天地蓋頂板",$E55="天地蓋底板")), AND(COUNTIF($E$52:$E$81,"抽底")>0, OR($E55="右抽牆",$E55="左抽牆",$E55="前抽牆",$E55="後抽牆")) ) ), "背板溝", "" ) ) ) ) ) ) -> 背板溝 | Q55: =IF(OR($E55="天地蓋右側板",$E55="天地蓋左側板"), "側 面", IF(OR($E55="背拉桿",$E55="中立板",$E55="頂板",$E55="底板",$E55="前抽牆",$E55="後抽牆",$E55="內左側落板",$E55="內右側落板",$E55="抽屜拉桿",$E55="立板"), "側", IF(OR($E55="木滑門",$E55="鋁框滑門"), "輪", IF(OR($E55="右側板",$E55="左側板",$E55="右抽牆",$E55="左抽牆",$E55="天地蓋頂板",$E55="天地蓋底板",$E55="內頂板"), "面", IF($E55="固隔","固","") ) ) ) ) -> 面 | R55: =IF( OR($E55="左側板",$E55="右側板",$E55="天地蓋左側板",$E55="天地蓋右側板",$E55="中立板",$E55="立板"), "排","") -> 排 | T55: =IF($E55="中立板","面開槽？排孔？", IF($E55="木框滑門","前排孔要退喔！", IF(OR($E55="左門板",$E55="右門板",$E55="抽頭"),"把手？", IF(OR($E55="左側板",$E55="右側板",$E55="天地蓋右側板",$E55="天地蓋左側板"),"排孔？","")))) -> 排孔？ | U55: =IF(E55="","",$L$48) -> 1
A56: =$C$45 -> 0 | C56: =C55+1 -> 2005 | D56: 桶身 | E56: 背板 | F56: =C47-22 -> -22 | G56: =IF( OR( $E56="頂板",$E56="底板",$E56="右側板",$E56="左側板", $E56="天地蓋頂板",$E56="天地蓋底板",$E56="天地蓋右側板",$E56="天地蓋左側板", $E56="前抽牆",$E56="後抽牆",$E56="左抽牆",$E56="右抽牆", $E56="踢腳板",$E56="補板",$E56="固隔",$E56="活隔", $E56="中立板",$E56="中立板(退)",$E56="固隔(退)",$E56="活固隔",$E56="立板", $E56="內頂板",$E56="內左側落板",$E56="內右側落板",$E56="內底板", $E56="內左側板",$E56="內右側板", $E56="上前平肢",$E56="上後平肢",$E56="上前立肢",$E56="上後立肢", $E56="下前立肢",$E56="下後立肢",$E56="下前平肢",$E56="下後平肢", $E56="左側落板",$E56="右側落板", $E56="外蓋背板",$E56="台面",$E56="床板",$E56="假門板", $E56="上掀門板",$E56="平掀門板",$E56="下掀門板", $E56="左門板",$E56="右門板", $E56="抽盤",$E56="抽盤抽頭", $E56="上軌道板",$E56="下軌道板",$E56="左軌道板",$E56="右軌道板",$E56="指縫擋板",$E56="左木框滑門",$E56="右木框滑門", $E56="層板",$E56="壁面層板",$E56="桌板",$E56="上封板",$E56="下封板",$E56="左封板",$E56="右封板", $E56="左圓角側板",$E56="右圓角側板",$E56="抽頭",$E56="入柱抽頭",$E56="假抽頭",$E56="背拉桿",$E56="木滑門",$E56="抽屜拉桿" ), "AA", "" ) | H56: =C49-22 -> -22 | I56: =IF( OR( $E56="右側板",$E56="左側板",$E56="活隔", $E56="天地蓋頂板",$E56="天地蓋底板", $E56="左門板",$E56="右門板", $E56="左側落板",$E56="右側落板", $E56="外蓋背板",$E56="活固隔", $E56="左木框滑門",$E56="右木框滑門", $E56="左鋁框滑門",$E56="右鋁框滑門", $E56="桌板",$E56="台面",$E56="床板",$E56="假門板", $E56="上掀門板",$E56="平掀門板",$E56="下掀門板", $E56="抽盤抽頭",$E56="抽盤",$E56="層板",$E56="壁面層板", $E56="上封板",$E56="下封板",$E56="左封板",$E56="右封板", $E56="抽頭",$E56="踢腳板",$E56="補板",$E56="木滑門" ), "AA", "" ) | J56: 4 | M56: =IFERROR(VLOOKUP(L56,色號!A:B,2,FALSE),"") | N56: =IFERROR(VLOOKUP(M56,色號!B:C,2,FALSE),"") | O56: =IFERROR(VLOOKUP(L56,色號!A:D,4,FALSE),"") | P56: =IF( OR($E56="左門板", $E56="右門板"), "鉸" & IF($F56<=1000, 2, IF($F56<=1800, 3, 4)), IF( $E56="入柱背板", "側", IF( $E56="外蓋背板", "面", IF( AND(COUNTIF($E$52:$E$81,"入柱背板")>0, OR($E56="頂板", $E56="底板")), "面", IF( AND(COUNTIF($E$52:$E$81,"外蓋背板")>0, OR($E56="左側板", $E56="右側板")), "側", IF( AND( COUNTIF($E$52:$E$81,"入柱背板")=0, COUNTIF($E$52:$E$81,"外蓋背板")=0, OR( AND(COUNTIF($E$52:$E$81,"背板")>0, OR($E56="左側板",$E56="右側板",$E56="頂板",$E56="底板",$E56="天地蓋左側板",$E56="天地蓋右側板",$E56="天地蓋頂板",$E56="天地蓋底板")), AND(COUNTIF($E$52:$E$81,"抽底")>0, OR($E56="右抽牆",$E56="左抽牆",$E56="前抽牆",$E56="後抽牆")) ) ), "背板溝", "" ) ) ) ) ) ) | Q56: =IF(OR($E56="天地蓋右側板",$E56="天地蓋左側板"), "側 面", IF(OR($E56="背拉桿",$E56="中立板",$E56="頂板",$E56="底板",$E56="前抽牆",$E56="後抽牆",$E56="內左側落板",$E56="內右側落板",$E56="抽屜拉桿",$E56="立板"), "側", IF(OR($E56="木滑門",$E56="鋁框滑門"), "輪", IF(OR($E56="右側板",$E56="左側板",$E56="右抽牆",$E56="左抽牆",$E56="天地蓋頂板",$E56="天地蓋底板",$E56="內頂板"), "面", IF($E56="固隔","固","") ) ) ) ) | R56: =IF( OR($E56="左側板",$E56="右側板",$E56="天地蓋左側板",$E56="天地蓋右側板",$E56="中立板",$E56="立板"), "排","") | T56: =IF($E56="中立板","面開槽？排孔？", IF($E56="木框滑門","前排孔要退喔！", IF(OR($E56="左門板",$E56="右門板",$E56="抽頭"),"把手？", IF(OR($E56="左側板",$E56="右側板",$E56="天地蓋右側板",$E56="天地蓋左側板"),"排孔？","")))) | U56: =IF(E56="","",$L$48) -> 1
A57: =$C$45 -> 0 | C57: =C56+1 -> 2006 | D57: 桶身 | E57: 背拉桿 | F57: =F52 -> -36 | G57: =IF( OR( $E57="頂板",$E57="底板",$E57="右側板",$E57="左側板", $E57="天地蓋頂板",$E57="天地蓋底板",$E57="天地蓋右側板",$E57="天地蓋左側板", $E57="前抽牆",$E57="後抽牆",$E57="左抽牆",$E57="右抽牆", $E57="踢腳板",$E57="補板",$E57="固隔",$E57="活隔", $E57="中立板",$E57="中立板(退)",$E57="固隔(退)",$E57="活固隔",$E57="立板", $E57="內頂板",$E57="內左側落板",$E57="內右側落板",$E57="內底板", $E57="內左側板",$E57="內右側板", $E57="上前平肢",$E57="上後平肢",$E57="上前立肢",$E57="上後立肢", $E57="下前立肢",$E57="下後立肢",$E57="下前平肢",$E57="下後平肢", $E57="左側落板",$E57="右側落板", $E57="外蓋背板",$E57="台面",$E57="床板",$E57="假門板", $E57="上掀門板",$E57="平掀門板",$E57="下掀門板", $E57="左門板",$E57="右門板", $E57="抽盤",$E57="抽盤抽頭", $E57="上軌道板",$E57="下軌道板",$E57="左軌道板",$E57="右軌道板",$E57="指縫擋板",$E57="左木框滑門",$E57="右木框滑門", $E57="層板",$E57="壁面層板",$E57="桌板",$E57="上封板",$E57="下封板",$E57="左封板",$E57="右封板", $E57="左圓角側板",$E57="右圓角側板",$E57="抽頭",$E57="入柱抽頭",$E57="假抽頭",$E57="背拉桿",$E57="木滑門",$E57="抽屜拉桿" ), "AA", "" ) -> AA | H57: 120 | I57: =IF( OR( $E57="右側板",$E57="左側板",$E57="活隔", $E57="天地蓋頂板",$E57="天地蓋底板", $E57="左門板",$E57="右門板", $E57="左側落板",$E57="右側落板", $E57="外蓋背板",$E57="活固隔", $E57="左木框滑門",$E57="右木框滑門", $E57="左鋁框滑門",$E57="右鋁框滑門", $E57="桌板",$E57="台面",$E57="床板",$E57="假門板", $E57="上掀門板",$E57="平掀門板",$E57="下掀門板", $E57="抽盤抽頭",$E57="抽盤",$E57="層板",$E57="壁面層板", $E57="上封板",$E57="下封板",$E57="左封板",$E57="右封板", $E57="抽頭",$E57="踢腳板",$E57="補板",$E57="木滑門" ), "AA", "" ) | J57: 18 | M57: =IFERROR(VLOOKUP(L57,色號!A:B,2,FALSE),"") | N57: =IFERROR(VLOOKUP(M57,色號!B:C,2,FALSE),"") | O57: =IFERROR(VLOOKUP(L57,色號!A:D,4,FALSE),"") | P57: =IF( OR($E57="左門板", $E57="右門板"), "鉸" & IF($F57<=1000, 2, IF($F57<=1800, 3, 4)), IF( $E57="入柱背板", "側", IF( $E57="外蓋背板", "面", IF( AND(COUNTIF($E$52:$E$81,"入柱背板")>0, OR($E57="頂板", $E57="底板")), "面", IF( AND(COUNTIF($E$52:$E$81,"外蓋背板")>0, OR($E57="左側板", $E57="右側板")), "側", IF( AND( COUNTIF($E$52:$E$81,"入柱背板")=0, COUNTIF($E$52:$E$81,"外蓋背板")=0, OR( AND(COUNTIF($E$52:$E$81,"背板")>0, OR($E57="左側板",$E57="右側板",$E57="頂板",$E57="底板",$E57="天地蓋左側板",$E57="天地蓋右側板",$E57="天地蓋頂板",$E57="天地蓋底板")), AND(COUNTIF($E$52:$E$81,"抽底")>0, OR($E57="右抽牆",$E57="左抽牆",$E57="前抽牆",$E57="後抽牆")) ) ), "背板溝", "" ) ) ) ) ) ) | Q57: =IF(OR($E57="天地蓋右側板",$E57="天地蓋左側板"), "側 面", IF(OR($E57="背拉桿",$E57="中立板",$E57="頂板",$E57="底板",$E57="前抽牆",$E57="後抽牆",$E57="內左側落板",$E57="內右側落板",$E57="抽屜拉桿",$E57="立板"), "側", IF(OR($E57="木滑門",$E57="鋁框滑門"), "輪", IF(OR($E57="右側板",$E57="左側板",$E57="右抽牆",$E57="左抽牆",$E57="天地蓋頂板",$E57="天地蓋底板",$E57="內頂板"), "面", IF($E57="固隔","固","") ) ) ) ) -> 側 | R57: =IF( OR($E57="左側板",$E57="右側板",$E57="天地蓋左側板",$E57="天地蓋右側板",$E57="中立板",$E57="立板"), "排","") | T57: =IF($E57="中立板","面開槽？排孔？", IF($E57="木框滑門","前排孔要退喔！", IF(OR($E57="左門板",$E57="右門板",$E57="抽頭"),"把手？", IF(OR($E57="左側板",$E57="右側板",$E57="天地蓋右側板",$E57="天地蓋左側板"),"排孔？","")))) | U57: =IF(E57="","",$L$48) -> 1
A58: =$C$45 -> 0 | C58: =C57+1 -> 2007 | D58: 內部 | E58: 中立板 | F58: =F52 -> -36 | G58: =IF( OR( $E58="頂板",$E58="底板",$E58="右側板",$E58="左側板", $E58="天地蓋頂板",$E58="天地蓋底板",$E58="天地蓋右側板",$E58="天地蓋左側板", $E58="前抽牆",$E58="後抽牆",$E58="左抽牆",$E58="右抽牆", $E58="踢腳板",$E58="補板",$E58="固隔",$E58="活隔", $E58="中立板",$E58="中立板(退)",$E58="固隔(退)",$E58="活固隔",$E58="立板", $E58="內頂板",$E58="內左側落板",$E58="內右側落板",$E58="內底板", $E58="內左側板",$E58="內右側板", $E58="上前平肢",$E58="上後平肢",$E58="上前立肢",$E58="上後立肢", $E58="下前立肢",$E58="下後立肢",$E58="下前平肢",$E58="下後平肢", $E58="左側落板",$E58="右側落板", $E58="外蓋背板",$E58="台面",$E58="床板",$E58="假門板", $E58="上掀門板",$E58="平掀門板",$E58="下掀門板", $E58="左門板",$E58="右門板", $E58="抽盤",$E58="抽盤抽頭", $E58="上軌道板",$E58="下軌道板",$E58="左軌道板",$E58="右軌道板",$E58="指縫擋板",$E58="左木框滑門",$E58="右木框滑門", $E58="層板",$E58="壁面層板",$E58="桌板",$E58="上封板",$E58="下封板",$E58="左封板",$E58="右封板", $E58="左圓角側板",$E58="右圓角側板",$E58="抽頭",$E58="入柱抽頭",$E58="假抽頭",$E58="背拉桿",$E58="木滑門",$E58="抽屜拉桿" ), "AA", "" ) -> AA | H58: =C48-22 -> -22 | I58: =IF( OR( $E58="右側板",$E58="左側板",$E58="活隔", $E58="天地蓋頂板",$E58="天地蓋底板", $E58="左門板",$E58="右門板", $E58="左側落板",$E58="右側落板", $E58="外蓋背板",$E58="活固隔", $E58="左木框滑門",$E58="右木框滑門", $E58="左鋁框滑門",$E58="右鋁框滑門", $E58="桌板",$E58="台面",$E58="床板",$E58="假門板", $E58="上掀門板",$E58="平掀門板",$E58="下掀門板", $E58="抽盤抽頭",$E58="抽盤",$E58="層板",$E58="壁面層板", $E58="上封板",$E58="下封板",$E58="左封板",$E58="右封板", $E58="抽頭",$E58="踢腳板",$E58="補板",$E58="木滑門" ), "AA", "" ) | J58: 18 | M58: =IFERROR(VLOOKUP(L58,色號!A:B,2,FALSE),"") | N58: =IFERROR(VLOOKUP(M58,色號!B:C,2,FALSE),"") | O58: =IFERROR(VLOOKUP(L58,色號!A:D,4,FALSE),"") | P58: =IF( OR($E58="左門板", $E58="右門板"), "鉸" & IF($F58<=1000, 2, IF($F58<=1800, 3, 4)), IF( $E58="入柱背板", "側", IF( $E58="外蓋背板", "面", IF( AND(COUNTIF($E$52:$E$81,"入柱背板")>0, OR($E58="頂板", $E58="底板")), "面", IF( AND(COUNTIF($E$52:$E$81,"外蓋背板")>0, OR($E58="左側板", $E58="右側板")), "側", IF( AND( COUNTIF($E$52:$E$81,"入柱背板")=0, COUNTIF($E$52:$E$81,"外蓋背板")=0, OR( AND(COUNTIF($E$52:$E$81,"背板")>0, OR($E58="左側板",$E58="右側板",$E58="頂板",$E58="底板",$E58="天地蓋左側板",$E58="天地蓋右側板",$E58="天地蓋頂板",$E58="天地蓋底板")), AND(COUNTIF($E$52:$E$81,"抽底")>0, OR($E58="右抽牆",$E58="左抽牆",$E58="前抽牆",$E58="後抽牆")) ) ), "背板溝", "" ) ) ) ) ) ) | Q58: =IF(OR($E58="天地蓋右側板",$E58="天地蓋左側板"), "側 面", IF(OR($E58="背拉桿",$E58="中立板",$E58="頂板",$E58="底板",$E58="前抽牆",$E58="後抽牆",$E58="內左側落板",$E58="內右側落板",$E58="抽屜拉桿",$E58="立板"), "側", IF(OR($E58="木滑門",$E58="鋁框滑門"), "輪", IF(OR($E58="右側板",$E58="左側板",$E58="右抽牆",$E58="左抽牆",$E58="天地蓋頂板",$E58="天地蓋底板",$E58="內頂板"), "面", IF($E58="固隔","固","") ) ) ) ) -> 側 | R58: =IF( OR($E58="左側板",$E58="右側板",$E58="天地蓋左側板",$E58="天地蓋右側板",$E58="中立板",$E58="立板"), "排","") -> 排 | T58: =IF($E58="中立板","面開槽？排孔？", IF($E58="木框滑門","前排孔要退喔！", IF(OR($E58="左門板",$E58="右門板",$E58="抽頭"),"把手？", IF(OR($E58="左側板",$E58="右側板",$E58="天地蓋右側板",$E58="天地蓋左側板"),"排孔？","")))) -> 面開槽？排孔？ | U58: =IF(E58="","",$L$48) -> 1
A59: =$C$45 -> 0 | C59: =C58+1 -> 2008 | D59: 內部 | E59: 活隔 | G59: =IF( OR( $E59="頂板",$E59="底板",$E59="右側板",$E59="左側板", $E59="天地蓋頂板",$E59="天地蓋底板",$E59="天地蓋右側板",$E59="天地蓋左側板", $E59="前抽牆",$E59="後抽牆",$E59="左抽牆",$E59="右抽牆", $E59="踢腳板",$E59="補板",$E59="固隔",$E59="活隔", $E59="中立板",$E59="中立板(退)",$E59="固隔(退)",$E59="活固隔",$E59="立板", $E59="內頂板",$E59="內左側落板",$E59="內右側落板",$E59="內底板", $E59="內左側板",$E59="內右側板", $E59="上前平肢",$E59="上後平肢",$E59="上前立肢",$E59="上後立肢", $E59="下前立肢",$E59="下後立肢",$E59="下前平肢",$E59="下後平肢", $E59="左側落板",$E59="右側落板", $E59="外蓋背板",$E59="台面",$E59="床板",$E59="假門板", $E59="上掀門板",$E59="平掀門板",$E59="下掀門板", $E59="左門板",$E59="右門板", $E59="抽盤",$E59="抽盤抽頭", $E59="上軌道板",$E59="下軌道板",$E59="左軌道板",$E59="右軌道板",$E59="指縫擋板",$E59="左木框滑門",$E59="右木框滑門", $E59="層板",$E59="壁面層板",$E59="桌板",$E59="上封板",$E59="下封板",$E59="左封板",$E59="右封板", $E59="左圓角側板",$E59="右圓角側板",$E59="抽頭",$E59="入柱抽頭",$E59="假抽頭",$E59="背拉桿",$E59="木滑門",$E59="抽屜拉桿" ), "AA", "" ) -> AA | H59: =C48-22-10 -> -32 | I59: =IF( OR( $E59="右側板",$E59="左側板",$E59="活隔", $E59="天地蓋頂板",$E59="天地蓋底板", $E59="左門板",$E59="右門板", $E59="左側落板",$E59="右側落板", $E59="外蓋背板",$E59="活固隔", $E59="左木框滑門",$E59="右木框滑門", $E59="左鋁框滑門",$E59="右鋁框滑門", $E59="桌板",$E59="台面",$E59="床板",$E59="假門板", $E59="上掀門板",$E59="平掀門板",$E59="下掀門板", $E59="抽盤抽頭",$E59="抽盤",$E59="層板",$E59="壁面層板", $E59="上封板",$E59="下封板",$E59="左封板",$E59="右封板", $E59="抽頭",$E59="踢腳板",$E59="補板",$E59="木滑門" ), "AA", "" ) -> AA | J59: 18 | M59: =IFERROR(VLOOKUP(L59,色號!A:B,2,FALSE),"") | N59: =IFERROR(VLOOKUP(M59,色號!B:C,2,FALSE),"") | O59: =IFERROR(VLOOKUP(L59,色號!A:D,4,FALSE),"") | P59: =IF( OR($E59="左門板", $E59="右門板"), "鉸" & IF($F59<=1000, 2, IF($F59<=1800, 3, 4)), IF( $E59="入柱背板", "側", IF( $E59="外蓋背板", "面", IF( AND(COUNTIF($E$52:$E$81,"入柱背板")>0, OR($E59="頂板", $E59="底板")), "面", IF( AND(COUNTIF($E$52:$E$81,"外蓋背板")>0, OR($E59="左側板", $E59="右側板")), "側", IF( AND( COUNTIF($E$52:$E$81,"入柱背板")=0, COUNTIF($E$52:$E$81,"外蓋背板")=0, OR( AND(COUNTIF($E$52:$E$81,"背板")>0, OR($E59="左側板",$E59="右側板",$E59="頂板",$E59="底板",$E59="天地蓋左側板",$E59="天地蓋右側板",$E59="天地蓋頂板",$E59="天地蓋底板")), AND(COUNTIF($E$52:$E$81,"抽底")>0, OR($E59="右抽牆",$E59="左抽牆",$E59="前抽牆",$E59="後抽牆")) ) ), "背板溝", "" ) ) ) ) ) ) | Q59: =IF(OR($E59="天地蓋右側板",$E59="天地蓋左側板"), "側 面", IF(OR($E59="背拉桿",$E59="中立板",$E59="頂板",$E59="底板",$E59="前抽牆",$E59="後抽牆",$E59="內左側落板",$E59="內右側落板",$E59="抽屜拉桿",$E59="立板"), "側", IF(OR($E59="木滑門",$E59="鋁框滑門"), "輪", IF(OR($E59="右側板",$E59="左側板",$E59="右抽牆",$E59="左抽牆",$E59="天地蓋頂板",$E59="天地蓋底板",$E59="內頂板"), "面", IF($E59="固隔","固","") ) ) ) ) | R59: =IF( OR($E59="左側板",$E59="右側板",$E59="天地蓋左側板",$E59="天地蓋右側板",$E59="中立板",$E59="立板"), "排","") | T59: =IF($E59="中立板","面開槽？排孔？", IF($E59="木框滑門","前排孔要退喔！", IF(OR($E59="左門板",$E59="右門板",$E59="抽頭"),"把手？", IF(OR($E59="左側板",$E59="右側板",$E59="天地蓋右側板",$E59="天地蓋左側板"),"排孔？","")))) | U59: =IF(E59="","",$L$48) -> 1
A60: =$C$45 -> 0 | C60: =C59+1 -> 2009 | D60: 內部 | E60: 固隔 | G60: =IF( OR( $E60="頂板",$E60="底板",$E60="右側板",$E60="左側板", $E60="天地蓋頂板",$E60="天地蓋底板",$E60="天地蓋右側板",$E60="天地蓋左側板", $E60="前抽牆",$E60="後抽牆",$E60="左抽牆",$E60="右抽牆", $E60="踢腳板",$E60="補板",$E60="固隔",$E60="活隔", $E60="中立板",$E60="中立板(退)",$E60="固隔(退)",$E60="活固隔",$E60="立板", $E60="內頂板",$E60="內左側落板",$E60="內右側落板",$E60="內底板", $E60="內左側板",$E60="內右側板", $E60="上前平肢",$E60="上後平肢",$E60="上前立肢",$E60="上後立肢", $E60="下前立肢",$E60="下後立肢",$E60="下前平肢",$E60="下後平肢", $E60="左側落板",$E60="右側落板", $E60="外蓋背板",$E60="台面",$E60="床板",$E60="假門板", $E60="上掀門板",$E60="平掀門板",$E60="下掀門板", $E60="左門板",$E60="右門板", $E60="抽盤",$E60="抽盤抽頭", $E60="上軌道板",$E60="下軌道板",$E60="左軌道板",$E60="右軌道板",$E60="指縫擋板",$E60="左木框滑門",$E60="右木框滑門", $E60="層板",$E60="壁面層板",$E60="桌板",$E60="上封板",$E60="下封板",$E60="左封板",$E60="右封板", $E60="左圓角側板",$E60="右圓角側板",$E60="抽頭",$E60="入柱抽頭",$E60="假抽頭",$E60="背拉桿",$E60="木滑門",$E60="抽屜拉桿" ), "AA", "" ) -> AA | H60: =C48-22 -> -22 | I60: =IF( OR( $E60="右側板",$E60="左側板",$E60="活隔", $E60="天地蓋頂板",$E60="天地蓋底板", $E60="左門板",$E60="右門板", $E60="左側落板",$E60="右側落板", $E60="外蓋背板",$E60="活固隔", $E60="左木框滑門",$E60="右木框滑門", $E60="左鋁框滑門",$E60="右鋁框滑門", $E60="桌板",$E60="台面",$E60="床板",$E60="假門板", $E60="上掀門板",$E60="平掀門板",$E60="下掀門板", $E60="抽盤抽頭",$E60="抽盤",$E60="層板",$E60="壁面層板", $E60="上封板",$E60="下封板",$E60="左封板",$E60="右封板", $E60="抽頭",$E60="踢腳板",$E60="補板",$E60="木滑門" ), "AA", "" ) | J60: 18 | M60: =IFERROR(VLOOKUP(L60,色號!A:B,2,FALSE),"") | N60: =IFERROR(VLOOKUP(M60,色號!B:C,2,FALSE),"") | O60: =IFERROR(VLOOKUP(L60,色號!A:D,4,FALSE),"") | P60: =IF( OR($E60="左門板", $E60="右門板"), "鉸" & IF($F60<=1000, 2, IF($F60<=1800, 3, 4)), IF( $E60="入柱背板", "側", IF( $E60="外蓋背板", "面", IF( AND(COUNTIF($E$52:$E$81,"入柱背板")>0, OR($E60="頂板", $E60="底板")), "面", IF( AND(COUNTIF($E$52:$E$81,"外蓋背板")>0, OR($E60="左側板", $E60="右側板")), "側", IF( AND( COUNTIF($E$52:$E$81,"入柱背板")=0, COUNTIF($E$52:$E$81,"外蓋背板")=0, OR( AND(COUNTIF($E$52:$E$81,"背板")>0, OR($E60="左側板",$E60="右側板",$E60="頂板",$E60="底板",$E60="天地蓋左側板",$E60="天地蓋右側板",$E60="天地蓋頂板",$E60="天地蓋底板")), AND(COUNTIF($E$52:$E$81,"抽底")>0, OR($E60="右抽牆",$E60="左抽牆",$E60="前抽牆",$E60="後抽牆")) ) ), "背板溝", "" ) ) ) ) ) ) | Q60: =IF(OR($E60="天地蓋右側板",$E60="天地蓋左側板"), "側 面", IF(OR($E60="背拉桿",$E60="中立板",$E60="頂板",$E60="底板",$E60="前抽牆",$E60="後抽牆",$E60="內左側落板",$E60="內右側落板",$E60="抽屜拉桿",$E60="立板"), "側", IF(OR($E60="木滑門",$E60="鋁框滑門"), "輪", IF(OR($E60="右側板",$E60="左側板",$E60="右抽牆",$E60="左抽牆",$E60="天地蓋頂板",$E60="天地蓋底板",$E60="內頂板"), "面", IF($E60="固隔","固","") ) ) ) ) -> 固 | R60: =IF( OR($E60="左側板",$E60="右側板",$E60="天地蓋左側板",$E60="天地蓋右側板",$E60="中立板",$E60="立板"), "排","") | T60: =IF($E60="中立板","面開槽？排孔？", IF($E60="木框滑門","前排孔要退喔！", IF(OR($E60="左門板",$E60="右門板",$E60="抽頭"),"把手？", IF(OR($E60="左側板",$E60="右側板",$E60="天地蓋右側板",$E60="天地蓋左側板"),"排孔？","")))) | U60: =IF(E60="","",$L$48) -> 1
A61: =$C$45 -> 0 | C61: =C60+1 -> 2010 | D61: 外部 | E61: 左門板 | G61: =IF( OR( $E61="頂板",$E61="底板",$E61="右側板",$E61="左側板", $E61="天地蓋頂板",$E61="天地蓋底板",$E61="天地蓋右側板",$E61="天地蓋左側板", $E61="前抽牆",$E61="後抽牆",$E61="左抽牆",$E61="右抽牆", $E61="踢腳板",$E61="補板",$E61="固隔",$E61="活隔", $E61="中立板",$E61="中立板(退)",$E61="固隔(退)",$E61="活固隔",$E61="立板", $E61="內頂板",$E61="內左側落板",$E61="內右側落板",$E61="內底板", $E61="內左側板",$E61="內右側板", $E61="上前平肢",$E61="上後平肢",$E61="上前立肢",$E61="上後立肢", $E61="下前立肢",$E61="下後立肢",$E61="下前平肢",$E61="下後平肢", $E61="左側落板",$E61="右側落板", $E61="外蓋背板",$E61="台面",$E61="床板",$E61="假門板", $E61="上掀門板",$E61="平掀門板",$E61="下掀門板", $E61="左門板",$E61="右門板", $E61="抽盤",$E61="抽盤抽頭", $E61="上軌道板",$E61="下軌道板",$E61="左軌道板",$E61="右軌道板",$E61="指縫擋板",$E61="左木框滑門",$E61="右木框滑門", $E61="層板",$E61="壁面層板",$E61="桌板",$E61="上封板",$E61="下封板",$E61="左封板",$E61="右封板", $E61="左圓角側板",$E61="右圓角側板",$E61="抽頭",$E61="入柱抽頭",$E61="假抽頭",$E61="背拉桿",$E61="木滑門",$E61="抽屜拉桿" ), "AA", "" ) -> AA | H61: =C49/2-4 -> -4 | I61: =IF( OR( $E61="右側板",$E61="左側板",$E61="活隔", $E61="天地蓋頂板",$E61="天地蓋底板", $E61="左門板",$E61="右門板", $E61="左側落板",$E61="右側落板", $E61="外蓋背板",$E61="活固隔", $E61="左木框滑門",$E61="右木框滑門", $E61="左鋁框滑門",$E61="右鋁框滑門", $E61="桌板",$E61="台面",$E61="床板",$E61="假門板", $E61="上掀門板",$E61="平掀門板",$E61="下掀門板", $E61="抽盤抽頭",$E61="抽盤",$E61="層板",$E61="壁面層板", $E61="上封板",$E61="下封板",$E61="左封板",$E61="右封板", $E61="抽頭",$E61="踢腳板",$E61="補板",$E61="木滑門" ), "AA", "" ) -> AA | J61: 18 | M61: =IFERROR(VLOOKUP(L61,色號!A:B,2,FALSE),"") | N61: =IFERROR(VLOOKUP(M61,色號!B:C,2,FALSE),"") | O61: =IFERROR(VLOOKUP(L61,色號!A:D,4,FALSE),"") | P61: =IF( OR($E61="左門板", $E61="右門板"), "鉸" & IF($F61<=1000, 2, IF($F61<=1800, 3, 4)), IF( $E61="入柱背板", "側", IF( $E61="外蓋背板", "面", IF( AND(COUNTIF($E$52:$E$81,"入柱背板")>0, OR($E61="頂板", $E61="底板")), "面", IF( AND(COUNTIF($E$52:$E$81,"外蓋背板")>0, OR($E61="左側板", $E61="右側板")), "側", IF( AND( COUNTIF($E$52:$E$81,"入柱背板")=0, COUNTIF($E$52:$E$81,"外蓋背板")=0, OR( AND(COUNTIF($E$52:$E$81,"背板")>0, OR($E61="左側板",$E61="右側板",$E61="頂板",$E61="底板",$E61="天地蓋左側板",$E61="天地蓋右側板",$E61="天地蓋頂板",$E61="天地蓋底板")), AND(COUNTIF($E$52:$E$81,"抽底")>0, OR($E61="右抽牆",$E61="左抽牆",$E61="前抽牆",$E61="後抽牆")) ) ), "背板溝", "" ) ) ) ) ) ) -> 鉸2 | T61: =IF($E61="中立板","面開槽？排孔？", IF($E61="木框滑門","前排孔要退喔！", IF(OR($E61="左門板",$E61="右門板",$E61="抽頭"),"把手？", IF(OR($E61="左側板",$E61="右側板",$E61="天地蓋右側板",$E61="天地蓋左側板"),"排孔？","")))) -> 把手？ | U61: =IF(E61="","",$L$48) -> 1
A62: =$C$45 -> 0 | C62: =C61+1 -> 2011 | D62: 外部 | E62: 右門板 | G62: =IF( OR( $E62="頂板",$E62="底板",$E62="右側板",$E62="左側板", $E62="天地蓋頂板",$E62="天地蓋底板",$E62="天地蓋右側板",$E62="天地蓋左側板", $E62="前抽牆",$E62="後抽牆",$E62="左抽牆",$E62="右抽牆", $E62="踢腳板",$E62="補板",$E62="固隔",$E62="活隔", $E62="中立板",$E62="中立板(退)",$E62="固隔(退)",$E62="活固隔",$E62="立板", $E62="內頂板",$E62="內左側落板",$E62="內右側落板",$E62="內底板", $E62="內左側板",$E62="內右側板", $E62="上前平肢",$E62="上後平肢",$E62="上前立肢",$E62="上後立肢", $E62="下前立肢",$E62="下後立肢",$E62="下前平肢",$E62="下後平肢", $E62="左側落板",$E62="右側落板", $E62="外蓋背板",$E62="台面",$E62="床板",$E62="假門板", $E62="上掀門板",$E62="平掀門板",$E62="下掀門板", $E62="左門板",$E62="右門板", $E62="抽盤",$E62="抽盤抽頭", $E62="上軌道板",$E62="下軌道板",$E62="左軌道板",$E62="右軌道板",$E62="指縫擋板",$E62="左木框滑門",$E62="右木框滑門", $E62="層板",$E62="壁面層板",$E62="桌板",$E62="上封板",$E62="下封板",$E62="左封板",$E62="右封板", $E62="左圓角側板",$E62="右圓角側板",$E62="抽頭",$E62="入柱抽頭",$E62="假抽頭",$E62="背拉桿",$E62="木滑門",$E62="抽屜拉桿" ), "AA", "" ) -> AA | H62: =C49/2-4 -> -4 | I62: =IF( OR( $E62="右側板",$E62="左側板",$E62="活隔", $E62="天地蓋頂板",$E62="天地蓋底板", $E62="左門板",$E62="右門板", $E62="左側落板",$E62="右側落板", $E62="外蓋背板",$E62="活固隔", $E62="左木框滑門",$E62="右木框滑門", $E62="左鋁框滑門",$E62="右鋁框滑門", $E62="桌板",$E62="台面",$E62="床板",$E62="假門板", $E62="上掀門板",$E62="平掀門板",$E62="下掀門板", $E62="抽盤抽頭",$E62="抽盤",$E62="層板",$E62="壁面層板", $E62="上封板",$E62="下封板",$E62="左封板",$E62="右封板", $E62="抽頭",$E62="踢腳板",$E62="補板",$E62="木滑門" ), "AA", "" ) -> AA | J62: 18 | M62: =IFERROR(VLOOKUP(L62,色號!A:B,2,FALSE),"") | N62: =IFERROR(VLOOKUP(M62,色號!B:C,2,FALSE),"") | O62: =IFERROR(VLOOKUP(L62,色號!A:D,4,FALSE),"") | P62: =IF( OR($E62="左門板", $E62="右門板"), "鉸" & IF($F62<=1000, 2, IF($F62<=1800, 3, 4)), IF( $E62="入柱背板", "側", IF( $E62="外蓋背板", "面", IF( AND(COUNTIF($E$52:$E$81,"入柱背板")>0, OR($E62="頂板", $E62="底板")), "面", IF( AND(COUNTIF($E$52:$E$81,"外蓋背板")>0, OR($E62="左側板", $E62="右側板")), "側", IF( AND( COUNTIF($E$52:$E$81,"入柱背板")=0, COUNTIF($E$52:$E$81,"外蓋背板")=0, OR( AND(COUNTIF($E$52:$E$81,"背板")>0, OR($E62="左側板",$E62="右側板",$E62="頂板",$E62="底板",$E62="天地蓋左側板",$E62="天地蓋右側板",$E62="天地蓋頂板",$E62="天地蓋底板")), AND(COUNTIF($E$52:$E$81,"抽底")>0, OR($E62="右抽牆",$E62="左抽牆",$E62="前抽牆",$E62="後抽牆")) ) ), "背板溝", "" ) ) ) ) ) ) -> 鉸2 | T62: =IF($E62="中立板","面開槽？排孔？", IF($E62="木框滑門","前排孔要退喔！", IF(OR($E62="左門板",$E62="右門板",$E62="抽頭"),"把手？", IF(OR($E62="左側板",$E62="右側板",$E62="天地蓋右側板",$E62="天地蓋左側板"),"排孔？","")))) -> 把手？ | U62: =IF(E62="","",$L$48) -> 1
A63: =$C$45 -> 0 | C63: =C62+1 -> 2012 | G63: =IF( OR( $E63="頂板",$E63="底板",$E63="右側板",$E63="左側板", $E63="天地蓋頂板",$E63="天地蓋底板",$E63="天地蓋右側板",$E63="天地蓋左側板", $E63="前抽牆",$E63="後抽牆",$E63="左抽牆",$E63="右抽牆", $E63="踢腳板",$E63="補板",$E63="固隔",$E63="活隔", $E63="中立板",$E63="中立板(退)",$E63="固隔(退)",$E63="活固隔",$E63="立板", $E63="內頂板",$E63="內左側落板",$E63="內右側落板",$E63="內底板", $E63="內左側板",$E63="內右側板", $E63="上前平肢",$E63="上後平肢",$E63="上前立肢",$E63="上後立肢", $E63="下前立肢",$E63="下後立肢",$E63="下前平肢",$E63="下後平肢", $E63="左側落板",$E63="右側落板", $E63="外蓋背板",$E63="台面",$E63="床板",$E63="假門板", $E63="上掀門板",$E63="平掀門板",$E63="下掀門板", $E63="左門板",$E63="右門板", $E63="抽盤",$E63="抽盤抽頭", $E63="上軌道板",$E63="下軌道板",$E63="左軌道板",$E63="右軌道板",$E63="指縫擋板",$E63="左木框滑門",$E63="右木框滑門", $E63="層板",$E63="壁面層板",$E63="桌板",$E63="上封板",$E63="下封板",$E63="左封板",$E63="右封板", $E63="左圓角側板",$E63="右圓角側板",$E63="抽頭",$E63="入柱抽頭",$E63="假抽頭",$E63="背拉桿",$E63="木滑門",$E63="抽屜拉桿" ), "AA", "" ) | I63: =IF( OR( $E63="右側板",$E63="左側板",$E63="活隔", $E63="天地蓋頂板",$E63="天地蓋底板", $E63="左門板",$E63="右門板", $E63="左側落板",$E63="右側落板", $E63="外蓋背板",$E63="活固隔", $E63="左木框滑門",$E63="右木框滑門", $E63="左鋁框滑門",$E63="右鋁框滑門", $E63="桌板",$E63="台面",$E63="床板",$E63="假門板", $E63="上掀門板",$E63="平掀門板",$E63="下掀門板", $E63="抽盤抽頭",$E63="抽盤",$E63="層板",$E63="壁面層板", $E63="上封板",$E63="下封板",$E63="左封板",$E63="右封板", $E63="抽頭",$E63="踢腳板",$E63="補板",$E63="木滑門" ), "AA", "" ) | J63: 18 | M63: =IFERROR(VLOOKUP(L63,色號!A:B,2,FALSE),"") | N63: =IFERROR(VLOOKUP(M63,色號!B:C,2,FALSE),"") | O63: =IFERROR(VLOOKUP(L63,色號!A:D,4,FALSE),"") | P63: =IF( OR($E63="左門板", $E63="右門板"), "鉸" & IF($F63<=1000, 2, IF($F63<=1800, 3, 4)), IF( $E63="入柱背板", "側", IF( $E63="外蓋背板", "面", IF( AND(COUNTIF($E$52:$E$81,"入柱背板")>0, OR($E63="頂板", $E63="底板")), "面", IF( AND(COUNTIF($E$52:$E$81,"外蓋背板")>0, OR($E63="左側板", $E63="右側板")), "側", IF( AND( COUNTIF($E$52:$E$81,"入柱背板")=0, COUNTIF($E$52:$E$81,"外蓋背板")=0, OR( AND(COUNTIF($E$52:$E$81,"背板")>0, OR($E63="左側板",$E63="右側板",$E63="頂板",$E63="底板",$E63="天地蓋左側板",$E63="天地蓋右側板",$E63="天地蓋頂板",$E63="天地蓋底板")), AND(COUNTIF($E$52:$E$81,"抽底")>0, OR($E63="右抽牆",$E63="左抽牆",$E63="前抽牆",$E63="後抽牆")) ) ), "背板溝", "" ) ) ) ) ) ) | T63: =IF($E63="中立板","面開槽？排孔？", IF($E63="木框滑門","前排孔要退喔！", IF(OR($E63="左門板",$E63="右門板",$E63="抽頭"),"把手？", IF(OR($E63="左側板",$E63="右側板",$E63="天地蓋右側板",$E63="天地蓋左側板"),"排孔？","")))) | U63: =IF(E63="","",$L$48)
A64: =$C$45 -> 0 | C64: =C63+1 -> 2013 | G64: =IF( OR( $E64="頂板",$E64="底板",$E64="右側板",$E64="左側板", $E64="天地蓋頂板",$E64="天地蓋底板",$E64="天地蓋右側板",$E64="天地蓋左側板", $E64="前抽牆",$E64="後抽牆",$E64="左抽牆",$E64="右抽牆", $E64="踢腳板",$E64="補板",$E64="固隔",$E64="活隔", $E64="中立板",$E64="中立板(退)",$E64="固隔(退)",$E64="活固隔",$E64="立板", $E64="內頂板",$E64="內左側落板",$E64="內右側落板",$E64="內底板", $E64="內左側板",$E64="內右側板", $E64="上前平肢",$E64="上後平肢",$E64="上前立肢",$E64="上後立肢", $E64="下前立肢",$E64="下後立肢",$E64="下前平肢",$E64="下後平肢", $E64="左側落板",$E64="右側落板", $E64="外蓋背板",$E64="台面",$E64="床板",$E64="假門板", $E64="上掀門板",$E64="平掀門板",$E64="下掀門板", $E64="左門板",$E64="右門板", $E64="抽盤",$E64="抽盤抽頭", $E64="上軌道板",$E64="下軌道板",$E64="左軌道板",$E64="右軌道板",$E64="指縫擋板",$E64="左木框滑門",$E64="右木框滑門", $E64="層板",$E64="壁面層板",$E64="桌板",$E64="上封板",$E64="下封板",$E64="左封板",$E64="右封板", $E64="左圓角側板",$E64="右圓角側板",$E64="抽頭",$E64="入柱抽頭",$E64="假抽頭",$E64="背拉桿",$E64="木滑門",$E64="抽屜拉桿" ), "AA", "" ) | I64: =IF( OR( $E64="右側板",$E64="左側板",$E64="活隔", $E64="天地蓋頂板",$E64="天地蓋底板", $E64="左門板",$E64="右門板", $E64="左側落板",$E64="右側落板", $E64="外蓋背板",$E64="活固隔", $E64="左木框滑門",$E64="右木框滑門", $E64="左鋁框滑門",$E64="右鋁框滑門", $E64="桌板",$E64="台面",$E64="床板",$E64="假門板", $E64="上掀門板",$E64="平掀門板",$E64="下掀門板", $E64="抽盤抽頭",$E64="抽盤",$E64="層板",$E64="壁面層板", $E64="上封板",$E64="下封板",$E64="左封板",$E64="右封板", $E64="抽頭",$E64="踢腳板",$E64="補板",$E64="木滑門" ), "AA", "" ) | M64: =IFERROR(VLOOKUP(L64,色號!A:B,2,FALSE),"") | N64: =IFERROR(VLOOKUP(M64,色號!B:C,2,FALSE),"") | O64: =IFERROR(VLOOKUP(L64,色號!A:D,4,FALSE),"") | P64: =IF( OR($E64="左門板", $E64="右門板"), "鉸" & IF($F64<=1000, 2, IF($F64<=1800, 3, 4)), IF( $E64="入柱背板", "側", IF( $E64="外蓋背板", "面", IF( AND(COUNTIF($E$52:$E$81,"入柱背板")>0, OR($E64="頂板", $E64="底板")), "面", IF( AND(COUNTIF($E$52:$E$81,"外蓋背板")>0, OR($E64="左側板", $E64="右側板")), "側", IF( AND( COUNTIF($E$52:$E$81,"入柱背板")=0, COUNTIF($E$52:$E$81,"外蓋背板")=0, OR( AND(COUNTIF($E$52:$E$81,"背板")>0, OR($E64="左側板",$E64="右側板",$E64="頂板",$E64="底板",$E64="天地蓋左側板",$E64="天地蓋右側板",$E64="天地蓋頂板",$E64="天地蓋底板")), AND(COUNTIF($E$52:$E$81,"抽底")>0, OR($E64="右抽牆",$E64="左抽牆",$E64="前抽牆",$E64="後抽牆")) ) ), "背板溝", "" ) ) ) ) ) ) | Q64: =IF(OR($E64="天地蓋右側板",$E64="天地蓋左側板"), "側 面", IF(OR($E64="背拉桿",$E64="中立板",$E64="頂板",$E64="底板",$E64="前抽牆",$E64="後抽牆",$E64="內左側落板",$E64="內右側落板",$E64="抽屜拉桿",$E64="立板"), "側", IF(OR($E64="木滑門",$E64="鋁框滑門"), "輪", IF(OR($E64="右側板",$E64="左側板",$E64="右抽牆",$E64="左抽牆",$E64="天地蓋頂板",$E64="天地蓋底板",$E64="內頂板"), "面", IF($E64="固隔","固","") ) ) ) ) | R64: =IF( OR($E64="左側板",$E64="右側板",$E64="天地蓋左側板",$E64="天地蓋右側板",$E64="中立板",$E64="立板"), "排","") | T64: =IF($E64="中立板","面開槽？排孔？", IF($E64="木框滑門","前排孔要退喔！", IF(OR($E64="左門板",$E64="右門板",$E64="抽頭"),"把手？", IF(OR($E64="左側板",$E64="右側板",$E64="天地蓋右側板",$E64="天地蓋左側板"),"排孔？","")))) | U64: =IF(E64="","",$L$48)
A65: =$C$45 -> 0 | C65: =C64+1 -> 2014 | G65: =IF( OR( $E65="頂板",$E65="底板",$E65="右側板",$E65="左側板", $E65="天地蓋頂板",$E65="天地蓋底板",$E65="天地蓋右側板",$E65="天地蓋左側板", $E65="前抽牆",$E65="後抽牆",$E65="左抽牆",$E65="右抽牆", $E65="踢腳板",$E65="補板",$E65="固隔",$E65="活隔", $E65="中立板",$E65="中立板(退)",$E65="固隔(退)",$E65="活固隔",$E65="立板", $E65="內頂板",$E65="內左側落板",$E65="內右側落板",$E65="內底板", $E65="內左側板",$E65="內右側板", $E65="上前平肢",$E65="上後平肢",$E65="上前立肢",$E65="上後立肢", $E65="下前立肢",$E65="下後立肢",$E65="下前平肢",$E65="下後平肢", $E65="左側落板",$E65="右側落板", $E65="外蓋背板",$E65="台面",$E65="床板",$E65="假門板", $E65="上掀門板",$E65="平掀門板",$E65="下掀門板", $E65="左門板",$E65="右門板", $E65="抽盤",$E65="抽盤抽頭", $E65="上軌道板",$E65="下軌道板",$E65="左軌道板",$E65="右軌道板",$E65="指縫擋板",$E65="左木框滑門",$E65="右木框滑門", $E65="層板",$E65="壁面層板",$E65="桌板",$E65="上封板",$E65="下封板",$E65="左封板",$E65="右封板", $E65="左圓角側板",$E65="右圓角側板",$E65="抽頭",$E65="入柱抽頭",$E65="假抽頭",$E65="背拉桿",$E65="木滑門",$E65="抽屜拉桿" ), "AA", "" ) | I65: =IF( OR( $E65="右側板",$E65="左側板",$E65="活隔", $E65="天地蓋頂板",$E65="天地蓋底板", $E65="左門板",$E65="右門板", $E65="左側落板",$E65="右側落板", $E65="外蓋背板",$E65="活固隔", $E65="左木框滑門",$E65="右木框滑門", $E65="左鋁框滑門",$E65="右鋁框滑門", $E65="桌板",$E65="台面",$E65="床板",$E65="假門板", $E65="上掀門板",$E65="平掀門板",$E65="下掀門板", $E65="抽盤抽頭",$E65="抽盤",$E65="層板",$E65="壁面層板", $E65="上封板",$E65="下封板",$E65="左封板",$E65="右封板", $E65="抽頭",$E65="踢腳板",$E65="補板",$E65="木滑門" ), "AA", "" ) | M65: =IFERROR(VLOOKUP(L65,色號!A:B,2,FALSE),"") | N65: =IFERROR(VLOOKUP(M65,色號!B:C,2,FALSE),"") | O65: =IFERROR(VLOOKUP(L65,色號!A:D,4,FALSE),"") | P65: =IF( OR($E65="左門板", $E65="右門板"), "鉸" & IF($F65<=1000, 2, IF($F65<=1800, 3, 4)), IF( $E65="入柱背板", "側", IF( $E65="外蓋背板", "面", IF( AND(COUNTIF($E$52:$E$81,"入柱背板")>0, OR($E65="頂板", $E65="底板")), "面", IF( AND(COUNTIF($E$52:$E$81,"外蓋背板")>0, OR($E65="左側板", $E65="右側板")), "側", IF( AND( COUNTIF($E$52:$E$81,"入柱背板")=0, COUNTIF($E$52:$E$81,"外蓋背板")=0, OR( AND(COUNTIF($E$52:$E$81,"背板")>0, OR($E65="左側板",$E65="右側板",$E65="頂板",$E65="底板",$E65="天地蓋左側板",$E65="天地蓋右側板",$E65="天地蓋頂板",$E65="天地蓋底板")), AND(COUNTIF($E$52:$E$81,"抽底")>0, OR($E65="右抽牆",$E65="左抽牆",$E65="前抽牆",$E65="後抽牆")) ) ), "背板溝", "" ) ) ) ) ) ) | Q65: =IF(OR($E65="天地蓋右側板",$E65="天地蓋左側板"), "側 面", IF(OR($E65="背拉桿",$E65="中立板",$E65="頂板",$E65="底板",$E65="前抽牆",$E65="後抽牆",$E65="內左側落板",$E65="內右側落板",$E65="抽屜拉桿",$E65="立板"), "側", IF(OR($E65="木滑門",$E65="鋁框滑門"), "輪", IF(OR($E65="右側板",$E65="左側板",$E65="右抽牆",$E65="左抽牆",$E65="天地蓋頂板",$E65="天地蓋底板",$E65="內頂板"), "面", IF($E65="固隔","固","") ) ) ) ) | R65: =IF( OR($E65="左側板",$E65="右側板",$E65="天地蓋左側板",$E65="天地蓋右側板",$E65="中立板",$E65="立板"), "排","") | T65: =IF($E65="中立板","面開槽？排孔？", IF($E65="木框滑門","前排孔要退喔！", IF(OR($E65="左門板",$E65="右門板",$E65="抽頭"),"把手？", IF(OR($E65="左側板",$E65="右側板",$E65="天地蓋右側板",$E65="天地蓋左側板"),"排孔？","")))) | U65: =IF(E65="","",$L$48)
A66: =$C$45 -> 0 | C66: =C65+1 -> 2015 | G66: =IF( OR( $E66="頂板",$E66="底板",$E66="右側板",$E66="左側板", $E66="天地蓋頂板",$E66="天地蓋底板",$E66="天地蓋右側板",$E66="天地蓋左側板", $E66="前抽牆",$E66="後抽牆",$E66="左抽牆",$E66="右抽牆", $E66="踢腳板",$E66="補板",$E66="固隔",$E66="活隔", $E66="中立板",$E66="中立板(退)",$E66="固隔(退)",$E66="活固隔",$E66="立板", $E66="內頂板",$E66="內左側落板",$E66="內右側落板",$E66="內底板", $E66="內左側板",$E66="內右側板", $E66="上前平肢",$E66="上後平肢",$E66="上前立肢",$E66="上後立肢", $E66="下前立肢",$E66="下後立肢",$E66="下前平肢",$E66="下後平肢", $E66="左側落板",$E66="右側落板", $E66="外蓋背板",$E66="台面",$E66="床板",$E66="假門板", $E66="上掀門板",$E66="平掀門板",$E66="下掀門板", $E66="左門板",$E66="右門板", $E66="抽盤",$E66="抽盤抽頭", $E66="上軌道板",$E66="下軌道板",$E66="左軌道板",$E66="右軌道板",$E66="指縫擋板",$E66="左木框滑門",$E66="右木框滑門", $E66="層板",$E66="壁面層板",$E66="桌板",$E66="上封板",$E66="下封板",$E66="左封板",$E66="右封板", $E66="左圓角側板",$E66="右圓角側板",$E66="抽頭",$E66="入柱抽頭",$E66="假抽頭",$E66="背拉桿",$E66="木滑門",$E66="抽屜拉桿" ), "AA", "" ) | I66: =IF( OR( $E66="右側板",$E66="左側板",$E66="活隔", $E66="天地蓋頂板",$E66="天地蓋底板", $E66="左門板",$E66="右門板", $E66="左側落板",$E66="右側落板", $E66="外蓋背板",$E66="活固隔", $E66="左木框滑門",$E66="右木框滑門", $E66="左鋁框滑門",$E66="右鋁框滑門", $E66="桌板",$E66="台面",$E66="床板",$E66="假門板", $E66="上掀門板",$E66="平掀門板",$E66="下掀門板", $E66="抽盤抽頭",$E66="抽盤",$E66="層板",$E66="壁面層板", $E66="上封板",$E66="下封板",$E66="左封板",$E66="右封板", $E66="抽頭",$E66="踢腳板",$E66="補板",$E66="木滑門" ), "AA", "" ) | M66: =IFERROR(VLOOKUP(L66,色號!A:B,2,FALSE),"") | N66: =IFERROR(VLOOKUP(M66,色號!B:C,2,FALSE),"") | O66: =IFERROR(VLOOKUP(L66,色號!A:D,4,FALSE),"") | P66: =IF( OR($E66="左門板", $E66="右門板"), "鉸" & IF($F66<=1000, 2, IF($F66<=1800, 3, 4)), IF( $E66="入柱背板", "側", IF( $E66="外蓋背板", "面", IF( AND(COUNTIF($E$52:$E$81,"入柱背板")>0, OR($E66="頂板", $E66="底板")), "面", IF( AND(COUNTIF($E$52:$E$81,"外蓋背板")>0, OR($E66="左側板", $E66="右側板")), "側", IF( AND( COUNTIF($E$52:$E$81,"入柱背板")=0, COUNTIF($E$52:$E$81,"外蓋背板")=0, OR( AND(COUNTIF($E$52:$E$81,"背板")>0, OR($E66="左側板",$E66="右側板",$E66="頂板",$E66="底板",$E66="天地蓋左側板",$E66="天地蓋右側板",$E66="天地蓋頂板",$E66="天地蓋底板")), AND(COUNTIF($E$52:$E$81,"抽底")>0, OR($E66="右抽牆",$E66="左抽牆",$E66="前抽牆",$E66="後抽牆")) ) ), "背板溝", "" ) ) ) ) ) ) | Q66: =IF(OR($E66="天地蓋右側板",$E66="天地蓋左側板"), "側 面", IF(OR($E66="背拉桿",$E66="中立板",$E66="頂板",$E66="底板",$E66="前抽牆",$E66="後抽牆",$E66="內左側落板",$E66="內右側落板",$E66="抽屜拉桿",$E66="立板"), "側", IF(OR($E66="木滑門",$E66="鋁框滑門"), "輪", IF(OR($E66="右側板",$E66="左側板",$E66="右抽牆",$E66="左抽牆",$E66="天地蓋頂板",$E66="天地蓋底板",$E66="內頂板"), "面", IF($E66="固隔","固","") ) ) ) ) | R66: =IF( OR($E66="左側板",$E66="右側板",$E66="天地蓋左側板",$E66="天地蓋右側板",$E66="中立板",$E66="立板"), "排","") | T66: =IF($E66="中立板","面開槽？排孔？", IF($E66="木框滑門","前排孔要退喔！", IF(OR($E66="左門板",$E66="右門板",$E66="抽頭"),"把手？", IF(OR($E66="左側板",$E66="右側板",$E66="天地蓋右側板",$E66="天地蓋左側板"),"排孔？","")))) | U66: =IF(E66="","",$L$48)
A67: =$C$45 -> 0 | C67: =C66+1 -> 2016 | I67: =IF( OR( $E67="右側板",$E67="左側板",$E67="活隔", $E67="天地蓋頂板",$E67="天地蓋底板", $E67="左門板",$E67="右門板", $E67="左側落板",$E67="右側落板", $E67="外蓋背板",$E67="活固隔", $E67="左木框滑門",$E67="右木框滑門", $E67="左鋁框滑門",$E67="右鋁框滑門", $E67="桌板",$E67="台面",$E67="床板",$E67="假門板", $E67="上掀門板",$E67="平掀門板",$E67="下掀門板", $E67="抽盤抽頭",$E67="抽盤",$E67="層板",$E67="壁面層板", $E67="上封板",$E67="下封板",$E67="左封板",$E67="右封板", $E67="抽頭",$E67="踢腳板",$E67="補板",$E67="木滑門" ), "AA", "" ) | M67: =IFERROR(VLOOKUP(L67,色號!A:B,2,FALSE),"") | N67: =IFERROR(VLOOKUP(M67,色號!B:C,2,FALSE),"") | O67: =IFERROR(VLOOKUP(L67,色號!A:D,4,FALSE),"") | P67: =IF( OR($E67="左門板", $E67="右門板"), "鉸" & IF($F67<=1000, 2, IF($F67<=1800, 3, 4)), IF( $E67="入柱背板", "側", IF( $E67="外蓋背板", "面", IF( AND(COUNTIF($E$52:$E$81,"入柱背板")>0, OR($E67="頂板", $E67="底板")), "面", IF( AND(COUNTIF($E$52:$E$81,"外蓋背板")>0, OR($E67="左側板", $E67="右側板")), "側", IF( AND( COUNTIF($E$52:$E$81,"入柱背板")=0, COUNTIF($E$52:$E$81,"外蓋背板")=0, OR( AND(COUNTIF($E$52:$E$81,"背板")>0, OR($E67="左側板",$E67="右側板",$E67="頂板",$E67="底板",$E67="天地蓋左側板",$E67="天地蓋右側板",$E67="天地蓋頂板",$E67="天地蓋底板")), AND(COUNTIF($E$52:$E$81,"抽底")>0, OR($E67="右抽牆",$E67="左抽牆",$E67="前抽牆",$E67="後抽牆")) ) ), "背板溝", "" ) ) ) ) ) ) | Q67: =IF(OR($E67="天地蓋右側板",$E67="天地蓋左側板"), "側 面", IF(OR($E67="背拉桿",$E67="中立板",$E67="頂板",$E67="底板",$E67="前抽牆",$E67="後抽牆",$E67="內左側落板",$E67="內右側落板",$E67="抽屜拉桿",$E67="立板"), "側", IF(OR($E67="木滑門",$E67="鋁框滑門"), "輪", IF(OR($E67="右側板",$E67="左側板",$E67="右抽牆",$E67="左抽牆",$E67="天地蓋頂板",$E67="天地蓋底板",$E67="內頂板"), "面", IF($E67="固隔","固","") ) ) ) ) | R67: =IF( OR($E67="左側板",$E67="右側板",$E67="天地蓋左側板",$E67="天地蓋右側板",$E67="中立板",$E67="立板"), "排","") | T67: =IF($E67="中立板","面開槽？排孔？", IF($E67="木框滑門","前排孔要退喔！", IF(OR($E67="左門板",$E67="右門板",$E67="抽頭"),"把手？", IF(OR($E67="左側板",$E67="右側板",$E67="天地蓋右側板",$E67="天地蓋左側板"),"排孔？","")))) | U67: =IF(E67="","",$L$48)
A68: =$C$45 -> 0 | C68: =C67+1 -> 2017 | G68: =IF( OR( $E68="頂板",$E68="底板",$E68="右側板",$E68="左側板", $E68="天地蓋頂板",$E68="天地蓋底板",$E68="天地蓋右側板",$E68="天地蓋左側板", $E68="前抽牆",$E68="後抽牆",$E68="左抽牆",$E68="右抽牆", $E68="踢腳板",$E68="補板",$E68="固隔",$E68="活隔", $E68="中立板",$E68="中立板(退)",$E68="固隔(退)",$E68="活固隔",$E68="立板", $E68="內頂板",$E68="內左側落板",$E68="內右側落板",$E68="內底板", $E68="內左側板",$E68="內右側板", $E68="上前平肢",$E68="上後平肢",$E68="上前立肢",$E68="上後立肢", $E68="下前立肢",$E68="下後立肢",$E68="下前平肢",$E68="下後平肢", $E68="左側落板",$E68="右側落板", $E68="外蓋背板",$E68="台面",$E68="床板",$E68="假門板", $E68="上掀門板",$E68="平掀門板",$E68="下掀門板", $E68="左門板",$E68="右門板", $E68="抽盤",$E68="抽盤抽頭", $E68="上軌道板",$E68="下軌道板",$E68="左軌道板",$E68="右軌道板",$E68="指縫擋板",$E68="左木框滑門",$E68="右木框滑門", $E68="層板",$E68="壁面層板",$E68="桌板",$E68="上封板",$E68="下封板",$E68="左封板",$E68="右封板", $E68="左圓角側板",$E68="右圓角側板",$E68="抽頭",$E68="入柱抽頭",$E68="假抽頭",$E68="背拉桿",$E68="木滑門",$E68="抽屜拉桿" ), "AA", "" ) | I68: =IF( OR( $E68="右側板",$E68="左側板",$E68="活隔", $E68="天地蓋頂板",$E68="天地蓋底板", $E68="左門板",$E68="右門板", $E68="左側落板",$E68="右側落板", $E68="外蓋背板",$E68="活固隔", $E68="左木框滑門",$E68="右木框滑門", $E68="左鋁框滑門",$E68="右鋁框滑門", $E68="桌板",$E68="台面",$E68="床板",$E68="假門板", $E68="上掀門板",$E68="平掀門板",$E68="下掀門板", $E68="抽盤抽頭",$E68="抽盤",$E68="層板",$E68="壁面層板", $E68="上封板",$E68="下封板",$E68="左封板",$E68="右封板", $E68="抽頭",$E68="踢腳板",$E68="補板",$E68="木滑門" ), "AA", "" ) | M68: =IFERROR(VLOOKUP(L68,色號!A:B,2,FALSE),"") | N68: =IFERROR(VLOOKUP(M68,色號!B:C,2,FALSE),"") | O68: =IFERROR(VLOOKUP(L68,色號!A:D,4,FALSE),"") | P68: =IF( OR($E68="左門板", $E68="右門板"), "鉸" & IF($F68<=1000, 2, IF($F68<=1800, 3, 4)), IF( $E68="入柱背板", "側", IF( $E68="外蓋背板", "面", IF( AND(COUNTIF($E$52:$E$81,"入柱背板")>0, OR($E68="頂板", $E68="底板")), "面", IF( AND(COUNTIF($E$52:$E$81,"外蓋背板")>0, OR($E68="左側板", $E68="右側板")), "側", IF( AND( COUNTIF($E$52:$E$81,"入柱背板")=0, COUNTIF($E$52:$E$81,"外蓋背板")=0, OR( AND(COUNTIF($E$52:$E$81,"背板")>0, OR($E68="左側板",$E68="右側板",$E68="頂板",$E68="底板",$E68="天地蓋左側板",$E68="天地蓋右側板",$E68="天地蓋頂板",$E68="天地蓋底板")), AND(COUNTIF($E$52:$E$81,"抽底")>0, OR($E68="右抽牆",$E68="左抽牆",$E68="前抽牆",$E68="後抽牆")) ) ), "背板溝", "" ) ) ) ) ) ) | Q68: =IF(OR($E68="天地蓋右側板",$E68="天地蓋左側板"), "側 面", IF(OR($E68="背拉桿",$E68="中立板",$E68="頂板",$E68="底板",$E68="前抽牆",$E68="後抽牆",$E68="內左側落板",$E68="內右側落板",$E68="抽屜拉桿",$E68="立板"), "側", IF(OR($E68="木滑門",$E68="鋁框滑門"), "輪", IF(OR($E68="右側板",$E68="左側板",$E68="右抽牆",$E68="左抽牆",$E68="天地蓋頂板",$E68="天地蓋底板",$E68="內頂板"), "面", IF($E68="固隔","固","") ) ) ) ) | R68: =IF( OR($E68="左側板",$E68="右側板",$E68="天地蓋左側板",$E68="天地蓋右側板",$E68="中立板",$E68="立板"), "排","") | T68: =IF($E68="中立板","面開槽？排孔？", IF($E68="木框滑門","前排孔要退喔！", IF(OR($E68="左門板",$E68="右門板",$E68="抽頭"),"把手？", IF(OR($E68="左側板",$E68="右側板",$E68="天地蓋右側板",$E68="天地蓋左側板"),"排孔？","")))) | U68: =IF(E68="","",$L$48)
A69: =$C$45 -> 0 | C69: =C68+1 -> 2018 | G69: =IF( OR( $E69="頂板",$E69="底板",$E69="右側板",$E69="左側板", $E69="天地蓋頂板",$E69="天地蓋底板",$E69="天地蓋右側板",$E69="天地蓋左側板", $E69="前抽牆",$E69="後抽牆",$E69="左抽牆",$E69="右抽牆", $E69="踢腳板",$E69="補板",$E69="固隔",$E69="活隔", $E69="中立板",$E69="中立板(退)",$E69="固隔(退)",$E69="活固隔",$E69="立板", $E69="內頂板",$E69="內左側落板",$E69="內右側落板",$E69="內底板", $E69="內左側板",$E69="內右側板", $E69="上前平肢",$E69="上後平肢",$E69="上前立肢",$E69="上後立肢", $E69="下前立肢",$E69="下後立肢",$E69="下前平肢",$E69="下後平肢", $E69="左側落板",$E69="右側落板", $E69="外蓋背板",$E69="台面",$E69="床板",$E69="假門板", $E69="上掀門板",$E69="平掀門板",$E69="下掀門板", $E69="左門板",$E69="右門板", $E69="抽盤",$E69="抽盤抽頭", $E69="上軌道板",$E69="下軌道板",$E69="左軌道板",$E69="右軌道板",$E69="指縫擋板",$E69="左木框滑門",$E69="右木框滑門", $E69="層板",$E69="壁面層板",$E69="桌板",$E69="上封板",$E69="下封板",$E69="左封板",$E69="右封板", $E69="左圓角側板",$E69="右圓角側板",$E69="抽頭",$E69="入柱抽頭",$E69="假抽頭",$E69="背拉桿",$E69="木滑門",$E69="抽屜拉桿" ), "AA", "" ) | I69: =IF( OR( $E69="右側板",$E69="左側板",$E69="活隔", $E69="天地蓋頂板",$E69="天地蓋底板", $E69="左門板",$E69="右門板", $E69="左側落板",$E69="右側落板", $E69="外蓋背板",$E69="活固隔", $E69="左木框滑門",$E69="右木框滑門", $E69="左鋁框滑門",$E69="右鋁框滑門", $E69="桌板",$E69="台面",$E69="床板",$E69="假門板", $E69="上掀門板",$E69="平掀門板",$E69="下掀門板", $E69="抽盤抽頭",$E69="抽盤",$E69="層板",$E69="壁面層板", $E69="上封板",$E69="下封板",$E69="左封板",$E69="右封板", $E69="抽頭",$E69="踢腳板",$E69="補板",$E69="木滑門" ), "AA", "" ) | M69: =IFERROR(VLOOKUP(L69,色號!A:B,2,FALSE),"") | N69: =IFERROR(VLOOKUP(M69,色號!B:C,2,FALSE),"") | O69: =IFERROR(VLOOKUP(L69,色號!A:D,4,FALSE),"") | P69: =IF( OR($E69="左門板", $E69="右門板"), "鉸" & IF($F69<=1000, 2, IF($F69<=1800, 3, 4)), IF( $E69="入柱背板", "側", IF( $E69="外蓋背板", "面", IF( AND(COUNTIF($E$52:$E$81,"入柱背板")>0, OR($E69="頂板", $E69="底板")), "面", IF( AND(COUNTIF($E$52:$E$81,"外蓋背板")>0, OR($E69="左側板", $E69="右側板")), "側", IF( AND( COUNTIF($E$52:$E$81,"入柱背板")=0, COUNTIF($E$52:$E$81,"外蓋背板")=0, OR( AND(COUNTIF($E$52:$E$81,"背板")>0, OR($E69="左側板",$E69="右側板",$E69="頂板",$E69="底板",$E69="天地蓋左側板",$E69="天地蓋右側板",$E69="天地蓋頂板",$E69="天地蓋底板")), AND(COUNTIF($E$52:$E$81,"抽底")>0, OR($E69="右抽牆",$E69="左抽牆",$E69="前抽牆",$E69="後抽牆")) ) ), "背板溝", "" ) ) ) ) ) ) | Q69: =IF(OR($E69="天地蓋右側板",$E69="天地蓋左側板"), "側 面", IF(OR($E69="背拉桿",$E69="中立板",$E69="頂板",$E69="底板",$E69="前抽牆",$E69="後抽牆",$E69="內左側落板",$E69="內右側落板",$E69="抽屜拉桿",$E69="立板"), "側", IF(OR($E69="木滑門",$E69="鋁框滑門"), "輪", IF(OR($E69="右側板",$E69="左側板",$E69="右抽牆",$E69="左抽牆",$E69="天地蓋頂板",$E69="天地蓋底板",$E69="內頂板"), "面", IF($E69="固隔","固","") ) ) ) ) | R69: =IF( OR($E69="左側板",$E69="右側板",$E69="天地蓋左側板",$E69="天地蓋右側板",$E69="中立板",$E69="立板"), "排","") | T69: =IF($E69="中立板","面開槽？排孔？", IF($E69="木框滑門","前排孔要退喔！", IF(OR($E69="左門板",$E69="右門板",$E69="抽頭"),"把手？", IF(OR($E69="左側板",$E69="右側板",$E69="天地蓋右側板",$E69="天地蓋左側板"),"排孔？","")))) | U69: =IF(E69="","",$L$48)
A70: =$C$45 -> 0 | C70: =C69+1 -> 2019 | G70: =IF( OR( $E70="頂板",$E70="底板",$E70="右側板",$E70="左側板", $E70="天地蓋頂板",$E70="天地蓋底板",$E70="天地蓋右側板",$E70="天地蓋左側板", $E70="前抽牆",$E70="後抽牆",$E70="左抽牆",$E70="右抽牆", $E70="踢腳板",$E70="補板",$E70="固隔",$E70="活隔", $E70="中立板",$E70="中立板(退)",$E70="固隔(退)",$E70="活固隔",$E70="立板", $E70="內頂板",$E70="內左側落板",$E70="內右側落板",$E70="內底板", $E70="內左側板",$E70="內右側板", $E70="上前平肢",$E70="上後平肢",$E70="上前立肢",$E70="上後立肢", $E70="下前立肢",$E70="下後立肢",$E70="下前平肢",$E70="下後平肢", $E70="左側落板",$E70="右側落板", $E70="外蓋背板",$E70="台面",$E70="床板",$E70="假門板", $E70="上掀門板",$E70="平掀門板",$E70="下掀門板", $E70="左門板",$E70="右門板", $E70="抽盤",$E70="抽盤抽頭", $E70="上軌道板",$E70="下軌道板",$E70="左軌道板",$E70="右軌道板",$E70="指縫擋板",$E70="左木框滑門",$E70="右木框滑門", $E70="層板",$E70="壁面層板",$E70="桌板",$E70="上封板",$E70="下封板",$E70="左封板",$E70="右封板", $E70="左圓角側板",$E70="右圓角側板",$E70="抽頭",$E70="入柱抽頭",$E70="假抽頭",$E70="背拉桿",$E70="木滑門",$E70="抽屜拉桿" ), "AA", "" ) | I70: =IF( OR( $E70="右側板",$E70="左側板",$E70="活隔", $E70="天地蓋頂板",$E70="天地蓋底板", $E70="左門板",$E70="右門板", $E70="左側落板",$E70="右側落板", $E70="外蓋背板",$E70="活固隔", $E70="左木框滑門",$E70="右木框滑門", $E70="左鋁框滑門",$E70="右鋁框滑門", $E70="桌板",$E70="台面",$E70="床板",$E70="假門板", $E70="上掀門板",$E70="平掀門板",$E70="下掀門板", $E70="抽盤抽頭",$E70="抽盤",$E70="層板",$E70="壁面層板", $E70="上封板",$E70="下封板",$E70="左封板",$E70="右封板", $E70="抽頭",$E70="踢腳板",$E70="補板",$E70="木滑門" ), "AA", "" ) | M70: =IFERROR(VLOOKUP(L70,色號!A:B,2,FALSE),"") | N70: =IFERROR(VLOOKUP(M70,色號!B:C,2,FALSE),"") | O70: =IFERROR(VLOOKUP(L70,色號!A:D,4,FALSE),"") | P70: =IF( OR($E70="左門板", $E70="右門板"), "鉸" & IF($F70<=1000, 2, IF($F70<=1800, 3, 4)), IF( $E70="入柱背板", "側", IF( $E70="外蓋背板", "面", IF( AND(COUNTIF($E$52:$E$81,"入柱背板")>0, OR($E70="頂板", $E70="底板")), "面", IF( AND(COUNTIF($E$52:$E$81,"外蓋背板")>0, OR($E70="左側板", $E70="右側板")), "側", IF( AND( COUNTIF($E$52:$E$81,"入柱背板")=0, COUNTIF($E$52:$E$81,"外蓋背板")=0, OR( AND(COUNTIF($E$52:$E$81,"背板")>0, OR($E70="左側板",$E70="右側板",$E70="頂板",$E70="底板",$E70="天地蓋左側板",$E70="天地蓋右側板",$E70="天地蓋頂板",$E70="天地蓋底板")), AND(COUNTIF($E$52:$E$81,"抽底")>0, OR($E70="右抽牆",$E70="左抽牆",$E70="前抽牆",$E70="後抽牆")) ) ), "背板溝", "" ) ) ) ) ) ) | Q70: =IF(OR($E70="天地蓋右側板",$E70="天地蓋左側板"), "側 面", IF(OR($E70="背拉桿",$E70="中立板",$E70="頂板",$E70="底板",$E70="前抽牆",$E70="後抽牆",$E70="內左側落板",$E70="內右側落板",$E70="抽屜拉桿",$E70="立板"), "側", IF(OR($E70="木滑門",$E70="鋁框滑門"), "輪", IF(OR($E70="右側板",$E70="左側板",$E70="右抽牆",$E70="左抽牆",$E70="天地蓋頂板",$E70="天地蓋底板",$E70="內頂板"), "面", IF($E70="固隔","固","") ) ) ) ) | R70: =IF( OR($E70="左側板",$E70="右側板",$E70="天地蓋左側板",$E70="天地蓋右側板",$E70="中立板",$E70="立板"), "排","") | T70: =IF($E70="中立板","面開槽？排孔？", IF($E70="木框滑門","前排孔要退喔！", IF(OR($E70="左門板",$E70="右門板",$E70="抽頭"),"把手？", IF(OR($E70="左側板",$E70="右側板",$E70="天地蓋右側板",$E70="天地蓋左側板"),"排孔？","")))) | U70: =IF(E70="","",$L$48)
A71: =$C$45 -> 0 | C71: =C70+1 -> 2020 | G71: =IF( OR( $E71="頂板",$E71="底板",$E71="右側板",$E71="左側板", $E71="天地蓋頂板",$E71="天地蓋底板",$E71="天地蓋右側板",$E71="天地蓋左側板", $E71="前抽牆",$E71="後抽牆",$E71="左抽牆",$E71="右抽牆", $E71="踢腳板",$E71="補板",$E71="固隔",$E71="活隔", $E71="中立板",$E71="中立板(退)",$E71="固隔(退)",$E71="活固隔",$E71="立板", $E71="內頂板",$E71="內左側落板",$E71="內右側落板",$E71="內底板", $E71="內左側板",$E71="內右側板", $E71="上前平肢",$E71="上後平肢",$E71="上前立肢",$E71="上後立肢", $E71="下前立肢",$E71="下後立肢",$E71="下前平肢",$E71="下後平肢", $E71="左側落板",$E71="右側落板", $E71="外蓋背板",$E71="台面",$E71="床板",$E71="假門板", $E71="上掀門板",$E71="平掀門板",$E71="下掀門板", $E71="左門板",$E71="右門板", $E71="抽盤",$E71="抽盤抽頭", $E71="上軌道板",$E71="下軌道板",$E71="左軌道板",$E71="右軌道板",$E71="指縫擋板",$E71="左木框滑門",$E71="右木框滑門", $E71="層板",$E71="壁面層板",$E71="桌板",$E71="上封板",$E71="下封板",$E71="左封板",$E71="右封板", $E71="左圓角側板",$E71="右圓角側板",$E71="抽頭",$E71="入柱抽頭",$E71="假抽頭",$E71="背拉桿",$E71="木滑門",$E71="抽屜拉桿" ), "AA", "" ) | I71: =IF( OR( $E71="右側板",$E71="左側板",$E71="活隔", $E71="天地蓋頂板",$E71="天地蓋底板", $E71="左門板",$E71="右門板", $E71="左側落板",$E71="右側落板", $E71="外蓋背板",$E71="活固隔", $E71="左木框滑門",$E71="右木框滑門", $E71="左鋁框滑門",$E71="右鋁框滑門", $E71="桌板",$E71="台面",$E71="床板",$E71="假門板", $E71="上掀門板",$E71="平掀門板",$E71="下掀門板", $E71="抽盤抽頭",$E71="抽盤",$E71="層板",$E71="壁面層板", $E71="上封板",$E71="下封板",$E71="左封板",$E71="右封板", $E71="抽頭",$E71="踢腳板",$E71="補板",$E71="木滑門" ), "AA", "" ) | M71: =IFERROR(VLOOKUP(L71,色號!A:B,2,FALSE),"") | N71: =IFERROR(VLOOKUP(M71,色號!B:C,2,FALSE),"") | O71: =IFERROR(VLOOKUP(L71,色號!A:D,4,FALSE),"") | P71: =IF( OR($E71="左門板", $E71="右門板"), "鉸" & IF($F71<=1000, 2, IF($F71<=1800, 3, 4)), IF( $E71="入柱背板", "側", IF( $E71="外蓋背板", "面", IF( AND(COUNTIF($E$52:$E$81,"入柱背板")>0, OR($E71="頂板", $E71="底板")), "面", IF( AND(COUNTIF($E$52:$E$81,"外蓋背板")>0, OR($E71="左側板", $E71="右側板")), "側", IF( AND( COUNTIF($E$52:$E$81,"入柱背板")=0, COUNTIF($E$52:$E$81,"外蓋背板")=0, OR( AND(COUNTIF($E$52:$E$81,"背板")>0, OR($E71="左側板",$E71="右側板",$E71="頂板",$E71="底板",$E71="天地蓋左側板",$E71="天地蓋右側板",$E71="天地蓋頂板",$E71="天地蓋底板")), AND(COUNTIF($E$52:$E$81,"抽底")>0, OR($E71="右抽牆",$E71="左抽牆",$E71="前抽牆",$E71="後抽牆")) ) ), "背板溝", "" ) ) ) ) ) ) | Q71: =IF(OR($E71="天地蓋右側板",$E71="天地蓋左側板"), "側 面", IF(OR($E71="背拉桿",$E71="中立板",$E71="頂板",$E71="底板",$E71="前抽牆",$E71="後抽牆",$E71="內左側落板",$E71="內右側落板",$E71="抽屜拉桿",$E71="立板"), "側", IF(OR($E71="木滑門",$E71="鋁框滑門"), "輪", IF(OR($E71="右側板",$E71="左側板",$E71="右抽牆",$E71="左抽牆",$E71="天地蓋頂板",$E71="天地蓋底板",$E71="內頂板"), "面", IF($E71="固隔","固","") ) ) ) ) | R71: =IF( OR($E71="左側板",$E71="右側板",$E71="天地蓋左側板",$E71="天地蓋右側板",$E71="中立板",$E71="立板"), "排","") | T71: =IF($E71="中立板","面開槽？排孔？", IF($E71="木框滑門","前排孔要退喔！", IF(OR($E71="左門板",$E71="右門板",$E71="抽頭"),"把手？", IF(OR($E71="左側板",$E71="右側板",$E71="天地蓋右側板",$E71="天地蓋左側板"),"排孔？","")))) | U71: =IF(E71="","",$L$48)
A72: =$C$45 -> 0 | C72: =C71+1 -> 2021 | G72: =IF( OR( $E72="頂板",$E72="底板",$E72="右側板",$E72="左側板", $E72="天地蓋頂板",$E72="天地蓋底板",$E72="天地蓋右側板",$E72="天地蓋左側板", $E72="前抽牆",$E72="後抽牆",$E72="左抽牆",$E72="右抽牆", $E72="踢腳板",$E72="補板",$E72="固隔",$E72="活隔", $E72="中立板",$E72="中立板(退)",$E72="固隔(退)",$E72="活固隔",$E72="立板", $E72="內頂板",$E72="內左側落板",$E72="內右側落板",$E72="內底板", $E72="內左側板",$E72="內右側板", $E72="上前平肢",$E72="上後平肢",$E72="上前立肢",$E72="上後立肢", $E72="下前立肢",$E72="下後立肢",$E72="下前平肢",$E72="下後平肢", $E72="左側落板",$E72="右側落板", $E72="外蓋背板",$E72="台面",$E72="床板",$E72="假門板", $E72="上掀門板",$E72="平掀門板",$E72="下掀門板", $E72="左門板",$E72="右門板", $E72="抽盤",$E72="抽盤抽頭", $E72="上軌道板",$E72="下軌道板",$E72="左軌道板",$E72="右軌道板",$E72="指縫擋板",$E72="左木框滑門",$E72="右木框滑門", $E72="層板",$E72="壁面層板",$E72="桌板",$E72="上封板",$E72="下封板",$E72="左封板",$E72="右封板", $E72="左圓角側板",$E72="右圓角側板",$E72="抽頭",$E72="入柱抽頭",$E72="假抽頭",$E72="背拉桿",$E72="木滑門",$E72="抽屜拉桿" ), "AA", "" ) | I72: =IF( OR( $E72="右側板",$E72="左側板",$E72="活隔", $E72="天地蓋頂板",$E72="天地蓋底板", $E72="左門板",$E72="右門板", $E72="左側落板",$E72="右側落板", $E72="外蓋背板",$E72="活固隔", $E72="左木框滑門",$E72="右木框滑門", $E72="左鋁框滑門",$E72="右鋁框滑門", $E72="桌板",$E72="台面",$E72="床板",$E72="假門板", $E72="上掀門板",$E72="平掀門板",$E72="下掀門板", $E72="抽盤抽頭",$E72="抽盤",$E72="層板",$E72="壁面層板", $E72="上封板",$E72="下封板",$E72="左封板",$E72="右封板", $E72="抽頭",$E72="踢腳板",$E72="補板",$E72="木滑門" ), "AA", "" ) | M72: =IFERROR(VLOOKUP(L72,色號!A:B,2,FALSE),"") | N72: =IFERROR(VLOOKUP(M72,色號!B:C,2,FALSE),"") | O72: =IFERROR(VLOOKUP(L72,色號!A:D,4,FALSE),"") | P72: =IF( OR($E72="左門板", $E72="右門板"), "鉸" & IF($F72<=1000, 2, IF($F72<=1800, 3, 4)), IF( $E72="入柱背板", "側", IF( $E72="外蓋背板", "面", IF( AND(COUNTIF($E$52:$E$81,"入柱背板")>0, OR($E72="頂板", $E72="底板")), "面", IF( AND(COUNTIF($E$52:$E$81,"外蓋背板")>0, OR($E72="左側板", $E72="右側板")), "側", IF( AND( COUNTIF($E$52:$E$81,"入柱背板")=0, COUNTIF($E$52:$E$81,"外蓋背板")=0, OR( AND(COUNTIF($E$52:$E$81,"背板")>0, OR($E72="左側板",$E72="右側板",$E72="頂板",$E72="底板",$E72="天地蓋左側板",$E72="天地蓋右側板",$E72="天地蓋頂板",$E72="天地蓋底板")), AND(COUNTIF($E$52:$E$81,"抽底")>0, OR($E72="右抽牆",$E72="左抽牆",$E72="前抽牆",$E72="後抽牆")) ) ), "背板溝", "" ) ) ) ) ) ) | Q72: =IF(OR($E72="天地蓋右側板",$E72="天地蓋左側板"), "側 面", IF(OR($E72="背拉桿",$E72="中立板",$E72="頂板",$E72="底板",$E72="前抽牆",$E72="後抽牆",$E72="內左側落板",$E72="內右側落板",$E72="抽屜拉桿",$E72="立板"), "側", IF(OR($E72="木滑門",$E72="鋁框滑門"), "輪", IF(OR($E72="右側板",$E72="左側板",$E72="右抽牆",$E72="左抽牆",$E72="天地蓋頂板",$E72="天地蓋底板",$E72="內頂板"), "面", IF($E72="固隔","固","") ) ) ) ) | R72: =IF( OR($E72="左側板",$E72="右側板",$E72="天地蓋左側板",$E72="天地蓋右側板",$E72="中立板",$E72="立板"), "排","") | T72: =IF($E72="中立板","面開槽？排孔？", IF($E72="木框滑門","前排孔要退喔！", IF(OR($E72="左門板",$E72="右門板",$E72="抽頭"),"把手？", IF(OR($E72="左側板",$E72="右側板",$E72="天地蓋右側板",$E72="天地蓋左側板"),"排孔？","")))) | U72: =IF(E72="","",$L$48)
A73: =$C$45 -> 0 | C73: =C72+1 -> 2022 | G73: =IF( OR( $E73="頂板",$E73="底板",$E73="右側板",$E73="左側板", $E73="天地蓋頂板",$E73="天地蓋底板",$E73="天地蓋右側板",$E73="天地蓋左側板", $E73="前抽牆",$E73="後抽牆",$E73="左抽牆",$E73="右抽牆", $E73="踢腳板",$E73="補板",$E73="固隔",$E73="活隔", $E73="中立板",$E73="中立板(退)",$E73="固隔(退)",$E73="活固隔",$E73="立板", $E73="內頂板",$E73="內左側落板",$E73="內右側落板",$E73="內底板", $E73="內左側板",$E73="內右側板", $E73="上前平肢",$E73="上後平肢",$E73="上前立肢",$E73="上後立肢", $E73="下前立肢",$E73="下後立肢",$E73="下前平肢",$E73="下後平肢", $E73="左側落板",$E73="右側落板", $E73="外蓋背板",$E73="台面",$E73="床板",$E73="假門板", $E73="上掀門板",$E73="平掀門板",$E73="下掀門板", $E73="左門板",$E73="右門板", $E73="抽盤",$E73="抽盤抽頭", $E73="上軌道板",$E73="下軌道板",$E73="左軌道板",$E73="右軌道板",$E73="指縫擋板",$E73="左木框滑門",$E73="右木框滑門", $E73="層板",$E73="壁面層板",$E73="桌板",$E73="上封板",$E73="下封板",$E73="左封板",$E73="右封板", $E73="左圓角側板",$E73="右圓角側板",$E73="抽頭",$E73="入柱抽頭",$E73="假抽頭",$E73="背拉桿",$E73="木滑門",$E73="抽屜拉桿" ), "AA", "" ) | I73: =IF( OR( $E73="右側板",$E73="左側板",$E73="活隔", $E73="天地蓋頂板",$E73="天地蓋底板", $E73="左門板",$E73="右門板", $E73="左側落板",$E73="右側落板", $E73="外蓋背板",$E73="活固隔", $E73="左木框滑門",$E73="右木框滑門", $E73="左鋁框滑門",$E73="右鋁框滑門", $E73="桌板",$E73="台面",$E73="床板",$E73="假門板", $E73="上掀門板",$E73="平掀門板",$E73="下掀門板", $E73="抽盤抽頭",$E73="抽盤",$E73="層板",$E73="壁面層板", $E73="上封板",$E73="下封板",$E73="左封板",$E73="右封板", $E73="抽頭",$E73="踢腳板",$E73="補板",$E73="木滑門" ), "AA", "" ) | M73: =IFERROR(VLOOKUP(L73,色號!A:B,2,FALSE),"") | N73: =IFERROR(VLOOKUP(M73,色號!B:C,2,FALSE),"") | O73: =IFERROR(VLOOKUP(L73,色號!A:D,4,FALSE),"") | P73: =IF( OR($E73="左門板", $E73="右門板"), "鉸" & IF($F73<=1000, 2, IF($F73<=1800, 3, 4)), IF( $E73="入柱背板", "側", IF( $E73="外蓋背板", "面", IF( AND(COUNTIF($E$52:$E$81,"入柱背板")>0, OR($E73="頂板", $E73="底板")), "面", IF( AND(COUNTIF($E$52:$E$81,"外蓋背板")>0, OR($E73="左側板", $E73="右側板")), "側", IF( AND( COUNTIF($E$52:$E$81,"入柱背板")=0, COUNTIF($E$52:$E$81,"外蓋背板")=0, OR( AND(COUNTIF($E$52:$E$81,"背板")>0, OR($E73="左側板",$E73="右側板",$E73="頂板",$E73="底板",$E73="天地蓋左側板",$E73="天地蓋右側板",$E73="天地蓋頂板",$E73="天地蓋底板")), AND(COUNTIF($E$52:$E$81,"抽底")>0, OR($E73="右抽牆",$E73="左抽牆",$E73="前抽牆",$E73="後抽牆")) ) ), "背板溝", "" ) ) ) ) ) ) | Q73: =IF(OR($E73="天地蓋右側板",$E73="天地蓋左側板"), "側 面", IF(OR($E73="背拉桿",$E73="中立板",$E73="頂板",$E73="底板",$E73="前抽牆",$E73="後抽牆",$E73="內左側落板",$E73="內右側落板",$E73="抽屜拉桿",$E73="立板"), "側", IF(OR($E73="木滑門",$E73="鋁框滑門"), "輪", IF(OR($E73="右側板",$E73="左側板",$E73="右抽牆",$E73="左抽牆",$E73="天地蓋頂板",$E73="天地蓋底板",$E73="內頂板"), "面", IF($E73="固隔","固","") ) ) ) ) | R73: =IF( OR($E73="左側板",$E73="右側板",$E73="天地蓋左側板",$E73="天地蓋右側板",$E73="中立板",$E73="立板"), "排","") | T73: =IF($E73="中立板","面開槽？排孔？", IF($E73="木框滑門","前排孔要退喔！", IF(OR($E73="左門板",$E73="右門板",$E73="抽頭"),"把手？", IF(OR($E73="左側板",$E73="右側板",$E73="天地蓋右側板",$E73="天地蓋左側板"),"排孔？","")))) | U73: =IF(E73="","",$L$48)
A74: =$C$45 -> 0 | C74: =C73+1 -> 2023 | G74: =IF( OR( $E74="頂板",$E74="底板",$E74="右側板",$E74="左側板", $E74="天地蓋頂板",$E74="天地蓋底板",$E74="天地蓋右側板",$E74="天地蓋左側板", $E74="前抽牆",$E74="後抽牆",$E74="左抽牆",$E74="右抽牆", $E74="踢腳板",$E74="補板",$E74="固隔",$E74="活隔", $E74="中立板",$E74="中立板(退)",$E74="固隔(退)",$E74="活固隔",$E74="立板", $E74="內頂板",$E74="內左側落板",$E74="內右側落板",$E74="內底板", $E74="內左側板",$E74="內右側板", $E74="上前平肢",$E74="上後平肢",$E74="上前立肢",$E74="上後立肢", $E74="下前立肢",$E74="下後立肢",$E74="下前平肢",$E74="下後平肢", $E74="左側落板",$E74="右側落板", $E74="外蓋背板",$E74="台面",$E74="床板",$E74="假門板", $E74="上掀門板",$E74="平掀門板",$E74="下掀門板", $E74="左門板",$E74="右門板", $E74="抽盤",$E74="抽盤抽頭", $E74="上軌道板",$E74="下軌道板",$E74="左軌道板",$E74="右軌道板",$E74="指縫擋板",$E74="左木框滑門",$E74="右木框滑門", $E74="層板",$E74="壁面層板",$E74="桌板",$E74="上封板",$E74="下封板",$E74="左封板",$E74="右封板", $E74="左圓角側板",$E74="右圓角側板",$E74="抽頭",$E74="入柱抽頭",$E74="假抽頭",$E74="背拉桿",$E74="木滑門",$E74="抽屜拉桿" ), "AA", "" ) | I74: =IF( OR( $E74="右側板",$E74="左側板",$E74="活隔", $E74="天地蓋頂板",$E74="天地蓋底板", $E74="左門板",$E74="右門板", $E74="左側落板",$E74="右側落板", $E74="外蓋背板",$E74="活固隔", $E74="左木框滑門",$E74="右木框滑門", $E74="左鋁框滑門",$E74="右鋁框滑門", $E74="桌板",$E74="台面",$E74="床板",$E74="假門板", $E74="上掀門板",$E74="平掀門板",$E74="下掀門板", $E74="抽盤抽頭",$E74="抽盤",$E74="層板",$E74="壁面層板", $E74="上封板",$E74="下封板",$E74="左封板",$E74="右封板", $E74="抽頭",$E74="踢腳板",$E74="補板",$E74="木滑門" ), "AA", "" ) | M74: =IFERROR(VLOOKUP(L74,色號!A:B,2,FALSE),"") | N74: =IFERROR(VLOOKUP(M74,色號!B:C,2,FALSE),"") | O74: =IFERROR(VLOOKUP(L74,色號!A:D,4,FALSE),"") | P74: =IF( OR($E74="左門板", $E74="右門板"), "鉸" & IF($F74<=1000, 2, IF($F74<=1800, 3, 4)), IF( $E74="入柱背板", "側", IF( $E74="外蓋背板", "面", IF( AND(COUNTIF($E$52:$E$81,"入柱背板")>0, OR($E74="頂板", $E74="底板")), "面", IF( AND(COUNTIF($E$52:$E$81,"外蓋背板")>0, OR($E74="左側板", $E74="右側板")), "側", IF( AND( COUNTIF($E$52:$E$81,"入柱背板")=0, COUNTIF($E$52:$E$81,"外蓋背板")=0, OR( AND(COUNTIF($E$52:$E$81,"背板")>0, OR($E74="左側板",$E74="右側板",$E74="頂板",$E74="底板",$E74="天地蓋左側板",$E74="天地蓋右側板",$E74="天地蓋頂板",$E74="天地蓋底板")), AND(COUNTIF($E$52:$E$81,"抽底")>0, OR($E74="右抽牆",$E74="左抽牆",$E74="前抽牆",$E74="後抽牆")) ) ), "背板溝", "" ) ) ) ) ) ) | Q74: =IF(OR($E74="天地蓋右側板",$E74="天地蓋左側板"), "側 面", IF(OR($E74="背拉桿",$E74="中立板",$E74="頂板",$E74="底板",$E74="前抽牆",$E74="後抽牆",$E74="內左側落板",$E74="內右側落板",$E74="抽屜拉桿",$E74="立板"), "側", IF(OR($E74="木滑門",$E74="鋁框滑門"), "輪", IF(OR($E74="右側板",$E74="左側板",$E74="右抽牆",$E74="左抽牆",$E74="天地蓋頂板",$E74="天地蓋底板",$E74="內頂板"), "面", IF($E74="固隔","固","") ) ) ) ) | R74: =IF( OR($E74="左側板",$E74="右側板",$E74="天地蓋左側板",$E74="天地蓋右側板",$E74="中立板",$E74="立板"), "排","") | T74: =IF($E74="中立板","面開槽？排孔？", IF($E74="木框滑門","前排孔要退喔！", IF(OR($E74="左門板",$E74="右門板",$E74="抽頭"),"把手？", IF(OR($E74="左側板",$E74="右側板",$E74="天地蓋右側板",$E74="天地蓋左側板"),"排孔？","")))) | U74: =IF(E74="","",$L$48)
A75: =$C$45 -> 0 | C75: =C74+1 -> 2024 | G75: =IF( OR( $E75="頂板",$E75="底板",$E75="右側板",$E75="左側板", $E75="天地蓋頂板",$E75="天地蓋底板",$E75="天地蓋右側板",$E75="天地蓋左側板", $E75="前抽牆",$E75="後抽牆",$E75="左抽牆",$E75="右抽牆", $E75="踢腳板",$E75="補板",$E75="固隔",$E75="活隔", $E75="中立板",$E75="中立板(退)",$E75="固隔(退)",$E75="活固隔",$E75="立板", $E75="內頂板",$E75="內左側落板",$E75="內右側落板",$E75="內底板", $E75="內左側板",$E75="內右側板", $E75="上前平肢",$E75="上後平肢",$E75="上前立肢",$E75="上後立肢", $E75="下前立肢",$E75="下後立肢",$E75="下前平肢",$E75="下後平肢", $E75="左側落板",$E75="右側落板", $E75="外蓋背板",$E75="台面",$E75="床板",$E75="假門板", $E75="上掀門板",$E75="平掀門板",$E75="下掀門板", $E75="左門板",$E75="右門板", $E75="抽盤",$E75="抽盤抽頭", $E75="上軌道板",$E75="下軌道板",$E75="左軌道板",$E75="右軌道板",$E75="指縫擋板",$E75="左木框滑門",$E75="右木框滑門", $E75="層板",$E75="壁面層板",$E75="桌板",$E75="上封板",$E75="下封板",$E75="左封板",$E75="右封板", $E75="左圓角側板",$E75="右圓角側板",$E75="抽頭",$E75="入柱抽頭",$E75="假抽頭",$E75="背拉桿",$E75="木滑門",$E75="抽屜拉桿" ), "AA", "" ) | I75: =IF( OR( $E75="右側板",$E75="左側板",$E75="活隔", $E75="天地蓋頂板",$E75="天地蓋底板", $E75="左門板",$E75="右門板", $E75="左側落板",$E75="右側落板", $E75="外蓋背板",$E75="活固隔", $E75="左木框滑門",$E75="右木框滑門", $E75="左鋁框滑門",$E75="右鋁框滑門", $E75="桌板",$E75="台面",$E75="床板",$E75="假門板", $E75="上掀門板",$E75="平掀門板",$E75="下掀門板", $E75="抽盤抽頭",$E75="抽盤",$E75="層板",$E75="壁面層板", $E75="上封板",$E75="下封板",$E75="左封板",$E75="右封板", $E75="抽頭",$E75="踢腳板",$E75="補板",$E75="木滑門" ), "AA", "" ) | M75: =IFERROR(VLOOKUP(L75,色號!A:B,2,FALSE),"") | N75: =IFERROR(VLOOKUP(M75,色號!B:C,2,FALSE),"") | O75: =IFERROR(VLOOKUP(L75,色號!A:D,4,FALSE),"") | P75: =IF( OR($E75="左門板", $E75="右門板"), "鉸" & IF($F75<=1000, 2, IF($F75<=1800, 3, 4)), IF( $E75="入柱背板", "側", IF( $E75="外蓋背板", "面", IF( AND(COUNTIF($E$52:$E$81,"入柱背板")>0, OR($E75="頂板", $E75="底板")), "面", IF( AND(COUNTIF($E$52:$E$81,"外蓋背板")>0, OR($E75="左側板", $E75="右側板")), "側", IF( AND( COUNTIF($E$52:$E$81,"入柱背板")=0, COUNTIF($E$52:$E$81,"外蓋背板")=0, OR( AND(COUNTIF($E$52:$E$81,"背板")>0, OR($E75="左側板",$E75="右側板",$E75="頂板",$E75="底板",$E75="天地蓋左側板",$E75="天地蓋右側板",$E75="天地蓋頂板",$E75="天地蓋底板")), AND(COUNTIF($E$52:$E$81,"抽底")>0, OR($E75="右抽牆",$E75="左抽牆",$E75="前抽牆",$E75="後抽牆")) ) ), "背板溝", "" ) ) ) ) ) ) | Q75: =IF(OR($E75="天地蓋右側板",$E75="天地蓋左側板"), "側 面", IF(OR($E75="背拉桿",$E75="中立板",$E75="頂板",$E75="底板",$E75="前抽牆",$E75="後抽牆",$E75="內左側落板",$E75="內右側落板",$E75="抽屜拉桿",$E75="立板"), "側", IF(OR($E75="木滑門",$E75="鋁框滑門"), "輪", IF(OR($E75="右側板",$E75="左側板",$E75="右抽牆",$E75="左抽牆",$E75="天地蓋頂板",$E75="天地蓋底板",$E75="內頂板"), "面", IF($E75="固隔","固","") ) ) ) ) | R75: =IF( OR($E75="左側板",$E75="右側板",$E75="天地蓋左側板",$E75="天地蓋右側板",$E75="中立板",$E75="立板"), "排","") | T75: =IF($E75="中立板","面開槽？排孔？", IF($E75="木框滑門","前排孔要退喔！", IF(OR($E75="左門板",$E75="右門板",$E75="抽頭"),"把手？", IF(OR($E75="左側板",$E75="右側板",$E75="天地蓋右側板",$E75="天地蓋左側板"),"排孔？","")))) | U75: =IF(E75="","",$L$48)
A76: =$C$45 -> 0 | C76: =C75+1 -> 2025 | G76: =IF( OR( $E76="頂板",$E76="底板",$E76="右側板",$E76="左側板", $E76="天地蓋頂板",$E76="天地蓋底板",$E76="天地蓋右側板",$E76="天地蓋左側板", $E76="前抽牆",$E76="後抽牆",$E76="左抽牆",$E76="右抽牆", $E76="踢腳板",$E76="補板",$E76="固隔",$E76="活隔", $E76="中立板",$E76="中立板(退)",$E76="固隔(退)",$E76="活固隔",$E76="立板", $E76="內頂板",$E76="內左側落板",$E76="內右側落板",$E76="內底板", $E76="內左側板",$E76="內右側板", $E76="上前平肢",$E76="上後平肢",$E76="上前立肢",$E76="上後立肢", $E76="下前立肢",$E76="下後立肢",$E76="下前平肢",$E76="下後平肢", $E76="左側落板",$E76="右側落板", $E76="外蓋背板",$E76="台面",$E76="床板",$E76="假門板", $E76="上掀門板",$E76="平掀門板",$E76="下掀門板", $E76="左門板",$E76="右門板", $E76="抽盤",$E76="抽盤抽頭", $E76="上軌道板",$E76="下軌道板",$E76="左軌道板",$E76="右軌道板",$E76="指縫擋板",$E76="左木框滑門",$E76="右木框滑門", $E76="層板",$E76="壁面層板",$E76="桌板",$E76="上封板",$E76="下封板",$E76="左封板",$E76="右封板", $E76="左圓角側板",$E76="右圓角側板",$E76="抽頭",$E76="入柱抽頭",$E76="假抽頭",$E76="背拉桿",$E76="木滑門",$E76="抽屜拉桿" ), "AA", "" ) | I76: =IF( OR( $E76="右側板",$E76="左側板",$E76="活隔", $E76="天地蓋頂板",$E76="天地蓋底板", $E76="左門板",$E76="右門板", $E76="左側落板",$E76="右側落板", $E76="外蓋背板",$E76="活固隔", $E76="左木框滑門",$E76="右木框滑門", $E76="左鋁框滑門",$E76="右鋁框滑門", $E76="桌板",$E76="台面",$E76="床板",$E76="假門板", $E76="上掀門板",$E76="平掀門板",$E76="下掀門板", $E76="抽盤抽頭",$E76="抽盤",$E76="層板",$E76="壁面層板", $E76="上封板",$E76="下封板",$E76="左封板",$E76="右封板", $E76="抽頭",$E76="踢腳板",$E76="補板",$E76="木滑門" ), "AA", "" ) | M76: =IFERROR(VLOOKUP(L76,色號!A:B,2,FALSE),"") | N76: =IFERROR(VLOOKUP(M76,色號!B:C,2,FALSE),"") | O76: =IFERROR(VLOOKUP(L76,色號!A:D,4,FALSE),"") | P76: =IF( OR($E76="左門板", $E76="右門板"), "鉸" & IF($F76<=1000, 2, IF($F76<=1800, 3, 4)), IF( $E76="入柱背板", "側", IF( $E76="外蓋背板", "面", IF( AND(COUNTIF($E$52:$E$81,"入柱背板")>0, OR($E76="頂板", $E76="底板")), "面", IF( AND(COUNTIF($E$52:$E$81,"外蓋背板")>0, OR($E76="左側板", $E76="右側板")), "側", IF( AND( COUNTIF($E$52:$E$81,"入柱背板")=0, COUNTIF($E$52:$E$81,"外蓋背板")=0, OR( AND(COUNTIF($E$52:$E$81,"背板")>0, OR($E76="左側板",$E76="右側板",$E76="頂板",$E76="底板",$E76="天地蓋左側板",$E76="天地蓋右側板",$E76="天地蓋頂板",$E76="天地蓋底板")), AND(COUNTIF($E$52:$E$81,"抽底")>0, OR($E76="右抽牆",$E76="左抽牆",$E76="前抽牆",$E76="後抽牆")) ) ), "背板溝", "" ) ) ) ) ) ) | Q76: =IF(OR($E76="天地蓋右側板",$E76="天地蓋左側板"), "側 面", IF(OR($E76="背拉桿",$E76="中立板",$E76="頂板",$E76="底板",$E76="前抽牆",$E76="後抽牆",$E76="內左側落板",$E76="內右側落板",$E76="抽屜拉桿",$E76="立板"), "側", IF(OR($E76="木滑門",$E76="鋁框滑門"), "輪", IF(OR($E76="右側板",$E76="左側板",$E76="右抽牆",$E76="左抽牆",$E76="天地蓋頂板",$E76="天地蓋底板",$E76="內頂板"), "面", IF($E76="固隔","固","") ) ) ) ) | R76: =IF( OR($E76="左側板",$E76="右側板",$E76="天地蓋左側板",$E76="天地蓋右側板",$E76="中立板",$E76="立板"), "排","") | T76: =IF($E76="中立板","面開槽？排孔？", IF($E76="木框滑門","前排孔要退喔！", IF(OR($E76="左門板",$E76="右門板",$E76="抽頭"),"把手？", IF(OR($E76="左側板",$E76="右側板",$E76="天地蓋右側板",$E76="天地蓋左側板"),"排孔？","")))) | U76: =IF(E76="","",$L$48)
A77: =$C$45 -> 0 | C77: =C76+1 -> 2026 | G77: =IF( OR( $E77="頂板",$E77="底板",$E77="右側板",$E77="左側板", $E77="天地蓋頂板",$E77="天地蓋底板",$E77="天地蓋右側板",$E77="天地蓋左側板", $E77="前抽牆",$E77="後抽牆",$E77="左抽牆",$E77="右抽牆", $E77="踢腳板",$E77="補板",$E77="固隔",$E77="活隔", $E77="中立板",$E77="中立板(退)",$E77="固隔(退)",$E77="活固隔",$E77="立板", $E77="內頂板",$E77="內左側落板",$E77="內右側落板",$E77="內底板", $E77="內左側板",$E77="內右側板", $E77="上前平肢",$E77="上後平肢",$E77="上前立肢",$E77="上後立肢", $E77="下前立肢",$E77="下後立肢",$E77="下前平肢",$E77="下後平肢", $E77="左側落板",$E77="右側落板", $E77="外蓋背板",$E77="台面",$E77="床板",$E77="假門板", $E77="上掀門板",$E77="平掀門板",$E77="下掀門板", $E77="左門板",$E77="右門板", $E77="抽盤",$E77="抽盤抽頭", $E77="上軌道板",$E77="下軌道板",$E77="左軌道板",$E77="右軌道板",$E77="指縫擋板",$E77="左木框滑門",$E77="右木框滑門", $E77="層板",$E77="壁面層板",$E77="桌板",$E77="上封板",$E77="下封板",$E77="左封板",$E77="右封板", $E77="左圓角側板",$E77="右圓角側板",$E77="抽頭",$E77="入柱抽頭",$E77="假抽頭",$E77="背拉桿",$E77="木滑門",$E77="抽屜拉桿" ), "AA", "" ) | I77: =IF( OR( $E77="右側板",$E77="左側板",$E77="活隔", $E77="天地蓋頂板",$E77="天地蓋底板", $E77="左門板",$E77="右門板", $E77="左側落板",$E77="右側落板", $E77="外蓋背板",$E77="活固隔", $E77="左木框滑門",$E77="右木框滑門", $E77="左鋁框滑門",$E77="右鋁框滑門", $E77="桌板",$E77="台面",$E77="床板",$E77="假門板", $E77="上掀門板",$E77="平掀門板",$E77="下掀門板", $E77="抽盤抽頭",$E77="抽盤",$E77="層板",$E77="壁面層板", $E77="上封板",$E77="下封板",$E77="左封板",$E77="右封板", $E77="抽頭",$E77="踢腳板",$E77="補板",$E77="木滑門" ), "AA", "" ) | M77: =IFERROR(VLOOKUP(L77,色號!A:B,2,FALSE),"") | N77: =IFERROR(VLOOKUP(M77,色號!B:C,2,FALSE),"") | O77: =IFERROR(VLOOKUP(L77,色號!A:D,4,FALSE),"") | P77: =IF( OR($E77="左門板", $E77="右門板"), "鉸" & IF($F77<=1000, 2, IF($F77<=1800, 3, 4)), IF( $E77="入柱背板", "側", IF( $E77="外蓋背板", "面", IF( AND(COUNTIF($E$52:$E$81,"入柱背板")>0, OR($E77="頂板", $E77="底板")), "面", IF( AND(COUNTIF($E$52:$E$81,"外蓋背板")>0, OR($E77="左側板", $E77="右側板")), "側", IF( AND( COUNTIF($E$52:$E$81,"入柱背板")=0, COUNTIF($E$52:$E$81,"外蓋背板")=0, OR( AND(COUNTIF($E$52:$E$81,"背板")>0, OR($E77="左側板",$E77="右側板",$E77="頂板",$E77="底板",$E77="天地蓋左側板",$E77="天地蓋右側板",$E77="天地蓋頂板",$E77="天地蓋底板")), AND(COUNTIF($E$52:$E$81,"抽底")>0, OR($E77="右抽牆",$E77="左抽牆",$E77="前抽牆",$E77="後抽牆")) ) ), "背板溝", "" ) ) ) ) ) ) | Q77: =IF(OR($E77="天地蓋右側板",$E77="天地蓋左側板"), "側 面", IF(OR($E77="背拉桿",$E77="中立板",$E77="頂板",$E77="底板",$E77="前抽牆",$E77="後抽牆",$E77="內左側落板",$E77="內右側落板",$E77="抽屜拉桿",$E77="立板"), "側", IF(OR($E77="木滑門",$E77="鋁框滑門"), "輪", IF(OR($E77="右側板",$E77="左側板",$E77="右抽牆",$E77="左抽牆",$E77="天地蓋頂板",$E77="天地蓋底板",$E77="內頂板"), "面", IF($E77="固隔","固","") ) ) ) ) | R77: =IF( OR($E77="左側板",$E77="右側板",$E77="天地蓋左側板",$E77="天地蓋右側板",$E77="中立板",$E77="立板"), "排","") | T77: =IF($E77="中立板","面開槽？排孔？", IF($E77="木框滑門","前排孔要退喔！", IF(OR($E77="左門板",$E77="右門板",$E77="抽頭"),"把手？", IF(OR($E77="左側板",$E77="右側板",$E77="天地蓋右側板",$E77="天地蓋左側板"),"排孔？","")))) | U77: =IF(E77="","",$L$48)
A78: =$C$45 -> 0 | C78: =C77+1 -> 2027 | G78: =IF( OR( $E78="頂板",$E78="底板",$E78="右側板",$E78="左側板", $E78="天地蓋頂板",$E78="天地蓋底板",$E78="天地蓋右側板",$E78="天地蓋左側板", $E78="前抽牆",$E78="後抽牆",$E78="左抽牆",$E78="右抽牆", $E78="踢腳板",$E78="補板",$E78="固隔",$E78="活隔", $E78="中立板",$E78="中立板(退)",$E78="固隔(退)",$E78="活固隔",$E78="立板", $E78="內頂板",$E78="內左側落板",$E78="內右側落板",$E78="內底板", $E78="內左側板",$E78="內右側板", $E78="上前平肢",$E78="上後平肢",$E78="上前立肢",$E78="上後立肢", $E78="下前立肢",$E78="下後立肢",$E78="下前平肢",$E78="下後平肢", $E78="左側落板",$E78="右側落板", $E78="外蓋背板",$E78="台面",$E78="床板",$E78="假門板", $E78="上掀門板",$E78="平掀門板",$E78="下掀門板", $E78="左門板",$E78="右門板", $E78="抽盤",$E78="抽盤抽頭", $E78="上軌道板",$E78="下軌道板",$E78="左軌道板",$E78="右軌道板",$E78="指縫擋板",$E78="左木框滑門",$E78="右木框滑門", $E78="層板",$E78="壁面層板",$E78="桌板",$E78="上封板",$E78="下封板",$E78="左封板",$E78="右封板", $E78="左圓角側板",$E78="右圓角側板",$E78="抽頭",$E78="入柱抽頭",$E78="假抽頭",$E78="背拉桿",$E78="木滑門",$E78="抽屜拉桿" ), "AA", "" ) | I78: =IF( OR( $E78="右側板",$E78="左側板",$E78="活隔", $E78="天地蓋頂板",$E78="天地蓋底板", $E78="左門板",$E78="右門板", $E78="左側落板",$E78="右側落板", $E78="外蓋背板",$E78="活固隔", $E78="左木框滑門",$E78="右木框滑門", $E78="左鋁框滑門",$E78="右鋁框滑門", $E78="桌板",$E78="台面",$E78="床板",$E78="假門板", $E78="上掀門板",$E78="平掀門板",$E78="下掀門板", $E78="抽盤抽頭",$E78="抽盤",$E78="層板",$E78="壁面層板", $E78="上封板",$E78="下封板",$E78="左封板",$E78="右封板", $E78="抽頭",$E78="踢腳板",$E78="補板",$E78="木滑門" ), "AA", "" ) | M78: =IFERROR(VLOOKUP(L78,色號!A:B,2,FALSE),"") | O78: =IFERROR(VLOOKUP(L78,色號!A:D,4,FALSE),"") | P78: =IF( OR($E78="左門板", $E78="右門板"), "鉸" & IF($F78<=1000, 2, IF($F78<=1800, 3, 4)), IF( $E78="入柱背板", "側", IF( $E78="外蓋背板", "面", IF( AND(COUNTIF($E$52:$E$81,"入柱背板")>0, OR($E78="頂板", $E78="底板")), "面", IF( AND(COUNTIF($E$52:$E$81,"外蓋背板")>0, OR($E78="左側板", $E78="右側板")), "側", IF( AND( COUNTIF($E$52:$E$81,"入柱背板")=0, COUNTIF($E$52:$E$81,"外蓋背板")=0, OR( AND(COUNTIF($E$52:$E$81,"背板")>0, OR($E78="左側板",$E78="右側板",$E78="頂板",$E78="底板",$E78="天地蓋左側板",$E78="天地蓋右側板",$E78="天地蓋頂板",$E78="天地蓋底板")), AND(COUNTIF($E$52:$E$81,"抽底")>0, OR($E78="右抽牆",$E78="左抽牆",$E78="前抽牆",$E78="後抽牆")) ) ), "背板溝", "" ) ) ) ) ) ) | Q78: =IF(OR($E78="天地蓋右側板",$E78="天地蓋左側板"), "側 面", IF(OR($E78="背拉桿",$E78="中立板",$E78="頂板",$E78="底板",$E78="前抽牆",$E78="後抽牆",$E78="內左側落板",$E78="內右側落板",$E78="抽屜拉桿",$E78="立板"), "側", IF(OR($E78="木滑門",$E78="鋁框滑門"), "輪", IF(OR($E78="右側板",$E78="左側板",$E78="右抽牆",$E78="左抽牆",$E78="天地蓋頂板",$E78="天地蓋底板",$E78="內頂板"), "面", IF($E78="固隔","固","") ) ) ) ) | R78: =IF( OR($E78="左側板",$E78="右側板",$E78="天地蓋左側板",$E78="天地蓋右側板",$E78="中立板",$E78="立板"), "排","") | T78: =IF($E78="中立板","面開槽？排孔？", IF($E78="木框滑門","前排孔要退喔！", IF(OR($E78="左門板",$E78="右門板",$E78="抽頭"),"把手？", IF(OR($E78="左側板",$E78="右側板",$E78="天地蓋右側板",$E78="天地蓋左側板"),"排孔？","")))) | U78: =IF(E78="","",$L$48)
A79: =$C$45 -> 0 | C79: =C78+1 -> 2028 | G79: =IF( OR( $E79="頂板",$E79="底板",$E79="右側板",$E79="左側板", $E79="天地蓋頂板",$E79="天地蓋底板",$E79="天地蓋右側板",$E79="天地蓋左側板", $E79="前抽牆",$E79="後抽牆",$E79="左抽牆",$E79="右抽牆", $E79="踢腳板",$E79="補板",$E79="固隔",$E79="活隔", $E79="中立板",$E79="中立板(退)",$E79="固隔(退)",$E79="活固隔",$E79="立板", $E79="內頂板",$E79="內左側落板",$E79="內右側落板",$E79="內底板", $E79="內左側板",$E79="內右側板", $E79="上前平肢",$E79="上後平肢",$E79="上前立肢",$E79="上後立肢", $E79="下前立肢",$E79="下後立肢",$E79="下前平肢",$E79="下後平肢", $E79="左側落板",$E79="右側落板", $E79="外蓋背板",$E79="台面",$E79="床板",$E79="假門板", $E79="上掀門板",$E79="平掀門板",$E79="下掀門板", $E79="左門板",$E79="右門板", $E79="抽盤",$E79="抽盤抽頭", $E79="上軌道板",$E79="下軌道板",$E79="左軌道板",$E79="右軌道板",$E79="指縫擋板",$E79="左木框滑門",$E79="右木框滑門", $E79="層板",$E79="壁面層板",$E79="桌板",$E79="上封板",$E79="下封板",$E79="左封板",$E79="右封板", $E79="左圓角側板",$E79="右圓角側板",$E79="抽頭",$E79="入柱抽頭",$E79="假抽頭",$E79="背拉桿",$E79="木滑門",$E79="抽屜拉桿" ), "AA", "" ) | I79: =IF( OR( $E79="右側板",$E79="左側板",$E79="活隔", $E79="天地蓋頂板",$E79="天地蓋底板", $E79="左門板",$E79="右門板", $E79="左側落板",$E79="右側落板", $E79="外蓋背板",$E79="活固隔", $E79="左木框滑門",$E79="右木框滑門", $E79="左鋁框滑門",$E79="右鋁框滑門", $E79="桌板",$E79="台面",$E79="床板",$E79="假門板", $E79="上掀門板",$E79="平掀門板",$E79="下掀門板", $E79="抽盤抽頭",$E79="抽盤",$E79="層板",$E79="壁面層板", $E79="上封板",$E79="下封板",$E79="左封板",$E79="右封板", $E79="抽頭",$E79="踢腳板",$E79="補板",$E79="木滑門" ), "AA", "" ) | M79: =IFERROR(VLOOKUP(L79,色號!A:B,2,FALSE),"") | N79: =IFERROR(VLOOKUP(M79,色號!B:C,2,FALSE),"") | O79: =IFERROR(VLOOKUP(L79,色號!A:D,4,FALSE),"") | P79: =IF( OR($E79="左門板", $E79="右門板"), "鉸" & IF($F79<=1000, 2, IF($F79<=1800, 3, 4)), IF( $E79="入柱背板", "側", IF( $E79="外蓋背板", "面", IF( AND(COUNTIF($E$52:$E$81,"入柱背板")>0, OR($E79="頂板", $E79="底板")), "面", IF( AND(COUNTIF($E$52:$E$81,"外蓋背板")>0, OR($E79="左側板", $E79="右側板")), "側", IF( AND( COUNTIF($E$52:$E$81,"入柱背板")=0, COUNTIF($E$52:$E$81,"外蓋背板")=0, OR( AND(COUNTIF($E$52:$E$81,"背板")>0, OR($E79="左側板",$E79="右側板",$E79="頂板",$E79="底板",$E79="天地蓋左側板",$E79="天地蓋右側板",$E79="天地蓋頂板",$E79="天地蓋底板")), AND(COUNTIF($E$52:$E$81,"抽底")>0, OR($E79="右抽牆",$E79="左抽牆",$E79="前抽牆",$E79="後抽牆")) ) ), "背板溝", "" ) ) ) ) ) ) | Q79: =IF(OR($E79="天地蓋右側板",$E79="天地蓋左側板"), "側 面", IF(OR($E79="背拉桿",$E79="中立板",$E79="頂板",$E79="底板",$E79="前抽牆",$E79="後抽牆",$E79="內左側落板",$E79="內右側落板",$E79="抽屜拉桿",$E79="立板"), "側", IF(OR($E79="木滑門",$E79="鋁框滑門"), "輪", IF(OR($E79="右側板",$E79="左側板",$E79="右抽牆",$E79="左抽牆",$E79="天地蓋頂板",$E79="天地蓋底板",$E79="內頂板"), "面", IF($E79="固隔","固","") ) ) ) ) | R79: =IF( OR($E79="左側板",$E79="右側板",$E79="天地蓋左側板",$E79="天地蓋右側板",$E79="中立板",$E79="立板"), "排","") | T79: =IF($E79="中立板","面開槽？排孔？", IF($E79="木框滑門","前排孔要退喔！", IF(OR($E79="左門板",$E79="右門板",$E79="抽頭"),"把手？", IF(OR($E79="左側板",$E79="右側板",$E79="天地蓋右側板",$E79="天地蓋左側板"),"排孔？","")))) | U79: =IF(E79="","",$L$48)
A80: =$C$45 -> 0 | C80: =C79+1 -> 2029 | G80: =IF( OR( $E80="頂板",$E80="底板",$E80="右側板",$E80="左側板", $E80="天地蓋頂板",$E80="天地蓋底板",$E80="天地蓋右側板",$E80="天地蓋左側板", $E80="前抽牆",$E80="後抽牆",$E80="左抽牆",$E80="右抽牆", $E80="踢腳板",$E80="補板",$E80="固隔",$E80="活隔", $E80="中立板",$E80="中立板(退)",$E80="固隔(退)",$E80="活固隔",$E80="立板", $E80="內頂板",$E80="內左側落板",$E80="內右側落板",$E80="內底板", $E80="內左側板",$E80="內右側板", $E80="上前平肢",$E80="上後平肢",$E80="上前立肢",$E80="上後立肢", $E80="下前立肢",$E80="下後立肢",$E80="下前平肢",$E80="下後平肢", $E80="左側落板",$E80="右側落板", $E80="外蓋背板",$E80="台面",$E80="床板",$E80="假門板", $E80="上掀門板",$E80="平掀門板",$E80="下掀門板", $E80="左門板",$E80="右門板", $E80="抽盤",$E80="抽盤抽頭", $E80="上軌道板",$E80="下軌道板",$E80="左軌道板",$E80="右軌道板",$E80="指縫擋板",$E80="左木框滑門",$E80="右木框滑門", $E80="層板",$E80="壁面層板",$E80="桌板",$E80="上封板",$E80="下封板",$E80="左封板",$E80="右封板", $E80="左圓角側板",$E80="右圓角側板",$E80="抽頭",$E80="入柱抽頭",$E80="假抽頭",$E80="背拉桿",$E80="木滑門",$E80="抽屜拉桿" ), "AA", "" ) | I80: =IF( OR( $E80="右側板",$E80="左側板",$E80="活隔", $E80="天地蓋頂板",$E80="天地蓋底板", $E80="左門板",$E80="右門板", $E80="左側落板",$E80="右側落板", $E80="外蓋背板",$E80="活固隔", $E80="左木框滑門",$E80="右木框滑門", $E80="左鋁框滑門",$E80="右鋁框滑門", $E80="桌板",$E80="台面",$E80="床板",$E80="假門板", $E80="上掀門板",$E80="平掀門板",$E80="下掀門板", $E80="抽盤抽頭",$E80="抽盤",$E80="層板",$E80="壁面層板", $E80="上封板",$E80="下封板",$E80="左封板",$E80="右封板", $E80="抽頭",$E80="踢腳板",$E80="補板",$E80="木滑門" ), "AA", "" ) | M80: =IFERROR(VLOOKUP(L80,色號!A:B,2,FALSE),"") | N80: =IFERROR(VLOOKUP(M80,色號!B:C,2,FALSE),"") | O80: =IFERROR(VLOOKUP(L80,色號!A:D,4,FALSE),"") | P80: =IF( OR($E80="左門板", $E80="右門板"), "鉸" & IF($F80<=1000, 2, IF($F80<=1800, 3, 4)), IF( $E80="入柱背板", "側", IF( $E80="外蓋背板", "面", IF( AND(COUNTIF($E$52:$E$81,"入柱背板")>0, OR($E80="頂板", $E80="底板")), "面", IF( AND(COUNTIF($E$52:$E$81,"外蓋背板")>0, OR($E80="左側板", $E80="右側板")), "側", IF( AND( COUNTIF($E$52:$E$81,"入柱背板")=0, COUNTIF($E$52:$E$81,"外蓋背板")=0, OR( AND(COUNTIF($E$52:$E$81,"背板")>0, OR($E80="左側板",$E80="右側板",$E80="頂板",$E80="底板",$E80="天地蓋左側板",$E80="天地蓋右側板",$E80="天地蓋頂板",$E80="天地蓋底板")), AND(COUNTIF($E$52:$E$81,"抽底")>0, OR($E80="右抽牆",$E80="左抽牆",$E80="前抽牆",$E80="後抽牆")) ) ), "背板溝", "" ) ) ) ) ) ) | Q80: =IF(OR($E80="天地蓋右側板",$E80="天地蓋左側板"), "側 面", IF(OR($E80="背拉桿",$E80="中立板",$E80="頂板",$E80="底板",$E80="前抽牆",$E80="後抽牆",$E80="內左側落板",$E80="內右側落板",$E80="抽屜拉桿",$E80="立板"), "側", IF(OR($E80="木滑門",$E80="鋁框滑門"), "輪", IF(OR($E80="右側板",$E80="左側板",$E80="右抽牆",$E80="左抽牆",$E80="天地蓋頂板",$E80="天地蓋底板",$E80="內頂板"), "面", IF($E80="固隔","固","") ) ) ) ) | R80: =IF( OR($E80="左側板",$E80="右側板",$E80="天地蓋左側板",$E80="天地蓋右側板",$E80="中立板",$E80="立板"), "排","") | T80: =IF($E80="中立板","面開槽？排孔？", IF($E80="木框滑門","前排孔要退喔！", IF(OR($E80="左門板",$E80="右門板",$E80="抽頭"),"把手？", IF(OR($E80="左側板",$E80="右側板",$E80="天地蓋右側板",$E80="天地蓋左側板"),"排孔？","")))) | U80: =IF(E80="","",$L$48)
A81: =$C$45 -> 0 | C81: =C80+1 -> 2030 | G81: =IF( OR( $E81="頂板",$E81="底板",$E81="右側板",$E81="左側板", $E81="天地蓋頂板",$E81="天地蓋底板",$E81="天地蓋右側板",$E81="天地蓋左側板", $E81="前抽牆",$E81="後抽牆",$E81="左抽牆",$E81="右抽牆", $E81="踢腳板",$E81="補板",$E81="固隔",$E81="活隔", $E81="中立板",$E81="中立板(退)",$E81="固隔(退)",$E81="活固隔",$E81="立板", $E81="內頂板",$E81="內左側落板",$E81="內右側落板",$E81="內底板", $E81="內左側板",$E81="內右側板", $E81="上前平肢",$E81="上後平肢",$E81="上前立肢",$E81="上後立肢", $E81="下前立肢",$E81="下後立肢",$E81="下前平肢",$E81="下後平肢", $E81="左側落板",$E81="右側落板", $E81="外蓋背板",$E81="台面",$E81="床板",$E81="假門板", $E81="上掀門板",$E81="平掀門板",$E81="下掀門板", $E81="左門板",$E81="右門板", $E81="抽盤",$E81="抽盤抽頭", $E81="上軌道板",$E81="下軌道板",$E81="左軌道板",$E81="右軌道板",$E81="指縫擋板",$E81="左木框滑門",$E81="右木框滑門", $E81="層板",$E81="壁面層板",$E81="桌板",$E81="上封板",$E81="下封板",$E81="左封板",$E81="右封板", $E81="左圓角側板",$E81="右圓角側板",$E81="抽頭",$E81="入柱抽頭",$E81="假抽頭",$E81="背拉桿",$E81="木滑門",$E81="抽屜拉桿" ), "AA", "" ) | I81: =IF( OR( $E81="右側板",$E81="左側板",$E81="活隔", $E81="天地蓋頂板",$E81="天地蓋底板", $E81="左門板",$E81="右門板", $E81="左側落板",$E81="右側落板", $E81="外蓋背板",$E81="活固隔", $E81="左木框滑門",$E81="右木框滑門", $E81="左鋁框滑門",$E81="右鋁框滑門", $E81="桌板",$E81="台面",$E81="床板",$E81="假門板", $E81="上掀門板",$E81="平掀門板",$E81="下掀門板", $E81="抽盤抽頭",$E81="抽盤",$E81="層板",$E81="壁面層板", $E81="上封板",$E81="下封板",$E81="左封板",$E81="右封板", $E81="抽頭",$E81="踢腳板",$E81="補板",$E81="木滑門" ), "AA", "" ) | M81: =IFERROR(VLOOKUP(L81,色號!A:B,2,FALSE),"") | N81: =IFERROR(VLOOKUP(M81,色號!B:C,2,FALSE),"") | O81: =IFERROR(VLOOKUP(L81,色號!A:D,4,FALSE),"") | P81: =IF( OR($E81="左門板", $E81="右門板"), "鉸" & IF($F81<=1000, 2, IF($F81<=1800, 3, 4)), IF( $E81="入柱背板", "側", IF( $E81="外蓋背板", "面", IF( AND(COUNTIF($E$52:$E$81,"入柱背板")>0, OR($E81="頂板", $E81="底板")), "面", IF( AND(COUNTIF($E$52:$E$81,"外蓋背板")>0, OR($E81="左側板", $E81="右側板")), "側", IF( AND( COUNTIF($E$52:$E$81,"入柱背板")=0, COUNTIF($E$52:$E$81,"外蓋背板")=0, OR( AND(COUNTIF($E$52:$E$81,"背板")>0, OR($E81="左側板",$E81="右側板",$E81="頂板",$E81="底板",$E81="天地蓋左側板",$E81="天地蓋右側板",$E81="天地蓋頂板",$E81="天地蓋底板")), AND(COUNTIF($E$52:$E$81,"抽底")>0, OR($E81="右抽牆",$E81="左抽牆",$E81="前抽牆",$E81="後抽牆")) ) ), "背板溝", "" ) ) ) ) ) ) | Q81: =IF(OR($E81="天地蓋右側板",$E81="天地蓋左側板"), "側 面", IF(OR($E81="背拉桿",$E81="中立板",$E81="頂板",$E81="底板",$E81="前抽牆",$E81="後抽牆",$E81="內左側落板",$E81="內右側落板",$E81="抽屜拉桿",$E81="立板"), "側", IF(OR($E81="木滑門",$E81="鋁框滑門"), "輪", IF(OR($E81="右側板",$E81="左側板",$E81="右抽牆",$E81="左抽牆",$E81="天地蓋頂板",$E81="天地蓋底板",$E81="內頂板"), "面", IF($E81="固隔","固","") ) ) ) ) | R81: =IF( OR($E81="左側板",$E81="右側板",$E81="天地蓋左側板",$E81="天地蓋右側板",$E81="中立板",$E81="立板"), "排","") | T81: =IF($E81="中立板","面開槽？排孔？", IF($E81="木框滑門","前排孔要退喔！", IF(OR($E81="左門板",$E81="右門板",$E81="抽頭"),"把手？", IF(OR($E81="左側板",$E81="右側板",$E81="天地蓋右側板",$E81="天地蓋左側板"),"排孔？","")))) | U81: =IF(E81="","",$L$48)
G82: =IF(OR($E82="頂板",$E82="底板",$E82="右側板",$E82="左側板",$E82="前抽牆",$E82="後抽牆",$E82="左抽牆",$E82="右抽牆",$E82="踢腳板",$E82="補板",$E82="固隔",$E82="活隔",$E82="左門板",$E82="右門板",$E82="中立板"),"AA","") | I82: =IF(OR($E82="右側板",$E82="左側板",$E82="活隔",$E82="左門板",$E82="右門板"),"AA","") | M82: =IFERROR(VLOOKUP(L82,色號!A:B,2,FALSE),"") | N82: =IFERROR(VLOOKUP(M82,色號!B:C,2,FALSE),"") | O82: =IFERROR(VLOOKUP(L82,色號!A:D,4,FALSE),"") | Q82: =IF( OR($E82="背拉桿",$E82="中立板",$E82="頂板",$E82="底板",$E82="前抽牆",$E82="後抽牆",$E82="天地蓋右側板",$E82="天地蓋左側板"), "側", IF( OR($E82="木滑門",$E82="鋁框滑門"), "輪", IF( OR($E82="右側板",$E82="左側板",$E82="右抽牆",$E82="左抽牆",$E82="天地蓋頂板",$E82="天地蓋底板"), "面", IF($E82="固隔","固","") ) )) | R82: =IF( OR($E82="左側板",$E82="右側板",$E82="天地蓋左側板",$E82="天地蓋右側板"), "排","")
A84: 櫃體名稱 | D84: {=_xlfn.IFS(OR(C84="水槽櫃",C84="爐檯櫃"),"無頂板",C84="油機吊櫃","無底板",TRUE,0)} -> 0
A85: 櫃號 | C85: =C46+1 -> 3 | K85: 板材片數： | L85: =SUMIF(D91:D120,"<>*五金",K91:K120) -> 0
A86: 櫃高 | K86: 板材才數： | L86: =板材才數分析.!P91 -> 0
A87: 櫃深 | D87: 不含門 | K87: 批次： | L87: 1
A88: 櫃寬
A89: 櫃名 | C89: 專案 | D89: 類別 | E89: 板材名稱 | F89: 開板尺寸 | K89: 生產 數量 | L89: 板材 色號 | M89: 色號 名稱 | N89: 板商 | O89: 封邊 色號 | P89: 備註 | Q89: 備註 | R89: 備註 | S89: 備註 | T89: 提醒 | U89: 批次
F90: 長(同紋) | G90: 封邊 | H90: 寬 | I90: 封邊 | J90: 厚
A91: =$C$84 -> 0 | C91: =(C85*1000)+1 -> 3001 | D91: 桶身 | E91: 頂板 | F91: =C88-36 -> -36 | G91: =IF( OR( $E91="頂板",$E91="底板",$E91="右側板",$E91="左側板", $E91="天地蓋頂板",$E91="天地蓋底板",$E91="天地蓋右側板",$E91="天地蓋左側板", $E91="前抽牆",$E91="後抽牆",$E91="左抽牆",$E91="右抽牆", $E91="踢腳板",$E91="補板",$E91="固隔",$E91="活隔", $E91="中立板",$E91="中立板(退)",$E91="固隔(退)",$E91="活固隔",$E91="立板", $E91="內頂板",$E91="內左側落板",$E91="內右側落板",$E91="內底板", $E91="內左側板",$E91="內右側板", $E91="上前平肢",$E91="上後平肢",$E91="上前立肢",$E91="上後立肢", $E91="下前立肢",$E91="下後立肢",$E91="下前平肢",$E91="下後平肢", $E91="左側落板",$E91="右側落板", $E91="外蓋背板",$E91="台面",$E91="床板",$E91="假門板", $E91="上掀門板",$E91="平掀門板",$E91="下掀門板", $E91="左門板",$E91="右門板", $E91="抽盤",$E91="抽盤抽頭", $E91="上軌道板",$E91="下軌道板",$E91="左軌道板",$E91="右軌道板",$E91="指縫擋板",$E91="左木框滑門",$E91="右木框滑門", $E91="層板",$E91="壁面層板",$E91="桌板",$E91="上封板",$E91="下封板",$E91="左封板",$E91="右封板", $E91="左圓角側板",$E91="右圓角側板",$E91="抽頭",$E91="入柱抽頭",$E91="假抽頭",$E91="背拉桿",$E91="木滑門",$E91="抽屜拉桿" ), "AA", "" ) -> AA | H91: =C87 -> 0 | I91: =IF( OR( $E91="右側板",$E91="左側板",$E91="活隔", $E91="天地蓋頂板",$E91="天地蓋底板", $E91="左門板",$E91="右門板", $E91="左側落板",$E91="右側落板", $E91="外蓋背板",$E91="活固隔", $E91="左木框滑門",$E91="右木框滑門", $E91="左鋁框滑門",$E91="右鋁框滑門", $E91="桌板",$E91="台面",$E91="床板",$E91="假門板", $E91="上掀門板",$E91="平掀門板",$E91="下掀門板", $E91="抽盤抽頭",$E91="抽盤",$E91="層板",$E91="壁面層板", $E91="上封板",$E91="下封板",$E91="左封板",$E91="右封板", $E91="抽頭",$E91="踢腳板",$E91="補板",$E91="木滑門" ), "AA", "" ) | J91: 18 | M91: =IFERROR(VLOOKUP(L91,色號!A:B,2,FALSE),"") | N91: =IFERROR(VLOOKUP(M91,色號!B:C,2,FALSE),"") | O91: =IFERROR(VLOOKUP(L91,色號!A:D,4,FALSE),"") | P91: =IF( OR($E91="左門板", $E91="右門板"), "鉸" & IF($F91<=1000, 2, IF($F91<=1800, 3, 4)), IF( $E91="入柱背板", "側", IF( $E91="外蓋背板", "面", IF( AND(COUNTIF($E$91:$E$120,"入柱背板")>0, OR($E91="頂板", $E91="底板")), "面", IF( AND(COUNTIF($E$91:$E$120,"外蓋背板")>0, OR($E91="左側板", $E91="右側板")), "側", IF( AND( COUNTIF($E$91:$E$120,"入柱背板")=0, COUNTIF($E$91:$E$120,"外蓋背板")=0, OR( AND(COUNTIF($E$91:$E$120,"背板")>0, OR($E91="左側板",$E91="右側板",$E91="頂板",$E91="底板",$E91="天地蓋左側板",$E91="天地蓋右側板",$E91="天地蓋頂板",$E91="天地蓋底板")), AND(COUNTIF($E$91:$E$120,"抽底")>0, OR($E91="右抽牆",$E91="左抽牆",$E91="前抽牆",$E91="後抽牆")) ) ), "背板溝", "" ) ) ) ) ) ) -> 背板溝 | Q91: =IF(OR($E91="天地蓋右側板",$E91="天地蓋左側板"), "側 面", IF(OR($E91="背拉桿",$E91="中立板",$E91="頂板",$E91="底板",$E91="前抽牆",$E91="後抽牆",$E91="內左側落板",$E91="內右側落板",$E91="抽屜拉桿",$E91="立板"), "側", IF(OR($E91="木滑門",$E91="鋁框滑門"), "輪", IF(OR($E91="右側板",$E91="左側板",$E91="右抽牆",$E91="左抽牆",$E91="天地蓋頂板",$E91="天地蓋底板",$E91="內頂板"), "面", IF($E91="固隔","固","") ) ) ) ) -> 側 | R91: =IF( OR($E91="左側板",$E91="右側板",$E91="天地蓋左側板",$E91="天地蓋右側板",$E91="中立板",$E91="立板"), "排","") | T91: =IF($E91="中立板","面開槽？排孔？", IF($E91="木框滑門","前排孔要退喔！", IF(OR($E91="左門板",$E91="右門板",$E91="抽頭"),"把手？", IF(OR($E91="左側板",$E91="右側板",$E91="天地蓋右側板",$E91="天地蓋左側板"),"排孔？","")))) | U91: =IF(E91="","",$L$87) -> 1
A92: =$C$84 -> 0 | C92: =C91+1 -> 3002 | D92: 桶身 | E92: 底板 | F92: =C88-36 -> -36 | G92: =IF( OR( $E92="頂板",$E92="底板",$E92="右側板",$E92="左側板", $E92="天地蓋頂板",$E92="天地蓋底板",$E92="天地蓋右側板",$E92="天地蓋左側板", $E92="前抽牆",$E92="後抽牆",$E92="左抽牆",$E92="右抽牆", $E92="踢腳板",$E92="補板",$E92="固隔",$E92="活隔", $E92="中立板",$E92="中立板(退)",$E92="固隔(退)",$E92="活固隔",$E92="立板", $E92="內頂板",$E92="內左側落板",$E92="內右側落板",$E92="內底板", $E92="內左側板",$E92="內右側板", $E92="上前平肢",$E92="上後平肢",$E92="上前立肢",$E92="上後立肢", $E92="下前立肢",$E92="下後立肢",$E92="下前平肢",$E92="下後平肢", $E92="左側落板",$E92="右側落板", $E92="外蓋背板",$E92="台面",$E92="床板",$E92="假門板", $E92="上掀門板",$E92="平掀門板",$E92="下掀門板", $E92="左門板",$E92="右門板", $E92="抽盤",$E92="抽盤抽頭", $E92="上軌道板",$E92="下軌道板",$E92="左軌道板",$E92="右軌道板",$E92="指縫擋板",$E92="左木框滑門",$E92="右木框滑門", $E92="層板",$E92="壁面層板",$E92="桌板",$E92="上封板",$E92="下封板",$E92="左封板",$E92="右封板", $E92="左圓角側板",$E92="右圓角側板",$E92="抽頭",$E92="入柱抽頭",$E92="假抽頭",$E92="背拉桿",$E92="木滑門",$E92="抽屜拉桿" ), "AA", "" ) -> AA | H92: =C87 -> 0 | I92: =IF( OR( $E92="右側板",$E92="左側板",$E92="活隔", $E92="天地蓋頂板",$E92="天地蓋底板", $E92="左門板",$E92="右門板", $E92="左側落板",$E92="右側落板", $E92="外蓋背板",$E92="活固隔", $E92="左木框滑門",$E92="右木框滑門", $E92="左鋁框滑門",$E92="右鋁框滑門", $E92="桌板",$E92="台面",$E92="床板",$E92="假門板", $E92="上掀門板",$E92="平掀門板",$E92="下掀門板", $E92="抽盤抽頭",$E92="抽盤",$E92="層板",$E92="壁面層板", $E92="上封板",$E92="下封板",$E92="左封板",$E92="右封板", $E92="抽頭",$E92="踢腳板",$E92="補板",$E92="木滑門" ), "AA", "" ) | J92: 18 | M92: =IFERROR(VLOOKUP(L92,色號!A:B,2,FALSE),"") | N92: =IFERROR(VLOOKUP(M92,色號!B:C,2,FALSE),"") | O92: =IFERROR(VLOOKUP(L92,色號!A:D,4,FALSE),"") | P92: =IF( OR($E92="左門板", $E92="右門板"), "鉸" & IF($F92<=1000, 2, IF($F92<=1800, 3, 4)), IF( $E92="入柱背板", "側", IF( $E92="外蓋背板", "面", IF( AND(COUNTIF($E$91:$E$120,"入柱背板")>0, OR($E92="頂板", $E92="底板")), "面", IF( AND(COUNTIF($E$91:$E$120,"外蓋背板")>0, OR($E92="左側板", $E92="右側板")), "側", IF( AND( COUNTIF($E$91:$E$120,"入柱背板")=0, COUNTIF($E$91:$E$120,"外蓋背板")=0, OR( AND(COUNTIF($E$91:$E$120,"背板")>0, OR($E92="左側板",$E92="右側板",$E92="頂板",$E92="底板",$E92="天地蓋左側板",$E92="天地蓋右側板",$E92="天地蓋頂板",$E92="天地蓋底板")), AND(COUNTIF($E$91:$E$120,"抽底")>0, OR($E92="右抽牆",$E92="左抽牆",$E92="前抽牆",$E92="後抽牆")) ) ), "背板溝", "" ) ) ) ) ) ) -> 背板溝 | Q92: =IF(OR($E92="天地蓋右側板",$E92="天地蓋左側板"), "側 面", IF(OR($E92="背拉桿",$E92="中立板",$E92="頂板",$E92="底板",$E92="前抽牆",$E92="後抽牆",$E92="內左側落板",$E92="內右側落板",$E92="抽屜拉桿",$E92="立板"), "側", IF(OR($E92="木滑門",$E92="鋁框滑門"), "輪", IF(OR($E92="右側板",$E92="左側板",$E92="右抽牆",$E92="左抽牆",$E92="天地蓋頂板",$E92="天地蓋底板",$E92="內頂板"), "面", IF($E92="固隔","固","") ) ) ) ) -> 側 | R92: =IF( OR($E92="左側板",$E92="右側板",$E92="天地蓋左側板",$E92="天地蓋右側板",$E92="中立板",$E92="立板"), "排","") | T92: =IF($E92="中立板","面開槽？排孔？", IF($E92="木框滑門","前排孔要退喔！", IF(OR($E92="左門板",$E92="右門板",$E92="抽頭"),"把手？", IF(OR($E92="左側板",$E92="右側板",$E92="天地蓋右側板",$E92="天地蓋左側板"),"排孔？","")))) | U92: =IF(E92="","",$L$87) -> 1
